Workbook
Name _Hlk91669107: 'REPRESENTACIÓN JUDICIAL DADEP'!$N$109
Name NativeTimeline_Data.FECHA_DE_PRESENTACION_DE_DEMANDA: #N/A

Sheet INFORME
B1: Representaciones Judiciales
C5: =Tablas!C2 -> 428 | AD5: =SUM(Consolidado!$J:$J) -> 3107916.2
C11: =Tablas!C3 -> 5
C17: =Tablas!C4 -> 1
C23: =Tablas!C5 -> 160
C29: =Tablas!C6 -> 127
C35: =Tablas!C7 -> 54
C41: =Tablas!C8 -> 81

Sheet Consolidado
A1: Name | B1: Data.ID | C1: Data.JURISDICCIÓN | D1: Data.TIPO DE PROCESO | E1: Data.FECHA DE PRESENTACION DE DEMANDA | F1: Data.ABOGADO A CARGO | G1: Data.TIPO DE REPRESENTACION DIRECTA - INDIRECTA | H1: Data.TIPO DE ZONA (CESIÓN, FISCALES, DOTACIONAL, PREDIO PÚBLICO DE NO CESIÓN, IN | I1: Data.LOCALIDAD | J1: Data.METROS CUADRADOS | K1: Data.EN CURSO - CON FALLO
A2: Tabla1 | B2: 713735 | C2: LABORAL | D2: ORDINARIO LABORAL | E2: 44267 | F2: GENARO SALAZAR GONZALEZ | G2: DIRECTA | H2: N/A | I2: SAN CRISTOBAL | J2: N/A | K2: EN CURSO
A3: Tabla1 | B3: 722198 | C3: LABORAL | D3: LABORAL | E3: 44813 | F3: GENARO SALAZAR GONZALEZ | G3: DIRECTA | H3: LABORAL | I3: CHAPINERO | J3: N/A | K3: CON FALLO
A4: Tabla1 | B4: 336186 | C4: LABORAL | D4: ORDINARIO LABORAL | E4: 40408 | F4: GENARO SALAZAR GONZALEZ | G4: DIRECTA | H4: N/A | I4: N/A | J4: NA | K4: EN CURSO
A5: Tabla1 | B5: 540276 | C5: LABORAL | D5: ORDINARIO LABORAL | E5: 42587 | F5: GENARO SALAZAR GONZALEZ | G5: DIRECTA | H5: N/A | I5: N/A | J5: NA | K5: CON FALLO
A6: Tabla1 | B6: 677535 | C6: LABORAL | D6: ORDINARIO LABORAL | E6: 43893 | F6: GENARO SALAZAR GONZALEZ | G6: DIRECTA | H6: N/A | I6: N/A | J6: N/A | K6: CON FALLO
A7: Tabla2 | B7: 16170 | C7: MASC | D7: MEDIACIÓN | E7: 45559 | F7: JOAN SEBASTIAN MARQUEZ ROJAS | G7: DIRECTA | H7: N/A | I7: N/A | J7: N/A | K7: EN CURSO
A8: Tabla3 | B8: 31038 | C8: CONSTITUCIONAL | D8: ACCION DE GRUPO | E8: 37222 | F8: MARIA FERNANDA MADIEDO SANCHEZ | G8: INDIRECTA | H8: BIENES DE USO PUBLICO | I8: SAN CRISTOBAL | J8: 10445 | K8: EN CURSO
A9: Tabla3 | B9: 167094 | C9: CONSTITUCIONAL | D9: ACCION POPULAR | E9: 37193 | F9: MARIA FERNANDA MADIEDO SANCHEZ | G9: INDIRECTA | H9: VIAS PEATONALES - VIAS VEHICULARES - ZONA VERDE - ZONA COMUNAL | I9: KENNEDY | J9: 2739 | K9: CON FALLO
A10: Tabla3 | B10: 10886 | C10: CONSTITUCIONAL | D10: ACCION POPULAR | E10: 37245 | F10: SHIRLEY AVELLANEDA PEÑA | G10: INDIRECTA | H10: RONDA - ZAMPA | I10: SUBA | J10: NA | K10: CON FALLO
A11: Tabla3 | B11: 12622 | C11: CONSTITUCIONAL | D11: ACCION POPULAR | E11: 37672 | F11: MARIA FERNANDA MADIEDO SANCHEZ | G11: INDIRECTA | H11: REMOCION EN MASA | I11: CIUDAD BOLIVAR | J11: 10465 | K11: CON FALLO
A12: Tabla3 | B12: 54949 | C12: CONSTITUCIONAL | D12: ACCION POPULAR | E12: 37930 | F12: SHIRLEY AVELLANEDA PEÑA | G12: INDIRECTA | H12: CESION | I12: SUBA | J12: 544.56 | K12: CON FALLO
A13: Tabla3 | B13: 10886 | C13: CONSTITUCIONAL | D13: ACCION POPULAR | E13: 37653 | F13: SHIRLEY AVELLANEDA PEÑA | G13: INDIRECTA | H13: BIEN DE USO PUBLICO DE NO CESION | I13: SANTAFE | J13: NA | K13: CON FALLO
A14: Tabla3 | B14: 52051 | C14: CONSTITUCIONAL | D14: ACCION POPULAR | E14: 38090 | F14: MARIA FERNANDA MADIEDO SANCHEZ | G14: INDIRECTA | H14: ZONA DE CESION | I14: KENNEDY | J14: 1516.82 | K14: CON FALLO
A15: Tabla3 | B15: 51123 | C15: CONSTITUCIONAL | D15: ACCION POPULAR | E15: 38464 | F15: MARIA FERNANDA MADIEDO SANCHEZ | G15: INDIRECTA | H15: CERRO ORIENTAL | I15: CHAPINERO | J15: NA | K15: CON FALLO
A16: Tabla3 | B16: 188832 | C16: CONSTITUCIONAL | D16: ACCION POPULAR | E16: 39020 | F16: SHIRLEY AVELLANEDA PEÑA | G16: INDIRECTA | H16: VERDE | I16: BARRIOS UNIDOS | J16: 2380.39 | K16: CON FALLO
A17: Tabla3 | B17: 167054 | C17: CONSTITUCIONAL | D17: ACCION POPULAR | E17: 38718 | F17: MARIA FERNANDA MADIEDO SANCHEZ | G17: INDIRECTA | H17: ZONA DE CESION | I17: KENNEDY | J17: 6033 | K17: CON FALLO
A18: Tabla3 | B18: 249292 | C18: CONSTITUCIONAL | D18: ACCION POPULAR | E18: 39468 | F18: MARIA FERNANDA MADIEDO SANCHEZ | G18: INDIRECTA | H18: ZONA DE CESION | I18: RAFAEL URIBE | J18: 48728.75 | K18: CON FALLO
A19: Tabla3 | B19: 266228 | C19: CONSTITUCIONAL | D19: ACCION POPULAR | E19: 39792 | F19: MAGDA BOLENA ROJAS BALLESTEROS | G19: INDIRECTA | H19: CESION - LOTE INSTITUCIONAL | I19: KENNEDY | J19: 4903 | K19: CON FALLO
A20: Tabla3 | B20: 267029 | C20: CONSTITUCIONAL | D20: ACCION POPULAR | E20: 39814 | F20: MARIA FERNANDA MADIEDO SANCHEZ | G20: INDIRECTA | H20: ZONA DE CESION | I20: KENNEDY | J20: 22321.75 | K20: CON FALLO
A21: Tabla3 | B21: 271268 | C21: CONSTITUCIONAL | D21: ACCION POPULAR | E21: 39902 | F21: SHIRLEY AVELLANEDA PEÑA | G21: INDIRECTA | H21: CESION | I21: SUBA | J21: 647000 | K21: EN CURSO
A22: Tabla3 | B22: 285457 | C22: CONSTITUCIONAL | D22: ACCION POPULAR | E22: 39814 | F22: MARIA FERNANDA MADIEDO SANCHEZ | G22: INDIRECTA | H22: VIAS - ANDENES | I22: KENNEDY | J22: 77857.53 | K22: CON FALLO
A23: Tabla3 | B23: 324636 | C23: CONSTITUCIONAL | D23: ACCION POPULAR | E23: 40395 | F23: SHIRLEY AVELLANEDA PEÑA | G23: INDIRECTA | H23: BIENES DE USO PUBLICO | I23: BOSA | J23: 131 | K23: CON FALLO
A24: Tabla3 | B24: 332456 | C24: CONSTITUCIONAL | D24: ACCION POPULAR | E24: 40458 | F24: MARIA FERNANDA MADIEDO SANCHEZ | G24: INDIRECTA | H24: VIA VEHICULAR | I24: TEUSAQUILLO | J24: 2605.63 | K24: CON FALLO
A25: Tabla3 | B25: 334871 | C25: CONSTITUCIONAL | D25: ACCION POPULAR | E25: 40499 | F25: SHIRLEY AVELLANEDA PEÑA | G25: INDIRECTA | H25: DOTACIONAL | I25: FONTIBON | J25: NA | K25: CON FALLO
A26: Tabla3 | B26: 316655 | C26: CONSTITUCIONAL | D26: ACCION POPULAR | E26: 40380 | F26: SHIRLEY AVELLANEDA PEÑA | G26: INDIRECTA | H26: CESION | I26: MARTIRES | J26: 400 | K26: CON FALLO
A27: Tabla3 | B27: 33157 | C27: CONSTITUCIONAL | D27: ACCION POPULAR | E27: 40491 | F27: MARIA FERNANDA MADIEDO SANCHEZ | G27: INDIRECTA | H27: ZONA DE CESION | I27: KENNEDY | J27: NA | K27: CON FALLO
A28: Tabla3 | B28: 352556 | C28: CONSTITUCIONAL | D28: ACCION POPULAR | E28: 40791 | F28: MARIA FERNANDA MADIEDO SANCHEZ | G28: INDIRECTA | H28: ZONA DE CESION | I28: SUBA | J28: 3.182,00 | K28: CON FALLO
A29: Tabla3 | B29: 351749 | C29: CONSTITUCIONAL | D29: ACCION POPULAR | E29: 40560 | F29: MARIA FERNANDA MADIEDO SANCHEZ | G29: INDIRECTA | H29: BIEN DE USO PUBLICO DE NO CESION | I29: KENNEDY | J29: 1311 | K29: CON FALLO
A30: Tabla3 | B30: 359511 | C30: CONSTITUCIONAL | D30: ACCION POPULAR | E30: 40777 | F30: MARIA FERNANDA MADIEDO SANCHEZ | G30: INDIRECTA | H30: BIEN DE USO PUBLICO DE NO CESION | I30: USAQUEN | J30: NA | K30: CON FALLO
A31: Tabla3 | B31: 382225 | C31: CONSTITUCIONAL | D31: ACCION DE CUMPLIMIENTO | E31: 41116 | F31: MARIA FERNANDA MADIEDO SANCHEZ | G31: INDIRECTA | H31: CESION | I31: RAFAEL URIBE | J31: NA | K31: CON FALLO
A32: Tabla3 | B32: 346341 | C32: CONSTITUCIONAL | D32: ACCION POPULAR | E32: 40556 | F32: MARIA FERNANDA MADIEDO SANCHEZ | G32: INDIRECTA | H32: CESION | I32: SUBA | J32: 1420 | K32: CON FALLO
A33: Tabla3 | B33: 430013 | C33: CONSTITUCIONAL | D33: ACCION POPULAR | E33: 41572 | F33: MARIA FERNANDA MADIEDO SANCHEZ | G33: INDIRECTA | H33: CESION | I33: CHAPINERO | J33: 880 | K33: CON FALLO
A34: Tabla3 | B34: 417192 | C34: CONSTITUCIONAL | D34: ACCION POPULAR | E34: 41337 | F34: MARIA FERNANDA MADIEDO SANCHEZ | G34: INDIRECTA | H34: CESION | I34: CHAPINERO | J34: 8061 | K34: CON FALLO
A35: Tabla3 | B35: 454500 | C35: CONSTITUCIONAL | D35: ACCION POPULAR | E35: 41753 | F35: MARIA FERNANDA MADIEDO SANCHEZ | G35: INDIRECTA | H35: BIEN DE USO PUBLICO DE NO CESION | I35: SUBA | J35: 2647.58 | K35: CON FALLO
A36: Tabla3 | B36: 493772 | C36: CONSTITUCIONAL | D36: ACCION POPULAR | E36: 42250 | F36: MARIA FERNANDA MADIEDO SANCHEZ | G36: INDIRECTA | H36: CESION | I36: SUBA | J36: NA | K36: EN CURSO
A37: Tabla3 | B37: 492279 | C37: CONSTITUCIONAL | D37: ACCION POPULAR | E37: 42116 | F37: SHIRLEY AVELLANEDA PEÑA | G37: INDIRECTA | H37: CESION | I37: ENGATIVA | J37: 600 | K37: CON FALLO
A38: Tabla3 | B38: 498496 | C38: CONSTITUCIONAL | D38: ACCION POPULAR | E38: 42118 | F38: MARIA FERNANDA MADIEDO SANCHEZ | G38: INDIRECTA | H38: ZONA DE CESION | I38: KENNEDY | J38: 5.084,00 | K38: CON FALLO
A39: Tabla3 | B39: 526651 | C39: CONSTITUCIONAL | D39: ACCION POPULAR | E39: 42444 | F39: SHIRLEY AVELLANEDA PEÑA | G39: INDIRECTA | H39: BIEN DE USO PUBLICO DE NO CESION | I39: ENGATIVA | J39: 1842 | K39: EN CURSO
A40: Tabla3 | B40: 347551 | C40: CONSTITUCIONAL | D40: ACCION POPULAR | E40: 40590 | F40: MARIA FERNANDA MADIEDO SANCHEZ | G40: INDIRECTA | H40: ZONA DE CESION | I40: USAQUEN | J40: 1730 | K40: EN CURSO
A41: Tabla3 | B41: 524062 | C41: CONSTITUCIONAL | D41: ACCION POPULAR | E41: 42412 | F41: SHIRLEY AVELLANEDA PEÑA | G41: INDIRECTA | H41: CESION | I41: RAFAEL URIBE | J41: NA | K41: EN CURSO
A42: Tabla3 | B42: 535702 | C42: CONSTITUCIONAL | D42: ACCION POPULAR | E42: 42570 | F42: SHIRLEY AVELLANEDA PEÑA | G42: INDIRECTA | H42: PRIVADOS | I42: SUBA | J42: NA | K42: EN CURSO
A43: Tabla3 | B43: 20208 | C43: CONSTITUCIONAL | D43: ACCION POPULAR | E43: 37622 | F43: SHIRLEY AVELLANEDA PEÑA | G43: INDIRECTA | H43: ESPACIO PUBLICO | I43: CANDELARIA | J43: NA | K43: EN CURSO
A44: Tabla3 | B44: 545764 | C44: CONSTITUCIONAL | D44: ACCION POPULAR | E44: 42768 | F44: SHIRLEY AVELLANEDA PEÑA | G44: INDIRECTA | H44: NA | I44: BARRIOS UNIDOS | J44: NA | K44: EN CURSO
A45: Tabla3 | B45: 545547 | C45: CONSTITUCIONAL | D45: ACCION POPULAR | E45: 42783 | F45: MAGDA BOLENA ROJAS BALLESTEROS | G45: INDIRECTA | H45: NA | I45: TEUSAQUILLO | J45: NA | K45: CON FALLO
A46: Tabla3 | B46: 557203 | C46: CONSTITUCIONAL | D46: ACCION POPULAR | E46: 42944 | F46: MARIA FERNANDA MADIEDO SANCHEZ | G46: INDIRECTA | H46: ZONA DE CESION | I46: ENGATIVA | J46: 5267.87 según Acta de Recibo Número 35 del 25 de septiembre de 1997 | K46: EN CURSO
A47: Tabla3 | B47: 552215 | C47: CONSTITUCIONAL | D47: ACCION DE GRUPO | E47: 42880 | F47: MARIA FERNANDA MADIEDO SANCHEZ | G47: INDIRECTA | H47: NA | I47: NA | J47: NA | K47: CON FALLO
A48: Tabla3 | B48: 552770 | C48: CONSTITUCIONAL | D48: ACCION POPULAR | E48: 42799 | F48: SHIRLEY AVELLANEDA PEÑA | G48: INDIRECTA | H48: NA | I48: TEUSAQUILLO | J48: NA | K48: CON FALLO
A49: Tabla3 | B49: 555753 | C49: CONSTITUCIONAL | D49: ACCION POPULAR | E49: 42909 | F49: SHIRLEY AVELLANEDA PEÑA | G49: INDIRECTA | H49: ZONA DE CESION | I49: SUBA | J49: POR COMPLETAR | K49: CON FALLO
A50: Tabla3 | B50: 671001 | C50: CONSTITUCIONAL | D50: ACCION POPULAR | E50: 44307 | F50: MARIA FERNANDA MADIEDO SANCHEZ | G50: INDIRECTA | H50: BIENES DE USO PUBLICO | I50: BARRIOS UNIDOS | J50: NA | K50: CON FALLO
A51: Tabla3 | B51: 680724 | C51: CONSTITUCIONAL | D51: ACCION POPULAR | E51: 44435 | F51: MAGDA BOLENA ROJAS BALLESTEROS | G51: INDIRECTA | H51: ZONAS DE CESION | I51: NA | J51: N/A | K51: EN CURSO
A52: Tabla3 | B52: 680477 | C52: CONSTITUCIONAL | D52: ACCION POPULAR | E52: 44433 | F52: SHIRLEY AVELLANEDA PEÑA | G52: INDIRECTA | H52: ZONA DE CESION | I52: USAQUEN | J52: N/A | K52: CON FALLO
... A61: Tabla3 | B61: 456972 | C61: CONSTITUCIONAL | D61: ACCION POPULAR | E61: 41799 | F61: SHIRLEY AVELLANEDA PEÑA | G61: INDIRECTA | H61: CESION Y OTRAS | I61: SUBA | J61: N/A | K61: CON FALLO
A62: Tabla3 | B62: 419829 | C62: CONSTITUCIONAL | D62: ACCION POPULAR | E62: 41337 | F62: MARIA FERNANDA MADIEDO SANCHEZ | G62: INDIRECTA | H62: BIENES DE USO PUBLICO | I62: KENNEDY | K62: CON FALLO
A63: Tabla3 | B63: 582434 | C63: CONSTITUCIONAL | D63: ACCION POPULAR | E63: 43357 | F63: SHIRLEY AVELLANEDA PEÑA | G63: INDIRECTA | H63: ESPACIO PUBLICO | I63: KENNEDY | J63: N/A | K63: EN CURSO
A64: Tabla3 | B64: 591702 | C64: CONSTITUCIONAL | D64: ACCION POPULAR | E64: 43510 | F64: MAGDA BOLENA ROJAS BALLESTEROS | G64: INDIRECTA | H64: ANTEJARDIN | I64: USAQUEN | J64: N/A | K64: EN CURSO
A65: Tabla3 | B65: 594447 | C65: CONSTITUCIONAL | D65: ACCION POPULAR | E65: 43543 | F65: MARIA FERNANDA MADIEDO SANCHEZ | G65: INDIRECTA | H65: N/A | I65: USAQUEN | J65: 3534.41 | K65: EN CURSO
A66: Tabla3 | B66: 576515 | C66: CONSTITUCIONAL | D66: ACCION POPULAR | E66: 43276 | F66: MARIA FERNANDA MADIEDO SANCHEZ | G66: INDIRECTA | H66: N/A | I66: TEUSAQUILLO | J66: N/A | K66: CON FALLO
A67: Tabla3 | B67: 591624 | C67: CONSTITUCIONAL | D67: ACCION POPULAR | E67: 43595 | F67: SHIRLEY AVELLANEDA PEÑA | G67: INDIRECTA | H67: ZONAS DE CESION | I67: KENNEDY | J67: N/A | K67: EN CURSO
A68: Tabla3 | B68: 601973 | C68: CONSTITUCIONAL | D68: ACCION POPULAR | E68: 43658 | F68: SHIRLEY AVELLANEDA PEÑA | G68: INDIRECTA | H68: N/A | I68: ENGATIVA | J68: N/A | K68: EN CURSO
A69: Tabla3 | B69: 602979 | C69: CONSTITUCIONAL | D69: ACCION POPULAR | E69: 43668 | F69: SHIRLEY AVELLANEDA PEÑA | G69: INDIRECTA | H69: ZONAS DE CESION | I69: SUBA | J69: N/A | K69: CON FALLO
A70: Tabla3 | B70: 613075 | C70: CONSTITUCIONAL | D70: ACCION POPULAR | E70: 43739 | F70: MAGDA BOLENA ROJAS BALLESTEROS | G70: INDIRECTA | H70: ESPACIO PUBLICO | I70: ANTONIO NARIÑO | J70: N/A | K70: EN CURSO
A71: Tabla3 | B71: 613904 | C71: CONSTITUCIONAL | D71: ACCION POPULAR | E71: 43746 | F71: SHIRLEY AVELLANEDA PEÑA | G71: INDIRECTA | H71: CESION -ZONAS VIALES | I71: ENGATIVA | J71: N/ | K71: CON FALLO
A72: Tabla3 | B72: 625110 | C72: CONSTITUCIONAL | D72: ACCION POPULAR | E72: 43857 | F72: SHIRLEY AVELLANEDA PEÑA | G72: INDIRECTA | H72: ESPACIO PUBLICO | I72: FONTIBON | J72: N/A | K72: EN CURSO
A73: Tabla3 | B73: 702817 | C73: CONSTITUCIONAL | D73: ACCION POPULAR | E73: 44705 | F73: MARIA FERNANDA MADIEDO SANCHEZ | G73: INDIRECTA | H73: BIENES DE USO PUBLICO | I73: ANTONIO NARIÑO | J73: NA | K73: EN CURSO
A74: Tabla3 | B74: 433318 | C74: CONSTITUCIONAL | D74: ACCION POPULAR | E74: 41626 | F74: MARIA FERNANDA MADIEDO SANCHEZ | G74: INDIRECTA | H74: BIENES DE USO PUBLICO | I74: SUBA | J74: NA | K74: CON FALLO
A75: Tabla3 | B75: 681092 | C75: CONSTITUCIONAL | D75: ACCION POPULAR | E75: 44236 | F75: SHIRLEY AVELLANEDA PEÑA | G75: INDIRECTA | H75: BIENES DE USO PUBLICO | I75: SUBA | J75: N/A | K75: EN CURSO
A76: Tabla3 | B76: 598792 | C76: CONSTITUCIONAL | D76: ACCION POPULAR | E76: 43609 | F76: MAGDA BOLENA ROJAS BALLESTEROS | G76: INDIRECTA | H76: N/A | I76: SUBA | J76: N/ | K76: EN CURSO
A77: Tabla3 | B77: 598870 | C77: CONSTITUCIONAL | D77: ACCION POPULAR | E77: 43612 | F77: MAGDA BOLENA ROJAS BALLESTEROS | G77: INDIRECTA | H77: BIENES DE USO PUBLICO | I77: PUENTE ARANDA | J77: N/A | K77: CON FALLO
A78: Tabla3 | B78: 707444 | C78: CONSTITUCIONAL | D78: ACCION POPULAR | E78: 44677 | F78: SHIRLEY AVELLANEDA PEÑA | G78: INDIRECTA | H78: ZONA DE CESION | I78: KENNEDY | J78: N/A | K78: EN CURSO
A79: Tabla3 | B79: 569362 | C79: CONSTITUCIONAL | D79: ACCION POPULAR | E79: 43166 | F79: SHIRLEY AVELLANEDA PEÑA | G79: INDIRECTA | H79: ZONA DE CESIÓN | I79: USAQUEN | J79: 91560 | K79: EN CURSO
A80: Tabla3 | B80: 587856 | C80: CONSTITUCIONAL | D80: ACCION POPULAR | E80: 43431 | F80: SHIRLEY AVELLANEDA PEÑA | G80: INDIRECTA | H80: ESPACIO PUBLICO | I80: SUBA | J80: N/A | K80: EN CURSO
A81: Tabla3 | B81: 559514 | C81: CONSTITUCIONAL | D81: ACCION POPULAR | E81: 42940 | F81: SHIRLEY AVELLANEDA PEÑA | G81: INDIRECTA | H81: FISCAL | I81: SUBA | J81: NA | K81: EN CURSO
A82: Tabla3 | B82: 559514 | C82: CONSTITUCIONAL | D82: ACCION POPULAR | E82: 42940 | F82: SHIRLEY AVELLANEDA PEÑA | G82: INDIRECTA | I82: SUBA | K82: EN CURSO
A83: Tabla3 | B83: 601973 | C83: CONSTITUCIONAL | D83: ACCION POPULAR | E83: 43654 | F83: SHIRLEY AVELLANEDA PEÑA | G83: INDIRECTA | H83: ZONAS DE CESION | I83: ENGATIVA | J83: N/A
A84: Tabla3 | B84: - | C84: CONSTITUCIONAL | D84: ACCION POPULAR | E84: 44760 | F84: SHIRLEY AVELLANEDA PEÑA | G84: INDIRECTA | H84: ZONAS DE CESION | I84: USAQUEN | J84: N/A | K84: EN CURSO
A85: Tabla3 | B85: 713057 | C85: CONSTITUCIONAL | D85: ACCION DE CUMPLIMIENTO | E85: 44803 | F85: SHIRLEY AVELLANEDA PEÑA | G85: DIRECTA | H85: N/A | I85: ENGATIVA | J85: N/A | K85: EN CURSO
A86: Tabla3 | B86: 712778 | C86: CONSTITUCIONAL | D86: ACCION POPULAR | E86: 44803 | F86: MARIA FERNANDA MADIEDO SANCHEZ | G86: INDIRECTA | H86: ZONA DE CESION | I86: SUBA | J86: N/A | K86: EN CURSO
A87: Tabla3 | B87: 708755 | C87: CONSTITUCIONAL | D87: ACCION POPULAR | E87: 44736 | F87: MAGDA BOLENA ROJAS BALLESTEROS | G87: INDIRECTA | H87: N/A | I87: SUBA | J87: N/A | K87: CON FALLO
A88: Tabla3 | B88: 799523 | C88: CONSTITUCIONAL | D88: ACCION POPULAR | E88: 44951 | F88: SHIRLEY AVELLANEDA PEÑA | G88: INDIRECTA | H88: N/A | I88: RAFAEL URIBE | J88: N/A | K88: EN CURSO
A89: Tabla3 | B89: 750444 | C89: CONSTITUCIONAL | D89: ACCION POPULAR | E89: 45092 | F89: MARIA FERNANDA MADIEDO SANCHEZ | G89: INDIRECTA | H89: PREDIO PUBLICO NO CESION | I89: ENGATIVA | J89: N/A | K89: EN CURSO
A90: Tabla3 | B90: 765931 | C90: CONSTITUCIONAL | D90: ACCION POPULAR | E90: 45029 | F90: MAGDA BOLENA ROJAS BALLESTEROS | G90: INDIRECTA | H90: ZONA DE CESION | I90: KENNEDY | J90: N/A | K90: EN CURSO
A91: Tabla3 | B91: 770042 | C91: CONSTITUCIONAL | D91: ACCION POPULAR | E91: 45212 | F91: MAGDA BOLENA ROJAS BALLESTEROS | G91: INDIRECTA | H91: ESPACIO PUBLICO | I91: SANTAFE | J91: N/A | K91: EN CURSO
A92: Tabla3 | B92: 774718 | C92: CONSTITUCIONAL | D92: ACCION POPULAR | E92: 45056 | F92: MARIA FERNANDA MADIEDO SANCHEZ | G92: INDIRECTA | H92: BIENES DE USO PUBLICO | I92: KENNEDY | J92: N/A | K92: EN CURSO
A93: Tabla3 | B93: - | C93: CONSTITUCIONAL | D93: ACCION POPULAR | E93: 45250 | F93: MAGDA BOLENA ROJAS BALLESTEROS | G93: INDIRECTA | H93: USO PÚBLICO DE CESIÓN | I93: FONTIBON | K93: EN CURSO
A94: Tabla3 | B94: 778590 | C94: CONSTITUCIONAL | D94: ACCION POPULAR | E94: 45257 | F94: SHIRLEY AVELLANEDA PEÑA | G94: INDIRECTA | H94: ESPACIO PUBLICO | I94: SANTAFE | J94: N/A | K94: EN CURSO
A95: Tabla3 | B95: 774679 | C95: CONSTITUCIONAL | D95: ACCION POPULAR | E95: 45212 | F95: MARIA FERNANDA MADIEDO SANCHEZ | G95: INDIRECTA | H95: N/A | I95: TEUSAQUILLO | J95: N/A | K95: CURSO
A96: Tabla3 | B96: 751037 | C96: CONSTITUCIONAL | D96: ACCION POPULAR | E96: 45053 | F96: SHIRLEY AVELLANEDA PEÑA | G96: INDIRECTA | H96: N/A | I96: BOSA | J96: N/A | K96: EN CURSO
A97: Tabla3 | B97: 783984 | C97: CONSTITUCIONAL | D97: ACCION POPULAR | E97: 45310 | F97: MARIA FERNANDA MADIEDO SANCHEZ | G97: INDIRECTA | H97: ZONAS VIALES | I97: SUBA | J97: N/A | K97: EN CURSO
A98: Tabla3 | B98: 744883 | C98: CONSTITUCIONAL | D98: ACCION POPULAR | E98: 45076 | F98: SHIRLEY AVELLANEDA PEÑA | G98: INDIRECTA | H98: N/A | I98: BOSA | J98: N/A | K98: EN CURSO
A99: Tabla3 | B99: 782777 | C99: CONSTITUCIONAL | D99: ACCION POPULAR | E99: 45253 | F99: MARIA FERNANDA MADIEDO SANCHEZ | G99: INDIRECTA | H99: ZONA DE CESION | I99: MARTIRES | J99: N/A | K99: EN CURSO
A100: Tabla3 | B100: 788115 | C100: CONSTITUCIONAL | D100: ACCION POPULAR | E100: 45338 | F100: SHIRLEY AVELLANEDA PEÑA | G100: INDIRECTA | H100: N/A | I100: SUBA | J100: N/A | K100: EN CURSO
A101: Tabla3 | B101: 413772 | C101: CONSTITUCIONAL | D101: ACCION POPULAR | E101: 41479 | F101: SHIRLEY AVELLANEDA PEÑA | G101: INDIRECTA | H101: ZONAS DE TRANCISIÓN DE APROVECHAMIENTOS AUTORIZADOS | I101: PUENTE ARANDA | J101: N/A | K101: EN CURSO
A102: Tabla3 | B102: 680724 | C102: CONSTITUCIONAL | D102: ACCION POPULAR | E102: 44435 | F102: SHIRLEY AVELLANEDA PEÑA | G102: INDIRECTA | H102: N/A | I102: NA | J102: N/A | K102: EN CURSO
A103: Tabla3 | B103: 792914 | C103: CONSTITUCIONAL | D103: ACCION POPULAR | E103: 45294 | F103: MARIA FERNANDA MADIEDO SANCHEZ | G103: INDIRECTA | H103: ZONA DE CESION | I103: KENNEDY | J103: N/A | K103: EN CURSO
A104: Tabla3 | B104: 792838 | C104: CONSTITUCIONAL | D104: ACCION POPULAR | E104: 45371 | F104: MARIA FERNANDA MADIEDO SANCHEZ | G104: INDIRECTA | H104: PROTECCION DERECHOS COLECTIVOS CASA DE LA CULTURA DE ENGATIVA | I104: ENGATIVA | J104: N/A | K104: EN CURSO
A105: Tabla3 | B105: 799047 | C105: CONSTITUCIONAL | D105: ACCION POPULAR | E105: 45418 | F105: SHIRLEY AVELLANEDA PEÑA | G105: INDIRECTA | H105: N/A | I105: ENGATIVA | J105: N/A | K105: 2
A106: Tabla3 | B106: 770042 | C106: CONSTITUCIONAL | D106: ACCION POPULAR | E106: 45212 | F106: SHIRLEY AVELLANEDA PEÑA | G106: INDIRECTA | H106: ESPACIO PUBLICO | I106: SANTAFE | J106: N/A | K106: CON FALLO
A107: Tabla3 | B107: 804413 | C107: CONSTITUCIONAL | D107: ACCION POPULAR | E107: 45462 | F107: SHIRLEY AVELLANEDA PEÑA | G107: INDIRECTA | H107: ESPACIO PUBLICO | I107: SUBA | J107: N/A | K107: EN CURSO
A108: Tabla3 | B108: 796249 | C108: CONSTITUCIONAL | D108: ACCION POPULAR | E108: 45400 | F108: SHIRLEY AVELLANEDA PEÑA | G108: INDIRECTA | H108: BIENES DE USO PUBLICO | I108: SUBA | J108: N/A | K108: EN CURSO
...

Sheet REPRESENTACIÓN JUDICIAL DADEP
A1: ID | B1: JURISDICCIÓN | C1: PROCESO | D1: TIPO DE PROCESO | E1: FECHA DE PRESENTACION DE DEMANDA | F1: DESPACHO QUE ACTUALMENTE CONOCE EL PROCESO | G1: ABOGADO A CARGO | H1: DEMANDANTE / DENUNCIANTE | I1: DEMANDADO / DENUNCIADO (APELLIDOS - NOMBRES) | J1: TIPO DE REPRESENTACION DIRECTA - INDIRECTA | K1: DADEP DTE - DDO - INTERVINIENTE - COMITÉ - DENUNCIANTE | L1: TEMA PROCESO | M1: DELITO (PROCESOS PENALES) | N1: DESCRIPCION | O1: NOMBRE DE LA URBANIZACION | P1: PRETENSIONES DE LA DEMANDA EN DINERO (DADEP DEMANDANTE) | Q1: VALOR EFECTIVO RECAUDO (EJECUTIVO) (DADEP DEMANDANTE) | R1: TIPO DE ZONA (CESIÓN, FISCALES, DOTACIONAL, PREDIO PÚBLICO DE NO CESIÓN, INSTITUCIONAL) | S1: RUPI | T1: LOCALIDAD | U1: METROS CUADRADOS | V1: AVALUO CATASTRAL - COMERCIAL PREDIO | W1: % DE LA CUOTA PARTE DEL DADEP (DIVISORIOS) | X1: CONDENAS O INDEMNIZACIONES QUE EN SENTENCIA EVITARÍA LA ENTIDAD EN METROS CUADRADOS | Y1: CONDENAS O INDEMNIZACIONES QUE EN SENTENCIA EVITARÍA LA ENTIDAD EN DINERO | Z1: FECHA DE SENTENCIA EN PRIMERA INSTANCIA | AA1: FECHA DE SENTENCIA EN SEGUNDA INSTANCIA | AB1: ORDENES AL DADEP EN SENTENCIA DEFINITIVA | AC1: ACCIONES A SEGUIR | AD1: EN CURSO - CON FALLO | AE1: AREA RESPONSABLE DEL CUMPLIMIENTO | AF1: ETAPA PROCESAL | AJ1: Datos Totales
A2: 432213 | B2: CONTENCIOSO ADMINISTRATIVA | C2: 2013-02688(TRIB) - 2015-00087 (CE) 11001032400020150008700 | D2: NULIDAD SIMPLE | E2: 41598 | F2: CONSEJO DE ESTADO - SECCION PRIMERA | G2: JOAN SEBASTIAN MARQUEZ ROJAS | H2: DADEP | I2: SUPERINTENDENCIA DE NOTARIADO Y REGISTRO | J2: DIRECTA | K2: DEMANDADO | L2: DEMANDA RESOLUCIONES SUPERNOTARIADO QUE NIEGAN CIERRE DE FMI - EL CASTILLO | M2: NA | N2: DEMANDA RESOLUCIONES SUPERNOTARIADO QUE NIEGAN CIERRE DE FMI - EL CASTILLO | O2: EL CASTILLO | P2: NA | Q2: NA | R2: ZONA DE CESIÓN | S2: 381 | T2: CHAPINERO | U2: 1850 | V2: NA | W2: NA | X2: NA | Y2: NA | Z2: NA | AA2: NA | AB2: NA | AC2: FIJACIÓN DE FECHA DE AUDIENCIA INICIAL | AD2: EN CURSO | AE2: N/A | AF2: AL DESPACHO PARA FALLO | AJ2: Procesos | AK2: =(COUNTA($A:$A)+COUNTA('REPRESENTACIÓN JUDICIAL SJD'!$A:$A))-6 -> 551
A3: 164816 | B3: CIVIL | C3: 2005-01587 | D3: NULIDAD DE ESCRITURA PÚBLICA | E3: 38688 | F3: JUZGADO 72 CIVIL MUNICIPAL | G3: MARIA FERNANDA CRUZ | H3: DADEP | I3: EDGAR GARZON HERREÑO - CARLOS EDUARDO PRIETO - ELIZABETH CERON - LOS CAMPOS | J3: DIRECTA | K3: DEMANDADO | L3: NULIDAD DE EP POR OBJETO ILÍCITO | M3: NA | N3: NULIDAD DE EP POR OBJETO ILÍCITO | O3: LOS CAMPOS | P3: NA | Q3: NA | R3: ZONA DE CESIÓN | S3: 615 | T3: ENGATIVA | U3: 60 | V3: NA | W3: NA | X3: NA | Y3: NA | Z3: 41304 | AA3: NA | AB3: TRAMITAR OFICIOS ORIP Y NOTARIA | AC3: TRAMITAR LOS OFICIOS CORRESPONDIENTES | AD3: EN CURSO | AE3: N/A | AF3: SE PRESENTÓ PROCESO EJCUTIVO PARA COBRO DE COSTAS.SE DECRETA MEDIDAS CAUTELARES. | AJ3: Accion Popular | AK3: =COUNTIF($D:$D,"ACCION POPULAR")+COUNTIF('REPRESENTACIÓN JUDICIAL SJD'!$A:$AF,"ACCION POPULAR") -> 252
A4: 715785 | B4: PENAL | C4: 2022-17968 | D4: PENAL | E4: 44568 | F4: FISCALIA 136 INTERVENCIÓN TEMPRANA | G4: JOSE AGUSTÍN AVENDAÑO | H4: DADEP | I4: CONTEXTUS | J4: DIRECTA | K4: DENUNCIANTE | L4: Denuncia a Contextus SAS por conservar el bien antes entregado en contrato CAMEP | M4: ENRIQUECIMIENTO ILÍCITO DE PARTICUALRES - USURPACIÓN DE FUNCIONES PÚBLICAS - ACCESO ABUSIVO A SISTEMA INFORMÁTICO | N4: ARCHIVO PARCIAL DEL DELITO DE ACCESO ABUSIVO A SIST. INFORMÁTICO + AMPLIACIÓN DE DENUNCIA POR EL RESTO DE DELITOS- CORREO DE IMPULSO 26.09.22 Y SOLICITUD DE ACLARACIÓN DEL ARCHIVO DE AMPLIACIÓN DE DENUNCIA | O4: PARQUEADERO CENTRO COMERCIAL LA CASTELLANA | P4: N/A | Q4: N/A | R4: ZONA DE CESIÓN | S4: 4028 | T4: USAQUEN | U4: N/A | V4: N/A | W4: N/A | X4: N/A | Y4: N/A | AA4: N/A | AB4: N/A | AC4: REVISION DE SOLICITUD DE DESARCHIVO | AD4: EN CURSO | AE4: N/A | AF4: ARCHIVADO
A5: 352796 | B5: CIVIL | C5: 1990-01429 | D5: RESTITUCION DE INMUEBLE ARRENDADO | E5: 33120 | F5: JUZGADO 46 - CIVIL DEL CIRCUITO | G5: JAMMER SAUL HERNANDEZ | H5: SEC GRAL | I5: JULIO ROBERTO SILVA RUIZ Y OTRO | J5: DIRECTA | K5: INTERVINIENTE | L5: RESTITUIR BIEN FISCAL CALLE 12 5 63 | M5: NA | N5: RESTITUIR BIEN FISCAL CALLE 12 5 63 | O5: NA | P5: NA | Q5: NA | R5: BIEN FISCAL | S5: 2-518 | T5: CANDELARIA | U5: 555.5 | V5: NA | W5: NA | X5: NA | Y5: NA | Z5: NA | AA5: NA | AB5: NA | AC5: EN FECHA 30-05-2023 SE EMITE SENTENCIA FAVORABLE DE PRIMERA INSTANCIA TERMINANDO EL CONTRATO DE ARRENDAMIENTO Y ORDENANDO SU RESTITUCIÓN, SE PRESENTA RECURSO DE APLEACIÓN QUE ES RESUELTO DE MANERA FAVORABLE AL DADEP EN FECHA 22-08-2023. DESPACHO COMISORIO EN LA ALCALDIA LOCAL DE SAN CRISTÓBAL FIJA FECHA PARA ENTREGA EL 28-10-2024 | AD5: CON FALLO | AE5: N/A | AF5: SENTENCIA DE PRIMERA Y SEGUNDA INSTANCIA DEBIDAMENTE EJECUTORIADA. PENDIENTE POR DILIGENCIA DE ENTREGA DEL PREDIO POSTERIOR A LA COMISIÓN.
A6: 543680 | B6: CONSTITUCIONAL | C6: 2016-00748 | D6: ACCION POPULAR | E6: 42751 | F6: JUZGADO 50 ADMINISTRATIVO SECCION SEGUNDA DE BOGOTÁ | G6: SHIRLEY AVELLANEDA PEÑA | H6: CONJUNTO AVENIDA PARQUE PROPIEDAD HORIZONTAL | I6: ALCALDIA LOCAL DE TEUSAQUILLO, ALCALDIA MAYOR DE BOGOTÁ, DADEP Y SECRETARIA DE MOVILIDAD | J6: DIRECTA | K6: DEMANDADO | L6: OCUPACION DE ESPACIO PÚBLICO | M6: N/A | N6: SOLICITA ORDENAR A LOS DEMANDADOS EJECUTAR LAS ACCIONES TENDIENTES CON EL FIN DE EVITAR EL DAÑO CONTINGENTE Y HACER CESAR EL PELIGRO, LAS AMENAZAS Y AGRAVIO SOBRE LOS DERECHOS E INTERESES COLECTIVOS DEL GOCE DEL ESPACIO PUBLICO | O6: N/A | P6: N/A | Q6: N/A | R6: OCUPACION DE BIEN DE USO PUBLICO | S6: POR DEFINIR | T6: TEUSAQUILLO | U6: N/A | V6: N/A | W6: N/A | X6: N/A | Y6: N/A | Z6: N/A | AA6: N/A | AB6: N/A | AC6: 2017-01-30 CONTESTACIÓN DE LA DEMANDA.- 2017-02-14 AUTO QUE FIJA FECHA PARA PACTO DE CUMPLIMIENTO.- 2017-02-27 AUDIENCIA DE CONCILIACIÓN FALLIDA.- 2017-03-08 AUTO QUE DECRETA PRUEBAS.- 2017-03-23 TRASLADO ALEGATOS DE CONCLUSIÓN 1ª INSTANCIA.- 2017-03-29 PRESENTACIÓN DE ALEGATOS.- 2017-06-13 COMUNICACIÓN DE LA SENTENCIA Fallo Desfavorable 1a Instancia. "Se protege el derecho colectivo al goce del espacio público y utilización y defensa de los bines de uso público, para lo cual la Alcaldía Mayor de Bogotá, ALcaldía Local de teusaquillo, el Departamento Administrativo de la Defensoría del Espacio Púlblico y la Secretaría de Movilidad, de una parte,por intermedio de la Policía Metropolitana de Bogotá, deberán realizar los operativos mínimo cada quince (15) días con el fín de erradicar el problema de invasión del espacio público; y de otro lado, de manera coordinada esas mismas entidades en el término máximo de seis (6) meses, contados a partir de la ejecutoria de la sentencia, adelanten y lleven a su culminación el procedimiento consagrado en el artículo 8 del decreto 098 de 2004, para la recuperación del espacio público de la zona comprendida en la Calle 24 A entre carreras 59 y 60, en la ciudad de Bogotá, ocupado indebidamente. (...).- 2017-06-21 AUTO QUE ADMITE RECURSO DE APELACION. 2017-06-21 AUTO QUE ADMITE RECURSO DE APELACION Tribunal Administrativo de Cundinamarca profiere Sentencia Desfavorable en Segunda Instancia en contra de las entidades Distritales convocadas, estableciendo en la parte resolutiva del fallo : "PRIMERO. MODIFICAR el numeral tercero y ADICIONAR la Sentencia del 13 de Junio de 2017 proferida por el Juzgado Cincuenta (50) Administrativo de Bogotá, de conformidad con lo expuesto en la parte motiva de esta providencia, la cual quedará así: "(...) TERCERO: SE PROTEGE el derecho al goce del espacio público y utilización y defensa de los bienes de uso público , para lo cual la Alcaldía Mayor de Bogotá, la Alcaldía Local de Teusaquillo, el Departamento Administrativo de la Defensoría del Espacio Público y la Secretaría de Movilidad, de una parte, por intermedio de la Policía Metropolitana de Bogotá, deberán realizar operativos mínimo cada quince (15) días, por el término inicial de cuatro (4) meses y posteriormente con una menos frecuencia, con el fin de erradicar el problema de invasión del espacio público; y de otro, de manera coordinada esas mismas entidades en el término máximo de un (1) año, contado a partir de la ejecutoria de la sentencia, adelanten y lleven a su culminación el procedimiento consagrado en el artículo 8 del decreto 098 de 2004,para la recuperación del espacio público de la zona comprendida en la Calle 24 A entre carreras 59 y 60, en la ciudad de Bogotá, ocupado indebidamente. Una vez agotado el anterior procedimiento, sino no (sic) se ha podido recuperar el espacio público invadido, el Alcalde de la Localidad de Teusaquillo en uso de sus las facultades policivas consagradas en la Ley, deberá ordenar a la Policia Metropolitana de Bogotá, para que de manera insistente pero pacífica realice todas las gestiones necesarias para garantizar su restitución inmediata. Igualmente, se ordenará a las demás demandadas Alcaldía Mayor de Bogotá, DADEP y Secretaría Distrital de Movilidad, que en el marco de sus competencias, acompañen y colaboren activamente con el procedimiento administrativo para la recuperación del espacio público en la zona objeto de esta controversia, frente a los vendedores informales, así como ante los vehículos mal parqueados,. Así mismo, que cada una de las actividades que se realicen se deberá informar por escrito a este despacho. TERCERO A : INSTAR a la Alcaldía Mayor de Bogotá, la Alcaldía Local de Teusaquillo, el DADEP y la Secretaría De Movilidad para que realicen un estudio detallado de la de la problemática de la zona, y en consecuencia adopten las medidas educativas, de transito peatonal y vehicular que se analizaron en la sentencia y den solución a la situación particular de los vendedores informales, con el fin de lograr el amparo constitucional de los derechos colectivos protegidos. (...)"."2018-11-19 INFORMES. 2018-12-17 INFORMES. - 2019-04-02 INFORMES.- 2019-05-16 INFORMES.- 2019-05-24 AUTO QUE ORDENA REQUERIR.- 2019-07-18 INFORMES.- 2019-07-19 AUTO QUE ORDENA REQUERIR.- 2019-08-13 INFORMES.- 2019-09-03 INFORMES.- 2019-09-03 INFORMES.- 2020-08-03 SEGUIMIENTO CUMPLIMIENTO SENTENCIAS.- 2020-11-11INFORMES.- 2021-08-12 INFORMES.- 2022-03-03 AUTO QUE ORDENA REQUERIR.- 2022-05-05 AUTO DE TRAMITE.- 2022-07-01 PRESENTACIÓN DE INFORMES.- 2022-10-21 AUTO QUE ORDENA REQUERIR.- 2023-12-22 INFORMES.- 2024-02-28 INFORMES.- 2024-02-28 PRESENTACIÓN DE INFORMES. 23-04-2024 SE ABSTIENE DE ABRIR INCIDENTE DE DESACATO. ABRIL 24 DE 2024 NOTIFICACION POR CORREO ELECTRONICO DEL AUTO QUE PRIMERO: DECLARA EL CUMPLIMIENTO DE LA SENTENCIA DE FECHA DEL 13 DE JUNIO DE 2017- SEGUNDO:SE ABSTIENE DE CONTINUAR CON EL TRAMITE INCIDENTAL CONFORME A LA PARTE MOTIVA DEL PRESENTE AUTO. TERCERO: CONMINAR A LA ALCALDIA MAYOR DE BOGOTA , A LA ALCALDIA LOCAL DE TEUSAQUILLO, AL DEPARTAMENTO ADMINISTRATIVO DE LA DEFENSORÍA DEL ESPACIO PÚBLICO, A LA SECRETAIA DISTRITAL DE MOVILIDAD Y A LA POLICIA METROPOLITANA DE BOGOTA, PARA QUE REALICEN LAS ACTUACIONES POLICIVAS TENDIENTES A LA PROTECCION Y RESTITUCION DEL ESPACIO PUBLICO QUE SEAN NECESARIOS PARA CONSERVAR EL GOCE Y DISFRUTE DEL ESPACIO PUBLICO EN LA ZONA DE LA CALLE 24 A ENTRE CARRERAS 59 Y 60 Y OTRAS DISPOSICIONES. | AD6: CON FALLO | AE6: SGIEP | AF6: SEGUIMIENTO CUMPLIMIENTO DE FALLO CONMINACION DEL JUEZ A SEGUIR REALIZANDO OPERATIVOS EN LA ZONA OBJETO DE ACCION POPULAR.
A7: 432549 | B7: PENAL | C7: 2008-14456 | D7: PENAL | E7: 39708 | F7: FISCALIA 119 SECCIONAL UNIDAD FE PUBLICA Y ORDEN ECONOMICO - TARDÍA ABREVIADO | G7: JOSE AGUSTÍN AVENDAÑO | H7: DADEP | I7: CARLOS ALBERTO LARA ACEVEDO | J7: DIRECTA | K7: DENUNCIANTE | L7: SUPERCENTER FALSEDAD | M7: FALSEDAD EN DOCUMENTO PUBLICO - FRAUDE PROCESAL | N7: DENUNCIADO EN REPRESENTACION DE SUPERCENTER CONSTITUYE URBANIZACION SEÑALANDO QUE LAS OBRAS YA HABIAN SIDO EJECUTADAS Y QUE SE ENCONTRABA LIBRE DE EMBARGOS, NO OBSTANTE TENIA EMBARGO DE BBVA | O7: SUPERCENTER | P7: NA | Q7: NA | R7: ZONA DE CESIÓN | S7: 1355 | T7: BARRIOS UNIDOS | U7: NA | V7: NA | W7: NA | X7: NA | Y7: NA | Z7: 22/02/2016 CONDENA A 84 MESES DE PRISION | AA7: 7-3-17 CONFIRMAR PARCIALMENTE FALLO - DECLARA PRESCRIPCIÓN DELITO FALSEDAD | AB7: NA | AC7: SEGUIMIENTO PROCESAL - SEGUIMIENTO RECURSO DE CASACIÓN- CON OFICIO 44318 SE DEVUELVEN LAS DILIGENCIAS AL TRIBUNAL DEL BOGOTA EN 5 CDNOS Y 28 CD | AD7: EN CURSO | AE7: N/A | AF7: CASACION
A8: 416638 | B8: CONTENCIOSO ADMINISTRATIVA | C8: No. 25000232400020120058100 | D8: NULIDAD SIMPLE | E8: 41438 | F8: CONSEJO DE ESTADO - SECCION PRIMERA | G8: JOAN SEBASTIAN MARQUEZ ROJAS | H8: VICTOR EDUARDO DUARTE SAAVEDRA | I8: DADEP - ALCALDIA MAYOR | J8: DIRECTA | K8: DEMANDADO | L8: NULIDAD CONTRA ACTA DE TOMA DE POSESION - ANTEJARDINES MADELENA | M8: NA | N8: NULIDAD CONTRA ACTA DE TOMA DE POSESION - ANTEJARDINES MADELENA | O8: MADELENA III Y IV SECTOR | P8: NA | Q8: NA | R8: ZONA DE CESIÓN | S8: 1481 | T8: CIUDAD BOLIVAR | U8: NA | V8: NA | W8: NA | X8: 26985 | Y8: NA | Z8: 42754 | AA8: NA | AB8: NA | AC8: SEGUIMIENTO PROCESAL - ALEGATOS PRESENTADOS - PENDIENTE FALLO CONSEJO DE ESTADO. ENTRO AL DESPACHPO PARA FALLO EL 1/04/2019 - 12-08-2022 REMITEN CONSTANCIA DEL ESTADO DEL PROCESO | AD8: EN CURSO | AE8: N/A | AF8: AL DESPACHO PARA FALLO
A9: 632501 | B9: CIVIL | C9: 2015-01376 | D9: PERTENENCIA | E9: 42331 | F9: JUZGADO 42 CIVIL MUNICIPAL DE BOGOTÁ | G9: MARIA FERNANDA CRUZ | H9: GABRIEL ROJAS HUERFANO | I9: ROBERTO RODRIGUEZ ALDANA | J9: DIRECTA | K9: INTERVINIENTE | L9: PRESCRIPCION INMUEBLE POR TENER LA POSESION POR MAS DE 10 AÑOS | M9: N/A | N9: N/A | O9: VILLA EL DORADO NORTE | P9: N/A | Q9: N/A | R9: ZONA DE CESIÓN | S9: 1533 | T9: SUBA | U9: 84,50 mts2 | V9: N/A | W9: N/A | X9: N/A | Y9: N/A | Z9: N/A | AA9: N/A | AB9: N/A | AC9: EL 1 DE OCTUBRE DE 2024, ME PRONUNCIÉ FRENTE AL RECURSO DE APELACIÓN. SIN EMBARGO, EL DESPACHO NO LO HA RESUELTO. | AD9: EN CURSO | AE9: N/A | AF9: APELACIÓN
A10: 556925 | B10: CIVIL | C10: 1988-01361 11001310302019880136100 | D10: EJECUTIVO | E10: 35796 | F10: JUZGADO 5 CIVIL DE CIRCUITO DE EJECUCIÓN DE SENTENCIAS | G10: GENARO SALAZAR GONZALEZ | H10: PILAR VANEGAS - CRISTIAN RODRIGUEZ | I10: GUILLERMO MARTINEZ - SOLEDAD RAMIREZ | J10: DIRECTA | K10: INTERVINIENTE | L10: RINCON DE LOS ANGELES - EJECUTIVO CON EL CUAL SE REMATA Y ADJUDICA PREDIO | M10: NA | N10: RINCON DE LOS ANGELES - EJECUTIVO CON EL CUAL SE REMATA Y ADJUDICA PREDIO | O10: RINCON DE LOS ANGELES | P10: NA | Q10: NA | R10: ZONA DE CESIÓN | S10: 1-4875; 1-4876 | T10: KENNEDY | U10: 2600 | V10: NA | W10: NA | X10: NA | Y10: NA | Z10: 32667 | AA10: NA | AB10: SIN ORDENES AL DADEP - DADEP INTERVIENE PARA DEFENDER BIENES DEL DISTRITO | AC10: INTERVENCIÓN - SE PRETENDE REVOCAR ACTA DE ENTREGA, EXISTE ACCION POPULAR Y NULIDAD DE ACTO ADMINISTRATIVO DE CATASTRO PENDIENTE POR RESOLVER PARA QUE CONTINUE EL TRAMITE PROCESAL. | AD10: CON FALLO | AE10: N/A | AF10: EN EJECUCIÓN - DADEP INTERVENCIÓN DEFENSA BIENES DEL DISTRITO CON OTRAS ACCIONES CONSTITUCIONALES Y JUDICIALES.
A11: 709676 | B11: CIVIL | C11: 1998-00939 | D11: PERTENENCIA | E11: 37231 | F11: JUZGADO 40 - CIVIL DEL CIRCUITO | G11: JAMMER SAUL HERNANDEZ | H11: MARIA EUGENIA MARTÍNEZ, HENRY GOMEZ RAMOS, ROSA HELENA GONZÁLEZ CUELLAR Y OTROS. | I11: PERSONAS INDETERMINADAS | J11: DIRECTA | K11: INTERVINIENTE | L11: PROCESO DE PERTENENCIA SOBRE UN PREDIO FISCAL | M11: NA | N11: NULIDAD DE LA SENTENCIA DE PERTENENCIA DE FECHA 26 DE MARZO DE 2004 | O11: NA | P11: NA | Q11: NA | R11: BIEN FISCAL | S11: 2-1250 | T11: SANTA FE | U11: 240,4 | V11: NA | W11: NA | X11: NA | Y11: NA | Z11: 26/03/2004 | AA11: NA | AB11: NA | AC11: SE PRESENTA NULIDAD DE LA SENTENCIA LA CUAL ES NEGADA EN PRIMERA Y SEGUNDA INSTANCIA | AD11: CON FALLO | AE11: SGC | AF11: CON PRONUNCIAMIENTO EN SEGUNDA INSTANCIA NEGANDO LA SOLICITUD DE NULIDAD, PROCESO ARCHIVADO, SIN ACTUACIONES PENDIENTES.
A12: 588924 | B12: CIVIL | C12: 2001-00056 | D12: EJECUTIVO | E12: 36922 | F12: JUZGADO 5 CIVIL DEL CIRCUITO DE EJECUCIÓN DE BOGOTÁ | G12: JAMMER SAUL HERNANDEZ | H12: BANCO DE BOGOTÁ S.A. | I12: LUIS EDUARDO MOSQUERA-COOPERATIVA DEL VIVIENDA DEL MAGISTERIO | J12: DIRECTA | K12: INTERVINIENTE | L12: PROCESO EJECUTIVO ENTRE PARTICULARES EN DONDE SE ORDENÓ EL EMBARGO DE LAS ZONA DE CESIÓN DE LA URABNIZACIÓN COOVIMAC LTDA | M12: N/A | N12: SE PRETENDE LEVANTAR LA MEDIDA DE EMBARGO QUE PESA SOBRE EL INMUEBLE 50C-233951 | O12: URBANIZACIÓN MULTIFAMILIAR COOVIMAC LTDA | P12: N/A | Q12: N/A | R12: ZONA DE CESIÓN | S12: 1519-1, 1519-2, 1519-3 | T12: ENGATIVA | U12: 1937,37 MTS2 | V12: N/A | W12: N/A | X12: N/A | Y12: N/A | Z12: 37369 | AA12: 37547 | AB12: N/A | AC12: EN FECHA 29 DE MARZO DE 2023, SE PROCEDE A ORDENAR LA TERMINACIÓN POR DESISTIMIENTO TÁCITO DEL PROCESO | AD12: CON FALLO | AE12: N/A | AF12: CON SENTENCIA DE PRIMERA Y SEGUNDA INSTANCIA EJECUTORIADAS EN EJECUCIÓN. CON SOLICITUD PARA CANCELAR LAS MEDIDAS CAUTELARES IMPUESTAS. SE ORDENA CANCELAR LA MEDIDA DE EMBARGO QUE PESABA SOBRE EL INMUEBLE Y SE INFORMA A LA SRI. SIN ACTUACIONES PENDIENTES.
A13: 597584 | B13: CIVIL | C13: 2019-00307 11001310300420190030700 | D13: NULIDAD DE ESCRITURA PÚBLICA | E13: 43452 | F13: JUZGADO 4 CIVIL DEL CIRCUITO DE BOGOTÁ | G13: GENARO SALAZAR GONZALEZ | H13: DADEP | I13: JOSE PABLO EMILIO YOPASA MUÑOZ | J13: DIRECTA | K13: DEMANDADO | L13: NULIDAD DE ESCRITURA PÚBLICA - DONACIÓN | M13: N/A | N13: NULIDAD DE EP POR OBJETO ILÍCITO | O13: JAVA II SECTOR | P13: N/A | Q13: N/A | R13: ZONA DE CESIÓN | S13: 1878 | T13: SUBA | U13: 19755 | V13: N/A | W13: N/A | X13: N/A | Y13: N/A | Z13: N/A | AA13: N/A | AB13: N/A | AC13: NOTIFICACIONES DE LOS DEMANDADOS HEREDEROS Y JAC BARRIO JAVA II SECTOR | AD13: EN CURSO | AE13: N/A | AF13: EL JUZGADO REQUIERE A LA PARTE DEMANDANTE PARA INFORMAR NOTIFICACION 26-09-2024
A14: 164016 | B14: CONTENCIOSO ADMINISTRATIVA | C14: 2005-01924 | D14: EJECUTIVO | E14: 38580 | F14: JUZGADO 58 ADMINISTRATIVO DEL CIRCUITO DE BOGOTÁ | G14: JAMMER SAUL HERNANDEZ | H14: DADEP | I14: FABIO ZAMORA CONTRERAS | J14: DIRECTA | K14: DEMANDADO | L14: INCUMPLIMIENTO CONTRATO ARRENDAMIENTO 004-1993 | M14: NA | N14: INCUMPLIMIENTO CONTRATO ARRENDAMIENTO 004-1993 | O14: NA | P14: 24676716 | Q14: NA | R14: BIEN DE USO PUBLICO | S14: NA | T14: TEUSAQUILLO | U14: NA | V14: NA | W14: NA | X14: NA | Y14: NA | Z14: 40855 | AA14: NA | AB14: NA | AC14: SEGUIMIENTO SECRETARÍA JURÍDICA - PROCESO DE REPRESENTACIÓN INDIRECTA | AD14: EN CURSO | AE14: N/A | AF14: ACREDITA TRAMITE EMBARGO DE CUENTAS - SEGUIMIENTO A BIENES EN CABEZA DEL DEMANDADO PARA INFORMAR AL DESPACHO
A15: 705577 | B15: PENAL | C15: 2022-69826 | D15: PENAL | E15: 44807 | F15: FISCALÍA 212 ADMÓN PÚBLICA | G15: JOSE AGUSTÍN AVENDAÑO | H15: DADEP | I15: FORJA S.A. | J15: DIRECTA | K15: DENUNCIANTE | L15: FORJA | M15: ENRIQUECIMIENTO ILÍCITO DE PARTICULARES - USURPACIÓN DE FUNCIONES | N15: A RAIZ DE LA TERMINACIÓN DE UN CONTRATO CAMEP ENTRE FORJA Y EL DADEP, EL PRIMERO NO RESTITUYÓ EL BIEN Y GENERÓ FRUTOS SOBRE EL MISMO, CONSERVANDO EL BIEN PÚBLICO PESE A LOS DIVERSAS SOLICITUDES DE RESTITUCIÓN Y ACCIONES JURÍDICAS POR PARTE DEL DADEP | O15: CHICO NORTE - NUEVA URBANIZACIÓN SANTA BARBARA II SECTOR II ETAPA CENTRO COMERCIAL | P15: N/A | Q15: N/A | R15: N/A | S15: 2545 | T15: USAQUEN | U15: N/A | V15: N/A | W15: N/A | X15: N/A | Y15: N/A | Z15: N/A | AA15: N/A | AB15: N/A | AC15: Transcurrido el mes que el despacho menciono, se asiste al mismo el dia 14/05/24 donde el fiscal indica que se encuentra en estudio el caso e indica volver dentro del mes siguiente. | AD15: EN CURSO | AE15: N/A | AF15: INDAGACIÓN
A16: 163864 | B16: CONTENCIOSO ADMINISTRATIVA | C16: 2005-01928 | D16: EJECUTIVO | E16: 38502 | F16: TRIBUNAL CONTENCIOSO ADMINISTRATIVO DE CUNDINAMARCA - SECCIÓN TERCERA | G16: MARIA FERNANDA CRUZ | H16: DADEP | I16: LUZ MARINA ARROYAVE DE RAMIREZ | J16: DIRECTA | K16: DEMANDADO | L16: INCUMPLIMIENTO CONTRATO ARRENDAMIENTO 0011-1993 | M16: NA | N16: INCUMPLIMIENTO CONTRATO ARRENDAMIENTO 0011-1993 | O16: NA | P16: 26976535 | Q16: NA | R16: BIEN FISCAL | S16: 2-440 | T16: SANTAFE | U16: NA | V16: NA | W16: NA | X16: NA | Y16: NA | Z16: 38827 | AA16: NA | AB16: NA | AC16: INFORMAR QUE BIENES SE ENCUENTRAN EN CABEZA DE LA DEMANDADA. A LA FECHA NO ME HAN RECONCIDO PERSONERÍA JURÍDICA | AD16: CON FALLO | AE16: N/A | AF16: SENTENCIA Y SE ESTA TRAMITANDO DE OBTENCION DEL DINERO ADEUDADO CON MEDIDAS CAUTALES
A17: 563426 | B17: CONSTITUCIONAL | C17: 2017-00693 | D17: ACCION POPULAR | E17: 43039 | F17: JUZGADO 13 CIVIL DEL CIRCUITO | G17: MAGDA BOLENA ROJAS BALLESTEROS | H17: DADEP | I17: INVERSIONES ALCABAMA S.A., INVERSIONES DIPRECA S.A. | J17: DIRECTA | K17: DEMANDADO | L17: ENTREGA DE ZONAS CE CESIÓN | M17: NA | N17: ENTREGUE, FORMAL Y MATERIALMENTE, ESCRITURE Y DOTE LAS ZONAS DE CESION NGRATUITAS A FAVOR DEL DISTRITO CAPITAL DE LA URBANIZACIÓN CAMINO VERDE | O17: LAS FLORES | P17: N/A | Q17: N/A | R17: ZONA DE CESIÓN | S17: 3167-3168 | T17: SUBA | V17: N/A | W17: N/A | X17: N/A | Y17: N/A | Z17: N/A | AA17: N/A | AB17: N/A | AC17: 2022-06-21 Se fija fecha para la celebración de audiencia de pacto para el 17 de agosto de 2022 a las 10:00AM 2022-08-17 Previo al inicio de la audiencia: 1. Se desiste de la solicitud de vinculación de máximo Beltrán RodrÍguez 2. Se desiste de la solicitud de desvinculación de Luis Hernán Noguera Garzón. 3. El juez resuelve aplazar la audiecia debido a la inasistencia de Luis Hernán Noguera Garzón y en atención al avance en el cumpimiento de la sociedad Alcabama S.A., quienes afirman haber suspendido el avance con ocasión de un oficio enviado por SRI por el cual la UAESP manifestó no darle continuidad al trámite. 4. Se acordó aclararle a la UAESP que podían continuar con el trámite y adelantar una mesa de trabajo con los urbanizadores para conocer los avances. 2022-09-16 Se adelanta mesa de trabajo con INVERSIONES ALCABAMA S.A., IDU, UAESP, IDRD y el JBJCM para conocer los avances. En desarrollo de la reunión se aclaró la inexistencia de impedimento alguno que obstaculizara continuar con el trámite de entrega ante la UAESP. 2022-09-28 Se envía oficio a la UAESP acalarando la inexistencia de impedimento alguno que obstaculizara continuar con el trámite de entrega ante la UAESP.2023-07-06 pendiente de aceptación de poder. 25/08/23. Se notificó por estado auto que ordenó requerir a la parte actora 3. El juez resuelve aplazar la audiecia debido a la inasistencia de Luis Hernán Noguera Garzón y en atención al avance en el cumpimiento de la sociedad Alcabama S.A., quienes afirman haber suspendido el avance con ocasión de un oficio enviado por SRI por el cual la UAESP manifestó no darle continuidad al trámite. 4. Se acordó aclararle a la UAESP que podían continuar con el trámite y adelantar una mesa de trabajo con los urbanizadores para conocer los avances. 2022-09-16 Se adelanta mesa de trabajo con INVERSIONES ALCABAMA S.A., IDU, UAESP, IDRD y el JBJCM para conocer los avances. En desarrollo de la reunión se aclaró la inexistencia de impedimento alguno que obstaculizara continuar con el trámite de entrega ante la UAESP. 2022-09-28 Se envía oficio a la UAESP acalarando la inexistencia de impedimento alguno que obstaculizara continuar con el trámite de entrega ante la UAESP. 2023-07-06 pendiente de aceptación de poder. 25/08/23. Se notificó por estado auto que requirió al DADEP para allegar comprobantes de notificación de la vinculación a la AP de la UAESP. 28/08/23. Se remite al despacho cumplimiento de la orden del auto del 25 de agosto de 2023. 12/09/2023. Contestación de la demanda. 25/10/2023. Traslado contestación de la demanda por el término de 5 días. 14/11/2023. Al Despacho. 31/01/2024. Se notificó por estado auto que citó a audiencia de pacto para el 13/03/24 a las 02:00 pm. 08/02/24. Con memorando 20241300012213 se solicitó a la SRI información sobre el estado actual de las zonas de cesión para efectos de la audiencia de pacto de cumplimiento (pendiente respuesta - fecha límite 26 de febrero de 2024). 14/02/2024. Memorando 20242010012973 de la SRI informando el estado actual de las áreas de cesión. 28/02/2024. Se radicó solicitud de nulidad. 29/02/2024. Al Despacho solicitud de nulidad. Pendiente de pronunciamiento despacho.04-08-2024 interposición de recurso contra auto que rechaza nulidad interpuesto por ENEL. fija diligencia de paxcto para el 23 de julio de 2024 auto de fecha 19 marzo de 2024. auto de fecha 12 abril de 2024 Traslado Art. 326 Inciso 1° C.G.P.. 29/04/2024. Se notificó por estado auto que resolvió negar el recurso de apelación. 23/07/2024. Se asistió a la audiencia de pacto la cual fue reprogramada para el 29/07/24 a las 09:00 am, teniendo en cuenta los inconvenientes del juez para conectarse a la misma. 29/07/2024. Se llevó a cabo la audiencia de pacto, no obstante la misma fue suspendida con el fin de otorgar tiempo suficiente a las partes para que lleguen a un acuerdo teniendo en cuenta los avances en el trámite de la cesión de zonas comunes, por lo que la audiencia se reprogramó para el 4 de febrero a las 09:00 am. 29/07/2024. Con memorando 20241300037153 se solicitó a la SRI especial seguimiento al caso atendiendo a la solicitud del Juez de gestionar el asunto de entrega de cesión de zonas comunes. 28/11/24. Se notificó por estado auto que aceptó renuncia a poder audiencia de pacto de cumplimiento el 4 de febrero de 2025 a las 9 am sin embargo teniendo en cuenta que se programo una mesa de soluciones para el 17 de febrero de 2025 para solventar el tema de ENEL CODENSA, el juzgado suspende la diligencia y solicita se informe inmediatamente por ultima vez los resultados de la mesa de soluciones con las entidades | AD17: EN CURSO | AE17: SRI | AF17: PARA AUDIENCIA DE PACTO DE CUMPLIMIENTO
A18: 526574 | B18: CONSTITUCIONAL | C18: 2015-00516 | D18: ACCION POPULAR | E18: 42262 | F18: JUZGADO 2 CIVIL DEL CIRCUITO DE ORALIDAD DE BOGOTÁ | G18: MARIA FERNANDA MADIEDO SANCHEZ | H18: DADEP | I18: FIDUCIARIA DE OCCIDENTE - BIENES Y COMERCIO - SADINSA | J18: DIRECTA | K18: DEMANDADO | L18: ENTREGA ZONAS DE CESIÓN | M18: NA | N18: ENTREGA Y ESCRITURACION ZONAS DE CESION VILLA ALSACIA | O18: VILLA ALSACIA LOTE 1 SECTOR A | P18: NA | Q18: NA | R18: ZONA DE CESIÓN | S18: 3205 | T18: KENNEDY | U18: 145038.7 | V18: NA | W18: NA | X18: NA | Y18: NA | Z18: NA | AA18: NA | AB18: NA | AC18: SEGUIMIENTO PROCESAL - NOTIFICADO CURADOR ADLITEM QUIEN CONTESTÓ DEMANDA Y ENTRÓ AL DESPACHO - A LA ESPERA TRASLADO EXCEPCIONES. AUDIENCIA PACTO DE CUMPLIIMIENTO PARA EL 1 DE OCTUBRE DE 2019. AL DESPACHO PARA RESOLVER RECURSO DE REPOSICION 9-2-2024 EN SECRETARIA CON EL AUTO DEL 12 DE MARZO DE 2020 QUE PONE EN CONOCIMIENTO DE CONFORMIDAD CON LA SOLICITUD DE ACLARACION ELEVADA POR EL APODERADO DE LA PARTE ACTORA, TENGASE PARA TODOS LOS EFECTOS POR NO ESCRITO EL ACAPITE DICTAMEN PERICIAL POR NO HABERSE SOLICITADO CON LA ACCION POPULAR. POR SECRETARIA DESE CUMPLIMIENTO AL AUTO QUE DECRETO PRUEBAS. A LA FECHA 10/05/2022 NO SE EVIDENCIA NINGUN ESTADO DIFERENTE AL DE PRUEBAS, POR LO CUAL SE REALIZARA EL RESPECTIVO //SEGUIMIENTO AL PROCESO. se consulta el proceso en la web de la rama el 9 de agosto de 2022 y se encuentra al despacho desde el 26 Marzo de 2021. se llevo a cabo mesa de trabajo el dia 6 de julio de 2022 con SRI y el accionante. Sin embargo, se manifiesto que no se va hacer modificacion de las zonas de cesion que en su tiempo presuntamente el DADEP no quiso entregar, se atienen a las resultas del proceso. se remite poder el 20-10-2022 para revision y posterior envio al despacho a fin de dar impulso procesal. El dia 24-10-2022 se radica 20221100165361 poder por correo electronico se reirera solicitud al despacho ya que no se registra la informacion en la web de la rama. se realiza consulta en la rama el 19-01-2023 ingresa al despacho con poder dadep. Auto de fecha 8-3-2023 requiere al accionado para que se pronuncie sobre el dictamen decretado a su solicitud. SE radica el 5-9-2023 solicitud de impulso procesal ya que el accionado no allega la prueba decretada. El 21-11-2023 se allega dictamen aportado por la demandada.El 27-12-2023 se solicito actualizacion estudio tecnico juridico. el 13-12-2023 se interpone recurso de reposicion contra auti de fecha 6-12-2023. a la espera de las resultas del recurso. Mediante oficio orfeo 20241300011381 de fecha 1 -2-2023 se remite estudio tecnico juridico actualizado del predio al juzgado para los fines que estime pertinentes.auto de fecha 9-10-2024 revoca parcialmente auto corre traslado a las partes sobre el estudio tecnico actualizado allegado por el DADEP a las partes.16/10/2024 APODERADA FIDUCIARIA DE OCCIDENTE S.A. / RECURSO DE REPOSICIÓN Y EN SUBSIDIO DE APELACIÓN. 28-10 -2024 Traslado Recurso Reposición Art. 319 C.G.P. al Despacho desde el 2024-11-05. una vez se resuelva recurso radicar informe tecnico. | AD18: EN CURSO | AE18: SRI | AF18: PRUEBAS
A19: 255193 | B19: CONTENCIOSO ADMINISTRATIVA | C19: 2006-00027 11001333103820060002700 | D19: EJECUTIVO | E19: 38985 | F19: JUZGADO 59 ADMINISTRATIVO | G19: GENARO SALAZAR GONZALEZ | H19: DADEP | I19: FRANCISCO JAVIER GOMEZ RAMIREZ | J19: DIRECTA | K19: DEMANDADO | L19: INCUMPLIMIENTO CONTRATO ARRENDAMIENTO 0051-1993 | M19: NA | N19: INCUMPLIMIENTO CONTRATO ARRENDAMIENTO 0051-1993 | O19: NA | P19: 75357472 | Q19: NA | R19: BIEN FISCAL | S19: 2-440 | T19: SANTAFE | U19: NA | V19: NA | W19: NA | X19: NA | Y19: NA | Z19: 40305 | AA19: NA | AB19: NA | AC19: AUTO REQUIERE AL SECUESTRE 22-11-2022, EL VEHICULO EMBARGADO NO APARECE FISICAMENTE, ES UN MODELO BASTANTE ANTIGUO LO QUE VALE ES EL CUPO (TAXI) DE NO APARECER SE DEBE BUSCAR EL DESISTIMIENTO TACITO Y ARCHIVAR. | AD19: CON FALLO | AE19: N/A | AF19: AUTO REQUIERE A LOS DDOS 30-07-2024
A20: 617610 | B20: CONSTITUCIONAL | C20: 2019-00611 11001310303520190061100 | D20: ACCION POPULAR | E20: 43776 | F20: JUZGADO 35 CIVIL DEL CIRCUITO DE BOGOTÁ | G20: MAGDA BOLENA ROJAS BALLESTEROS | H20: DADEP | I20: INVERSION Y DESARROLLO BARRANCO | J20: DIRECTA | K20: DEMANDADO | L20: ENTREGA DE ZONAS CE CESIÓN | M20: N/A | N20: CONSTRUCTORA INCUMPLIO CON LA OBLIGACION DE ESCRITURAR Y ENTREGAR LAS ZONAS DE CESIÓN. | O20: PANTANOS | P20: N/A | Q20: N/A | R20: ZONA DE CESIÓN | S20: 3616 | T20: KENNEDY | U20: 8305 | V20: NO APLICA | W20: N/A | X20: N/A | Y20: N/A | Z20: N/A | AA20: N/A | AB20: N/A | AC20: ESTA AL DESPACHO PARA SEÑALAR FECHA DE PACTO DE CUMPLIMIENTO 11-07-2023. Se notificó por estado auto que fijó fecha para audiencia de pacto el 21/02/2025 a las 09:00 am | AD20: EN CURSO | AE20: N/A | AF20: EL JUZGADO DECIDE EL RECURSO 18-04-2024
A21: 574069 | B21: CONSTITUCIONAL | C21: 2018-00106 | D21: ACCION POPULAR | E21: 43083 | F21: JUZGADO 2 CIVIL DEL CIRCUITO | G21: SHIRLEY AVELLANEDA PEÑA | H21: DADEP | I21: KADAS | J21: DIRECTA | K21: DEMANDADO | L21: SORATAMA | M21: N/A | N21: ENTREGA Y ESCRITURACION ZONAS DE CESION URBANIZACION BOSQUES DE SORATAMA | O21: BOSQUES DE SORAMATA | P21: N/A | Q21: N/A | R21: ZONA DE CESIÓN | S21: 3626 | T21: USAQUEN | U21: 33938.2 | V21: N/A | W21: N/A | X21: N/A | Y21: N/A | Z21: N/A | AA21: N/A | AB21: N/A | AC21: SEGUIMIENTO PROCESAL: CONTESTACIÓN DEMANDA Y ACTUACIONES PROCESALES. MEDIANTE RADICADO 20211100131541 MEMORIAL SOLICITANDO AL DESPACHO VINCULAR AL LIQUIDADOR. DIFERENTES MESAS DE TRABAJO CON EL LIQUIDADOR Y LA SRI. 27-04-2022 PODER IDRD. 25-07-2022 LA SRI ESTA GESTIONANDO ACTA DE TOMA DE POSESIÓN DE ACUERDO CON LA MESA DE TRABAJO CELEBRADA ENTRE LA OAJ Y SRI. AUTO DEL 2 DE NOVIEMBRE DE 2022, FIJA FECHA DE PACTO DE CUMPLIMIENTO PARA EL 24 DE NOVIEMBRE DE 2022 A LAS 10:00 A.M. AUTO 30/05/2023 FIJA AUDIENCVIA PACTO DE CUMPLIMIENTO 22/06/2023 A LAS 10:00 A.M. SE SUSPENDE DILIGENCIA DE PACTO DE CUMPLIMIENTO PARA EL 05-11-2023. MEDIANTE MEMORANDO ORFEO 2023130038133 SE SOLICITO A SRI INFORMACION DEL ESTADO DEL TRAMITE DE ESCRITURACI{ON. ORFEO 20232030039163 SE INFORMO ESTADO DE AVANCE DE LA ESCRITURACIÓN. RADICADO ORFEO 20231300166801 DEL 31-10-2023 SE SOLICITO AL DESPACHO FIJAR FECHA DE AUDIENCIA DE PACTO SUSPENDIDA. AL DESPACHO SIN ACTUACIÓN.22-01-2024 AL DESPACHO. | AD21: EN CURSO | AE21: SRI | AF21: FIJACION AUDIENCIA DE PACTO DE CUMPLIMIENTO
A22: 255007 | B22: CONTENCIOSO ADMINISTRATIVA | C22: 2006-00063 11001333103320060006300 | D22: EJECUTIVO | E22: 39028 | F22: JUZGADO 65 - ADMINISTRATIVO SECCIÓN TERCERA | G22: GENARO SALAZAR GONZALEZ | H22: DADEP | I22: DORIS ROCIO VANEGAS OLGUIN | J22: DIRECTA | K22: DEMANDADO | L22: INCUMPLIMIENTO CONTRATO ARRENDAMIENTO 0016-1999 | M22: NA | N22: INCUMPLIMIENTO CONTRATO ARRENDAMIENTO 0016-1999 | O22: NA | P22: 26979466 | Q22: NA | R22: BIEN FISCAL | S22: 2-440 | T22: SANTAFE | U22: NA | V22: NA | W22: NA | X22: NA | Y22: NA | Z22: 40622 | AA22: NA | AB22: NA | AC22: PROCESO CON SENTENCIA DEL EJECUTIVO, SE ENCUENTRA EMBARGADO LA CUOTA DE UN INMUEBLE DE DORIS ROCIO VANEGAS HOLGUIN | AD22: CON FALLO | AE22: N/A | AF22: SECUESTRO DEL BIEN INMUEBLE DECRETADO EL 23 DE MARZO DEL 2022, NO SE HA PODIDO CONCRETAR POR FALTA DE UBICACIÓN DEL PREDIO ESTA EN LA ALCALDIA DE BOSA.
A23: 681651 | B23: CIVIL | C23: (2007-00240) (11001310300220070024000) | D23: PERTENENCIA | E23: 39135 | F23: JUZGADO 47 CIVIL DEL CIRCUITO DE BOGOTÁ D.C. | G23: GENARO SALAZAR GONZALEZ | H23: ANA DOLORES SARMIENTO Y 2OTROS | I23: JOSE HECTOR BERMNUDEZ VARGAS Y OTROS | J23: DIRECTA | K23: INTERVINIENTE | L23: PERTENENCIA | M23: NO APLICA | N23: TERCEROS SE APODERARON DE UNA ZONA DE CESION EN EL TRAMITE JUDICIAL DE PERTENENCIA | O23: VILLAS DEL DORADO | P23: N/A | Q23: N/A | R23: ZONA DE CESIÓN | S23: 3103-7 | T23: ENGATIVA | U23: 875.80 MTS2 | V23: N/A | W23: N/A | X23: N/A | Y23: N/A | Z23: 40158 | AA23: N/A | AB23: N/A | AC23: SE PRESENTO INCIDENTE DE NULIDAD PROCESAL POR LA AFECTACIÓN DE UN PREDIO DESTINADO AL USO PUBLICO, EL JUZGADO CORRIO TRASLADO DEL MISMO. | AD23: CON FALLO | AE23: N/A | AF23: DESPACHO 26-09-2024 PARA TENER POR NOTIFICADO Y CONTESTADA LA DEMANDA Y DECRETAR PRUEBAS
A24: 606071 | B24: CONSTITUCIONAL | C24: 2019-00473 | D24: ACCION POPULAR | E24: 43664 | F24: JUZGADO 21 CIVIL DEL CIRCUITO DE BOGOTÁ | G24: MARIA FERNANDA MADIEDO SANCHEZ | H24: DADEP | I24: CONTRUCTORA LAS GALIAS S.A. | J24: DIRECTA | K24: DEMANDADO | L24: ENTREGA ZONAS DE CESIÓN | M24: N/A | N24: ZONAS DE CESION URBANIZACION QUINTAS DE CASTILLA | O24: QUINTAS DE CASTILLA | P24: N/A | Q24: N/A | R24: ZONA DE CESIÓN | S24: 848-1 AL 848-10 | T24: KENNEDY | U24: 6.196.65 | V24: N/A | W24: N/A | X24: N/A | Y24: N/A | Z24: N/A | AA24: N/A | AB24: N/A | AC24: Audiencia de pacto de cumplimiento llevada a cabo el día 06 de abril de 2022, donde la apoderada judicial de la parte accionada manifiesta que la certificación emitida por la UAESP, se les refundió, por tal motivo no la han podido aportar y completar todos los documentos para seguir con el trámite correspondiente; se envía petición a la UAESP de la respectiva acta por parte del juzgado y del DADEP con Rad No. 20221100051721, la audiencia se suspende y continúa el 08 de junio de 2022 la cual se declara fallida, ingresa el proceso al despacho para decretar las pruebas a que haya lugar, mediante auto de pruebas de 26 de septiembre de 2022, se decretan como pruebas solicitadas por la sociedad constructora, se señala interrogatorio de parte del representante del DADEP, el día 23 de enero de 2023 a las 2:15 pm, se decreta los testimonios de los señores, Ricardo Sánchez, Fabian Leonardo Gutiérrez Leal, María Cristina Naranjo y Carlos Humberto Guzmán, el día 30 de enero de 2023, Prueba de oficio: Se decreta el interrogatorio de parte del representante legal o quien haga sus veces de la sociedad demandada, el día 23 de enero a las 04:00 pm. se requiere la elaboración de dictamen pericial y para su presentación conceden el termino de 20 días, se procede a hacer la solicitud a la SRI, mediante memorando con Radicado DADEP No. 20221100068823, el cual se remite al juzgado el día 24 de octubre de 2022 con Radicado DADEP No. 20221100167141. Se asiste a audiencia el dia 23 de Enero de 2023, para pruebas en la misma se solicita por parte del apoderado del demandado la suspension y se coadyuva la solicitud por parte del DADEP se suspende la audiencia hasta el 28 de abril de 2023 a las 10 am. el despacho dio un termino de 5 dias para que el accionado remitiera cuestionario por parte de las galias. Audiencia de fecha 28 de Abril se suspende por 2 meses, toda vez que ya se esta en la etapa de escrituracion de las zonas de cesion. se solicita el dia 29 de Mayo de 2023 a SRI informe sobre el trámite de escrituración a fin de informar al despacho. se coadyuva solicitud de suspension de la diligencia programada para el 28 junio de 2023 para terminar los tramites administrativos, pendiente se radique por parte del urbanizador o notaria 15 la escritura publica para firma de la Directora. audiencia de continuacion 14-9-2023 a las 2:30 pm. se asiste a dligencia se presentan escrituras con transferencia zonas de cesion ingresa al despacho 25-9-2023 para sentencia. el 15 -3-2024 se profiere sentencia que aprueba el pacto de cumplimiento al haberse cumplido con la transferencia de las zonas de cesion. archivar proceso fecha 3 abril de 2024. | AD24: CON FALLO | AE24: SRI | AF24: ARCHIVO
A25: 164172 | B25: CONTENCIOSO ADMINISTRATIVA | C25: 2005-01927 | D25: EJECUTIVO | E25: 38580 | F25: JUZGADO 61 - ADMINISTRATIVO SECCIÓN TERCERA | G25: JAMMER SAUL HERNANDEZ | H25: DADEP | I25: EDDY ROCIO MELO CARRANZA | J25: DIRECTA | K25: DEMANDADO | L25: INCUMPLIMIENTO CONTRATO ARRENDAMIENTO 0010-1994 | M25: NA | N25: INCUMPLIMIENTO CONTRATO ARRENDAMIENTO 0010-1994 | O25: NA | P25: 51941169 | Q25: NA | R25: BIEN FISCAL | S25: 2-440 | T25: SANTAFE | U25: NA | V25: NA | W25: NA | X25: NA | Y25: NA | Z25: 40415 | AA25: NA | AB25: NA | AC25: SEGUIMIENTO SECRETARÍA JURÍDICA - PROCESO DE REPRESENTACIÓN INDIRECTA | AD25: EN CURSO | AE25: N/A | AF25: PENDIENTEGESTIÓN EMBARGO DE CUENTAS - SEGUIMIENTO A BIENES EN CABEZA DEL DEMANDADO PARA INFORMAR AL DESPACHO
A26: 617584 | B26: CONSTITUCIONAL | C26: 2019-00730 11001310302220190073000 | D26: ACCION POPULAR | E26: 43664 | F26: JUZGADO 22 CIVIL DEL CIRCUITO DE BOGOTÁ | G26: MAGDA BOLENA ROJAS BALLESTEROS | H26: DADEP | I26: FIDUCIARIA DE OCCIDENTE | J26: DIRECTA | K26: DEMANDADO | L26: ENTREGA DE ZONAS CE CESIÓN | M26: N/A | N26: CONSTRUCTORA INCUMPLIO CON LA OBLIGACION DE ESCRITURAR Y ENTREGAR LAS ZONAS DE CESIÓN. | O26: TINGUA | P26: N/A | Q26: N/A | R26: ZONA DE CESIÓN | S26: 3892 | T26: BOSA | U26: 14900 | V26: N/A | W26: N/A | X26: N/A | Y26: N/A | Z26: N/A | AA26: N/A | AB26: N/A | AC26: EL DESPACHO NO REPUSO AUTO Y ORDENO VINJCULAR A COLSUBSIDIO Y CURADOR URBANO 3. 16/02/2024. Se notificó por estado auto que requirió al DADEP para que remita cumplimiento del auto so pena de desistimiento de la demanda. 27/02/2024. Cumplimiento del auto por parte del DADEP. 04/10/2024. Se notificó por estado auto que ordenó vincular a la Secretaría Distrital del Hábitat. 23/10/2024. Memorial de cumplimiento del auto del 3 de octubre de 2024 por parte del DADEP a través del cual se remitió constancia de notificación a la Secretaría Distrital del Hábitat. 12/11/2024. Contestación demanda Secretaría de Hábitat | AD26: EN CURSO | AE26: N/A | AF26: DESPACHO 23-04-2024 PARA SEÑALAR FECHA DE PACTO DE CUMPLIMIENTO
A27: 391844 | B27: CONSTITUCIONAL | C27: 2012-00546 | D27: ACCION POPULAR | E27: 41151 | F27: JUZGADO 21 CIVIL DEL CIRCUITO DE BOGOTÁ | G27: SHIRLEY AVELLANEDA PEÑA | H27: DADEP | I27: CONSTRUCTORA NORMANDIA | J27: DIRECTA | K27: DEMANDADO | L27: ENTREGA Y ESCRITURACION BOSQUES DE SALAMANCA | M27: NA | N27: ENTREGA Y ESCRITURACION BOSQUES DE SALAMANCA | O27: BOSQUES DE SALAMANCA | P27: NA | Q27: NA | R27: ZONA DE CESIÓN | S27: 3977 | T27: SUBA | U27: 3065 | V27: NA | W27: NA | X27: NA | Y27: NA | Z27: NA | AA27: NA | AB27: NA | AC27: SEGUIMIENTO PROCESAL - SE ADELANTA GESTIONES TENDIENTES A ENTREGA ZONAS CESIÓN DE MANERA DIRECTA CON URBANIZADOR - PENDIENTE ESCRITURACIÓN. RADICARON SOLICITUD DEL 545 PERO AL PARECER SRI DETERMINA QUE NO ES VIABLE, SE CONTINUA CON PROCESO JUDICIAL. Se decretan pruebas y se señala para practicarlas 19/04/2024 10 A.M.26-01-2024 NO SE TIENE EN CUENTA CONTESTACION DE IDRD. SE CONVOCA PARA AUDIENCIA DE PACTO DE CUMPLIMEINTO EL DIA 9 DE DICIEMBRE DE 2019 A LAS 2:30 PM. 26-09-2022 FIJACION ESTADO AUTO RECONOCE PERSONERIA Y CONTESTACION DEMANDA Y CONCEDE TERMINO PARA APORTAR CERTIFICADO DE TRADICION ACTUALIZADO DEL BIEN OBJETO DE ACCION. 24-10-2023 AUTO DE PRUEBAS FIJA FECHA DE AUDIENCIA DE TESTIMONIOS ABRIL 13 DE 2024. EN DILIGENCIA LLEVADA A CABO EL 24 DE FEBRERO, LA JUEZA ORDENO HACER UN LEVANTAMIENTO TOPORAFICO, ESTUDIO DE TÍTULOS Y VISITA PARA PODER TENER CLARA LA FÓRMULA DE PACTO. POR LO ANTERIOR, SE SUSPENDE LA DILIGENCIA PARA QUE EL DADEP REALICE ESTOS ESTUDIOS. MEDIANTE OFICIO 20211100113181 01/10/2021 SE ALLEGARON AL DESPACHO ESTUDIO DE TITULOS Y LEVANTAMIENTO TOPOGRAFICO. 2022-05-27 REQUERIMIENTO JUZGADO PARTE ACTORA ALLEGAR OFICIOS A JARDIN BOTANICO, IDRD, SDP. 22-06-2022 MEDIANTE ORFEO 20221100089111 SE REMITIERON LOS OFICIOS SOLICITADOS POR EL DESPACHO. AL DESPACHO CON DILIGENCIAMIENTO OFICIO PARTE ACTORA Y PODER DE LA UAESP. 26-09-2022: AUTO RECONOCE PERSONERIA Y CONTESTACION DEMANDA JARDIN BOTANICO Y SOLICITUD DE CERTIFICADOS DE TRADICIÒN Y LIBERTAD. 19-10-2022 REMISION DE CERTIFICADOS DE TRADICION Y LIBERTAD. 27-02-2023 AUTO FIJA AUDIENCIA DE PACTO DE CUMPLIMIENTO. 28-07-2023 SE LLEVO A CABO AUDIENCIA DE PACTO DE CUMPLIMIENTO. AUDIENCIA DE PRUEBAS 19-04-2024. AUTO ALEGATOS DE CONCLUSION 05-06-2024. 12-06-2024 PRESENTACION ALEGATOS DE CONCLUSION. 18-12-2024 SENTENCIA DESFAVORABLE.14-01-2025 PRESENTACION RECURSO DE APELACIÓN. | AD27: EN CURSO | AE27: SRI | AF27: SENTENCIA DE PRIMERA INSTANCIA
A28: 764789 | B28: CIVIL | C28: (2023-00357) 11001310301320230035700 | D28: NULIDAD DE ESCRITURA PÚBLICA | E28: 45243 | F28: JUZGADO 13 CIVIL DEL CIRCUITO | G28: GENARO SALAZAR GONZALEZ | H28: DADEP | I28: NAMASTE S.A. | J28: DIRECTA | K28: DEMANDADO | L28: NULIDAD DE ESCRITURA PUBICA | M28: N/A | N28: El representante legal de la Asociación Provivienda de Trabajadores en su calidad de urbanizador responsable de hacer entrega de las zonas de cesión al Distrito Capital, incumplió con sus obligaciones urbanísticas señaladas en la mencionada Resolución 085 que aprobó los planos urbanísticos B16/4-18 al B16/4-29, y por el contrario, realizó un negocio jurídico de compraventa con la sociedad INVERSIONES NEMASTE S.A., con domicilio principal en la ciudad de Bogotá, identificado con el NIT 9001450807 representada legalmente por el señor LUIS DARIO DIAZ AGUIRRE mayor de edad, identificado con la cédula de ciudadanía Nro. 79.514.492, domiciliado y residenciado en la ciudad de Bogotá, sobre el bien inmueble ubicado actualmente en la calle 37B sur Nro. 72J-87 denominado lote 2 de la manzana 124 de la Urbanización Carvajal, con la suscripción de la Escritura Pública 1299 del 11 de junio del 2010 de la Notaria 44 del Círculo de Bogotá, sobre el cual se originó el Folio de Matrícula Inmobiliaria 050S-40534648 Carvajal con fecha de apertura el 19 de septiembre del 2009. | O28: CARVAJAL | P28: N/A | Q28: N/A | R28: ZONA DE CESIÓN | S28: 26330 | T28: KENNEDY | U28: 43 MTS2 | V28: N/A | W28: N/A | X28: N/A | Y28: N/A | Z28: EN CURSO | AA28: EN CURSO | AB28: EN CURSO | AC28: ESTA EN TRAMITE DE ADMISION DE LA DEMANDA | AD28: EN CURSO | AE28: N/A | AF28: DESPACHO PARA RESOLVER RECURSO DE NAMASTE 08-04-2024
A29: 558364 | B29: CONTENCIOSO ADMINISTRATIVA | C29: 2016-00311 | D29: REPARACIÓN DIRECTA | E29: 42970 | F29: TRIBUNAL ADMINISTRATIVO DE CUNDINAMARCA SECCIÓN TERCERA | G29: JOAN SEBASTIAN MARQUEZ ROJAS | H29: JOSE GABRIEL BOSSA MARTINEZ | I29: DADEP - PLANEACIÓN - GOBIERNO - ALC USAQUEN - PLANEACIÓN - CATASTRO | J29: DIRECTA | K29: DEMANDADO | L29: REF SOLICITA SE DECLARE LA NATURALEZA JURIDICA PRIVADA DE LOS INMUEBLES HEXAGONALES CON NOMECLATURA N CARRERA 5 BIS N 127 A 09 Y OTROS , EN RAZON A QUE NO CONSTITUYEN BUP NI EP NI ZUP POR NO POSEER DICHO CARACTER. | M29: NA | N29: REF SOLICITA SE DECLARE LA NATURALEZA JURIDICA PRIVADA DE LOS INMUEBLES HEXAGONALES CON NOMECLATURA N CARRERA 5 BIS N 127 A 09 Y OTROS , EN RAZON A QUE NO CONSTITUYEN BUP NI EP NI ZUP POR NO POSEER DICHO CARACTER. | O29: N/A | P29: N/A | Q29: NA | R29: ZONA DE CESIÓN | S29: 110223 | T29: USAQUEN | U29: 472.82 | V29: NA | W29: NA | X29: 472.82 | Y29: 221,586,057,70 | Z29: 25/07/2024 | AA29: NA | AB29: NA | AC29: Apelación de Sentencia de primera instancia del 25 de julio de 2024 - Pronunciamiento al recurso de apelación. | AD29: EN CURSO | AE29: N/A | AF29: EN APELACIÓN DE SENTENCIA - PRONUNCIAMIENTO.
A30: 674820 | B30: PENAL | C30: 2021-55466 | D30: PENAL | E30: 44347 | F30: FISCALIA 96 SECCIONALUNIDAD FE PUBLICA Y ORDEN ECONOMICO - ORDINARIO | G30: JOSE AGUSTÍN AVENDAÑO | H30: DADEP | I30: INDETERMINADO/ FRANCISCO DANIEL GOMEZ ZULUAGA | J30: DIRECTA | K30: DENUNCIANTE | L30: FALSIFICACION FIRMA NADIME AMPARO YAVER LICHT | M30: FALSEDAD MATERIAL EN DOCUMENTO PÚBLICO, OBTENCIÓN DE DOCUMENTO PÚBLICO FALSO, FRAUDE PROCESAL | N30: FALSIFICACION FIRMA NADIME AMPARO YAVER LICHT EN LA NOTARIA 58 DE BOGOTÁ | O30: BARRIO LA MERCED | P30: N/A | Q30: N/A | R30: BIEN FISCAL | S30: 2-1817 | T30: BARRIOS UNIDOS | U30: N/A | V30: N/A | W30: N/A | X30: N/A | Y30: N/A | Z30: N/A | AA30: N/A | AB30: N/A | AC30: EL DÍA 4 DE MAYO LA FISCALÍA 96 SECCIONAL DRA. MARÍA SARMIENTO, EMITE ÓRDENES A PJ, Y UN OFICIO CON DESTINO A LA OFICINA DE INSTRUMENTOS PÚBLICOS INFORMANDO QUE EL PREDIO CON MATRÍCULA INMOBILIARIA 50C-1791850 ES UN PREDIO DEL DISTRITO EN EL CUAL CURSA INVESTIGACION, EL DÍA 19 DE FEBRERO DE 2024 SE ASISTE A LA FISCALÍA 96 SECCIONAL DE BOGOTÁ, INFORMA EL DESPACHO QUE SE CONTINUA CON LA EVACUACIÓN DE ÓRDENES A PJ DE LO CUAL SE AGENDA REUNIÓN PARA EL DÍA 28 DE FEBRERO A LAS 3 PM, SE SOLICITO AUDIENCIA ANTE JUEZ PENAL DE CONTROL DE GARANTÍAS RESPECTO A LA SUSPENSIÓN DEL PODER DISPOSITIVO DEL INMUEBLE CON MATRÍCULA INMOBILIARIA 50C-1791850, AUDIENCIA FIJADA EL DÍA 19 DE MARZO A LAS 11 AM | AD30: EN CURSO | AE30: N/A | AF30: INDAGACIÓN PRELIMINAR
A31: 359396 | B31: CONSTITUCIONAL | C31: 2010-00522 | D31: ACCION POPULAR | E31: 40431 | F31: JUZGADO 6 CIVIL DEL CIRCUITO DE BOGOTÁ | G31: MARIA FERNANDA MADIEDO SANCHEZ | H31: DADEP | I31: CONSTRUCTORA AMG SA - CONSTRUCTORA BOLIVAR - INVERSIONES MAZUERA - HOSPITAL SAN CARLOS | J31: DIRECTA | K31: DEMANDADO | L31: ENTREGA ZONAS DE CESIÓN | M31: NA | N31: ENTREGA Y ESCRITURACION ZONAS DE CESION SAN CARLOS | O31: BOSQUE SAN CARLOS | P31: NA | Q31: NA | R31: ZONA DE CESIÓN | S31: 667 y 477-26 | T31: RAFAEL URIBE | U31: 41341 | V31: NA | W31: NA | X31: NA | Y31: NA | Z31: 41822 | AA31: 41983 | AB31: SIN ORDENES - DADEP EXIGIR DEMANDADO ENTREGA Y ESCRITURACION | AC31: Las ultimas actuaciones en el proceso por parte del juzgado sexto civil del circuito corresponde a que mediante auto del 14 de diciembre de 2021 manifiesta "Requerir a los intervinientes para que manifiesten lo que consideren correspondiente sobre la solicitud efectuada por la Fundación Hospital San Carlos y puesta en conocimiento en providencia del pasado 15 de julio. De otra parte, se requiere nuevamente al DADEP conforme lo ordenado en providencia del 26 de febrero de 2020 para que indique si ya dio cumplimiento total al fallo emitido dentro de esta acción que lleve a la finalización de este trámite". Tambien se evidencia en la rama judicial que el juzgado en la actuaciones del proceso publico que emitio un oficio requiriendo al DADEP con fecha 21 de febrero de 2022, pero se esta a la espera de la notificaciòn . Las acciones a seguir corresponde a elaborar memorando solicitando informaciòn a la Subdirecciòn de registro inmobiliario para saber en que estado se encuentra la RESTITUIR Y ESCRITURAR LAS ZONAS DE CESION. el dia 2-05-2022 se profiere un auto en donde se requiere a la sociedad de arquitectos por 10 dias para que informen sobre el adelantamiento dela entrega de las obras y/o informen sobre el plan de trabajo cronologico. se fija estado de fecha 2 de mayo de 2022, el 20 de Mayo de 2022 ingresa al despacho. auto de fecha 22 junio de 2022 pone en conocimiento el informe presentado por el urbanizador sobre el adelantamiento de las obras junto con el plan de trabajo cronologico con etapas y actvidades verificables, se cito a reunion por teams para seguimiento el dia 11 de agosto de 2022 de 4:00 a 5:00 pm. se remite informe de cumplimiento del fallo mediante orfeo 20221100152371 el dia 28 septiembre de 2022. auto de fecha 12-10-2022 despacho requiere se informe sobre gestiones adelantadas para la entrega de las zonas de cesion. mediante correo electronico de fecha 16-11 -2022 se solicita al despacho dar cumplimiento al auto de fecha 12-10-2022. Radicado orfeo 20222010165251 20-10-2022 SRI da anuencia sobre licencia de saneamiento, se solicita al urbanizador remitir copia de la licencia. El 26-1-2023 se remite correo a la apodera de CIGESA solicitando remitir lo solicitando mediante oficio 20222010165251 y se solicita informar de la situacion al despacho. EL 10 de marzo de 2023 se radica memorial al despacho informando sobre el cumplimiento de la accion popular, el proceso ingreso al despacho con esta solicitud desde el 14-3-2023. Mediante orfeo 20234000157102 aia informa sobre la radicacion ante la curaduria 5° de la licencia de urbanismo. se consulta web de la rama 27-7-2023 se emite respuesta juzgado 6 administrativo. Mediante correo de fecha 2-8-2023 se solicito informacion al apoyo técnico SRI sobre copia de la licencia de urbanismo y/o estado del tramite. el 24-8-2023 SRI remite oficio 20232010129071 al urbanizador. AUTO 15 NOVIEMBRE DE 2023 JUZGADO REQUIERE 5 DIAS PARA INFORME DE CUMPLIMIENTO. el 16-11-2023 mediante memorando 20231300041523 se solicita informe de cumplimiento a SRI. 21-11-2023 se descorre traslado al auto de fecha 15-11-2023. 01-02-2024 al despacho. 4-4-2024 IMPULSO PROCESAL, SEC ambiente da respuesta al urbanizador se remite copia al dadep. se revisa el proceso el 30-1-2025 proceso sin novedad procesal. | AD31: CON FALLO | AE31: SRI | AF31: CUMPLIMIENTO DE FALLO
A32: 286585 | B32: CONSTITUCIONAL | C32: 2009-00462 | D32: ACCION POPULAR | E32: 40029 | F32: JUZGADO 11 CIVIL DEL CIRCUITO DE BOGOTA | G32: SHIRLEY AVELLANEDA PEÑA | H32: DADEP | I32: ALIANZA FIDUCIARIA - NEGOCIACION BUENAVISTA | J32: DIRECTA | K32: DEMANDADO | L32: ESCRITURACION ENTREGA ZONAS DE CESION LA ESTANCIA ETAPA I | M32: NA | N32: ENTREGA DE LAS ZONAS DE CESION LA ESTANCIA ETAPA I | O32: LA ESTANCIA ETAPA I | P32: NA | Q32: NA | R32: ZONA DE CESIÓN | S32: 953 | T32: FONTIBON | U32: 6804 | V32: NA | W32: NA | X32: NA | Y32: NA | Z32: 42888 | AA32: 44124 | AB32: NA | AC32: SEGUIMIENTO PROCESAL CUMPLIMIENTO DE FALLO, SENTENCIA DEL 20 DE OCTUBRE DE 2020, SE SOLICITO INICIAR INCIDENTE DESACATO MEDIANTE RADICADO DEL 16 DE DICIEMBRE DE 2021. MEDIANTE RADICADO 20221100049491 DEL 19-04-2022. 17-05-2022 Al despacho. 01-08-2022.12-12-2023 OFICOS IDRD Y ALCALDIA DE FONTIBON. SRI ESTUDIO TECNICO PARA EVALUAR APLICACIÓN DEL 545.DADEP RESPONDE INCIDENTE. RADICADO 2022110049491 19-04-2022, SOLICITUD VIGILANCIA ESPECIAL. PRONUNCIAMIENTO PROCURADURIA RADICADO 20224000106962.17-05-2022 AL DESPACHO. MEDIANTE RADICADO 2022110047081 DEL 28-09-2022 SE RADICO REITERACION DE INCIDENTE DE DESACATO. 27-04-2023. INICIO INCIDENTE DESACATO. 07-08-2023 AUTO ORDENA REQUERIR COMITE VERIFICADOR. 10-08-2023 MESA DE TRABAJO COMITE VERIFICADOR. 11-08-2023 ENVIO INFORME IDU Y MESA DE TRABAJO COMITE VERIFICADOR CUMPLIMIENTO DE FALLO. 20-11-2023 AUTO DENIEGA SOLICITUD DE ACLARACIÓN DE SENTENCIA POR EXTEMPORANEA Y REQUIERE A IDRD Y A ALCALDIA LOCAL DE FONTIBÓN INFORME POR TERMINO DE 5 DÍAS Y AL DADEP PARA REMITIR LINK DE GRABACION COMITE VERIFICADOR. 06-12-2023 ENVIO OFICIOS IDRD Y ALCALDIA LOCAL DE FONTIBON. 23-01-2024 AL DESPACHO. 12-02-2024 PRESENTACION MEMORIAL ALIANZA FIDUCIARIA. 29-02-2024 CONTESTACION ALIANZA FIDUCIARIA, HACER SEGUIMIENTO EL 22-03-2024. MESAS DE TRABAJO CON ALIANZA FIDUCIARIA . 2024-12-13 PRESENTACIÓN DE INFORMES. 26-12-2024 INFORMACION ESTADO DE ZONAS ALIANZA FIDUCIARIA. 27-01-2025 MESA DE TRABAJO ALCALDIA LOCAL DE FONTIBON. | AD32: CON FALLO | AE32: SRI | AF32: PRIMERA INSTANCIA - DEFINIR INCIDENTE DESACATO POR EL DESPACHO JUDICIAL.
A33: 672915 | B33: CONSTITUCIONAL | C33: 2021-00142 (1100131030041 20210014200) | D33: ACCION POPULAR | E33: 44296 | F33: JUZGADO 41 CIVIL DEL CIRCUITO DE BOGOTÁ D.C. | G33: MAGDA BOLENA ROJAS BALLESTEROS | H33: DADEP | I33: JAC VENECIA PARROQUIA SANTA CAGALINA COLEGIO VENECIA | J33: DIRECTA | K33: DEMANDADO | L33: ENTREGA DE ZONAS CE CESIÓN | M33: N/A | N33: TERCEROS SE APODERARON DE UNA ZONA DE CESION EN EL PREDIO LAGUNA | O33: LAGUNA AZUL | P33: N/A | Q33: N/A | R33: ZONA DE CESIÓN | S33: 1062-94 | T33: TUNJUELITO | U33: 11.239 MTS2 | V33: N/A | W33: N/A | X33: N/A | Y33: N/A | Z33: N/A | AA33: N/A | AB33: N/A | AC33: 27/05/2024. Se notificó por estado auto que corrió traslado para alegatos de conclusión. 05/06/2024. Al despacho para sentencia de primera instancia | AD33: EN CURSO | AE33: N/A | AF33: AL DESPACHO PARA SENTENCIA DE PRIMERA INSTANCIA
A34: 718471 | B34: CIVIL | C34: (2022-00308) 11001310301020220030800 | D34: DESLINDE Y AMOJONAMIENTO | E34: 44842 | F34: JUZGADO 10 CIVIL DEL CIRCUITO | G34: GENARO SALAZAR GONZALEZ | H34: MARIA ALEJANDRA CARDENAS RICO LUZ DIANA CARDENAS RICO | I34: DEPARTAMENTO ADMINISTRATIVO DE LA DEFENSORIA DEL ESPACIO PUBLICO; ALVARO LOPEZ FONSECA | J34: DIRECTA | K34: DEMANDADO | L34: LINDEROS COLINDANTES ENTRE PREDIOS PRIVADOS CON ZONAS PUBLICAS | M34: N/A | N34: SE REQUIERE ADELANTAR EN ESTE PROCESO PARA DETERMINAR LA LÍNEA DIVISORIA, FIJAR MOJONES, DETERMINAR LINDEROS Y ÁREA DEL PREDIO.CUARTO. LAS DEMANDANTES MARIA ALEJANDRA ARDENAS RICO Y LUZ DIANA CARDENAS RICO SON PROPIETARIAS DE PLENO DOMINIO DEL INMUEBLE INMUEBLE OBJETO DEL DESLINDE Y AMOJONAMIENTO UBICADO EN LA KR5B BIS 127 A 29 Y/O KR5B BIS 127 A 31 Y CHIP 0101ORZE TAL Y COMO SE REGISTRA EN LA ANOTACIÓN 3 DEL FOLIO DE MATRÍCULA INMOBILIARIA NO. 50N 585880. DEMANDADO DISTRITO CAPITAL – DEPARTAMENTO ADMINISTRATIVO DE LA DEFENSORIA DEL ESPACIO PÚBLICO, ES PROPIETARIO DE LAS ZONA DE CESIÓN (ZONA VIALES) KR 6 – CALLE 127B/MANZANA IDENTIFICADA CON EL RUPI 1102-4 Y ZONA DE CESIÓN (ZONA VIALES) KR 5B BIS – KR 5B/MANZANA IDENTIFICADA CON EL RUPI 1102-16, LOS DEMANDADOS MARIA OFELIA RODRIGUEZ DE QUINTERO Y JOSÉ BERNARDO PEDRAZA CHACÓN | O34: DELICIAS DEL CARMEN | P34: N/A | Q34: N/A | R34: ZONA DE CESIÓN | S34: 1102-4 Y 1102-16 | T34: USAQUEN | U34: 872 MTS2 | V34: N/A | W34: N/A | X34: N/A | Y34: N/A | Z34: EN TRAMITE DE NOTIFICACION | AA34: EN TRAMITE DE NOTIFICACION | AB34: N/A | AC34: SE CONTESTO LA DEMANDA, ESTAR PENDIENTE LA CONTESTACION DE LOS DEMAS DEMANDADOS E INGRESO AL DESPACHO PARA FECHA DE AUDIENCIA | AD34: EN CURSO | AE34: N/A | AF34: AUTO DE TRAMITE 14-11-2024
A35: 336200 | B35: PENAL | C35: 2007-07760 | D35: PENAL | E35: 39406 | F35: FISCALIA 105 SECCIONAL UNIDAD DE PATRIMONIO ECONOMICO | G35: JOSE AGUSTÍN AVENDAÑO | H35: CARLA PATRICIA OSPINA RAMIREZ | I35: ANGELICA ESTHER TERNERA CASTAÑEDA | J35: DIRECTA | K35: INTERVINIENTE | L35: VENTA BIEN USO PUBLICO MODELIA SECTOR E | M35: FALSEDAD DOCUMENTO PUBLICO - FRAUDE PROCESAL | N35: VENTA POR ESCRITURA PUBLICA DE BIEN DE USO PUBLICO URBANIZACION MODELIA SECTOR E | O35: MODELIA SECTOR E | P35: NA | Q35: NA | R35: ZONA DE CESIÓN | S35: 1108-24 | T35: FONTIBON | U35: NA | V35: NA | W35: NA | X35: NA | Y35: NA | Z35: NA | AA35: NA | AB35: NA | AC35: SE ENVÍA MEMORIAL DE SEGUIMIENTO CON RADICADO ORFEO DADEP No. 20221100146741, POSTERIORMENTE RESPONDEN QUE: ATENTAMENTE ME PERMITO INFORMARLE QUE LA ORDEN 8112096, SE REFIERE A LA PRACTICA DE EXPERTICIOSTECNICOS DE LOFOSCOPIA Y GRAFOLOGIA, ENTRE ELLOS, LA CONFRONTACION DE LA FIRMA DE GERMAN DARIORODRIGUEZ QUIEN EN LA ESCRITURA 1923, ACTUO COMO DIRECTOR DE ESE DEPARTAMENTO, POR ESO SESOLICITA SU COLABORACIÓN PARA EL APORTE Y TOMA DE TALES MUESTRAS Y EL SUMINISTRO DE INFORMACIONSOBRE LA UBICACIÓN DE LUZ DARY ESPINOSA NEUTA. CORDIALMENTE. HECTOR A. RODRIGUEZ H.- ASISTENTEFISCALIA 105 SECCIONAL.(...)" | AD35: EN CURSO | AE35: N/A | AF35: INDAGACIÓN PRELIMINAR
A36: 523266 | B36: PENAL | C36: 2015-11119 | D36: PENAL | E36: 42188 | F36: FISCALIA 365 SUB UNIDAD DE TIERRAS | G36: JOSE AGUSTÍN AVENDAÑO | H36: DADEP | I36: NESTOR BELLO GARZON - HECTOR JOSE BUITRAGO - JOSE ANTONIO AVILA COLLAZOS | J36: DIRECTA | K36: DENUNCIANTE | L36: COLEGIO RODRIGO TRIANA | M36: FRAUDE PROCESAL - OBTENCION DOCUMENTO PUBLICO FALSO | N36: PARTICULARES INICIAN PROCESO REINVINDICATORIO SOBRE BIENES CESION CON DOCUMENTOS FALSOS | O36: COLEGIO RODRIGO TRIANA | P36: NA | Q36: NA | R36: BIEN FISCAL | S36: 1141 | T36: KENNEDY | U36: NA | V36: NA | W36: NA | X36: NA | Y36: NA | Z36: NA | AA36: NA | AB36: NA | AC36: El día 14 de mayo de 2024, se realiza visita de manera presencial al despacho de la fiscal de conocimiento, la cual indica que el proceso de referencia tiene órdenes a policía judicial pendientes por cumplir ya que el policía judicial despacho se encuentra en curso de acenso y están a la espera de que se les asigne uno nuevo. | AD36: EN CURSO | AE36: N/A | AF36: INDAGACIÓN
A37: 391750 | B37: CONSTITUCIONAL | C37: 2009-00483 | D37: ACCION POPULAR | E37: 40088 | F37: JUZGADO 9 CIVIL DEL CIRCUITO | G37: SHIRLEY AVELLANEDA PEÑA | H37: DADEP | I37: INVESIONES SANTANA Y CIA | J37: DIRECTA | K37: DEMANDADO | L37: ZONAS DE CESION LA ESTANCIA ETAPA III A Y III B | M37: NA | N37: ENTREGA DE LAS ZONAS DE CESION LA ESTANCIA ETAPA III A Y B | O37: LA ESTANCIA 3A Y 3B | P37: NA | Q37: NA | R37: ZONA DE CESIÓN | S37: 953 | T37: FONTIBON | U37: 56443 | V37: NA | W37: NA | X37: NA | Y37: NA | Z37: 41418 | AA37: 41548 | AB37: ORDENES AL DEMANDADO PARA ENTREGAR - DOTAR - EQUIPAR ZONAS CESION | AC37: EL DADEP SOLICITO APERTURA DE INCIDENTE DESACATO EL 15 DE AGOSTO DE 2014. 02-06-2022 AUTO DE TRAMITE ORDENA LIBRAR MANDAMIENTO DE PAGO. SE SOLICITO AL DESPACHO LIBRAR MANDAMIENTO DE PAGO TENIENDO EN CUENTA EL INCUMPLIMIENTO DEL URBANIZADOR.RADICADO 2022110049441 19-04-2022, SOLICITUD VIGILANCIA ESPECIAL MEDIANTE RADICADO 20221100049441 19-04-2022. PRONUNCIAMIENTO PROCURADURIA RADICADO UIS 67364-2009 2022 DEL 05/04/2022. 02-06-2022, AUTO DE TRAMITE SUBSANACIÒN PROCESO. 10-06-2022: MEMORIAL RETIRO PROCESO EJECUTIVO. MEMORANDO 20221100038613 DEL 16-06-2022 SOLICITUD A SRI ESTUDIO DE TITULOS. 07-10-2022 AUTO FIJA FECHA DE AUDIENCIA PARA EL 26-01-2023 A LAS 2:00 P.M. TENIENDO EN CUENTA LA DECISION DE LA JUEZ DE OTORGA SEIS MESES PARA DAR APERTURA A FOLIO DE MATRICULA. MENSUALMENTE SE HAN PRESENTADO LOS INFORMES DE AVANCE ANTE LA SUPERINTENDENCIA DE REGISTRO DE INSTRUMENTOS PUBLICOS Y CONTINUAR CON EL TRAMITE DE LA DECLARATORIA DE PROPIEDAD PUBLICA. SE HAN PRESENTADO INFORMES MENSUALES. MEDIANTE EL RADICADO. 14-11-2023 AUTO CONCEDE TERMINO DE 10 DIAS ENVIANDO INFORMES DEL DADEP PARA CUMPLIMIENTO DE FALLO. 27-11-2023 RESPUESTA APODERADO INFORMANDO QUE LAS GESTIONES DEBEN SER REALIZADAS POR EL DADEP. 01-15-2024 AUTO REQUIERE.20241300015303 SOLICITUD A SRI INFORME DECLARATORIA DE PROPIEDAD PUBLICA.08-11-2024 Presentación memorial a Juzgado avance y solicitud de oficiar a propietario de las zonas de cesión para poder continuar con declaratoria de propiedad publica, mediante correo electrónico se informa avance de cumplimiento de fallo a Secretaria Jurídica Distrital. 28-01-2025 solicitud de avance declararotia de propiedad publica SRI. | AD37: CON FALLO | AE37: SRI | AF37: CUMPLIIMIENTO FALLO
A38: 407780 | B38: CONTENCIOSO ADMINISTRATIVA | C38: 2012-00158 | D38: NULIDAD Y RESTABLECIMIENTO DEL DERECHO | E38: 41399 | F38: CONSEJO DE ESTADO - SECCION PRIMERA | G38: JOAN SEBASTIAN MARQUEZ ROJAS | H38: JORGE ENRIQUE CORTES ROJAS | I38: SUPERNOTARIADO - DADEP | J38: DIRECTA | K38: DEMANDADO | L38: NULIDAD DE RESOLUCION SNR MEDIANTE LA CUAL NEGO SOLICITUD REVOCATORIA DIRECTA DE INSCRIPCIONES FMI DADEP - JABOQUE | M38: NA | N38: NULIDAD DE RESOLUCION SNR MEDIANTE LA CUAL NEGO SOLICITUD REVOCATORIA DIRECTA DE INSCRIPCIONES FMI DADEP - JABOQUE | O38: HUMEDAL JABOQUE | P38: NA | Q38: NA | R38: HUMEDAL | S38: 1-1623 - 1-4138 | T38: ENGATIVA | U38: NA | V38: NA | W38: NA | X38: 2789.44 | Y38: 224193767 | Z38: 41548 | AA38: NA | AB38: NA | AC38: SEGUIMIENTO PROCESAL - SE PRESENTAN ALEGATOS DE CONCLUSIÓN EL 26 DE OCTUBRE DE 2020, ENTRA AL DESPACHO PARA PROFERIR FALLO. DE SEGUNDA INSTANCIA | AD38: EN CURSO | AE38: N/A | AF38: AL DESPACHO PARA FALLO
A39: 749798 | B39: CIVIL | C39: 2017-01068 | D39: PERTENENCIA | E39: 44988 | F39: JUZGADO 26 CIVIL MUNICIPAL DE BOGOTÁ | G39: MARIA FERNANDA CRUZ | H39: LUIS CRISTANCHO RUBIO AVILA | I39: PERSONAS INDETERMINADAS | J39: DIRECTA | K39: INTERVINIENTE | L39: PRESCRIPCIÓN ADQUISITIVA DE DOMINIO | M39: N/A | N39: EL SEÑOR LUIS CRISANTO RUBI AVILA SEÑALA HABER POSEISO EL INMUEBLE TV 56 A 76 15 POR MAS DE 10 AÑOS, AL ESTAR TRASLAPADO SOBRE EL RUPI 1269-15 SE PIDIO TERMINACIÓN PROCESO | O39: N/A | P39: N/A | Q39: N/A | R39: ZONA DE CESIÓN | S39: 1269-15 | T39: BARRIOS UNIDOS | U39: N/A | V39: N/A | W39: N/A | X39: N/A | Y39: N/A | Z39: N/A | AA39: N/A | AB39: N/A | AC39: EL DESPACHO PROFIRIÓ RENTENCIA ANTICIPADA Y EL DEMANDANTE APELÓ, SIN EMBARGO, NO SUSTENTÓ EL RECURSO EN EL TÉRMINO CORRESPONDIENTE. | AD39: CON FALLO | AE39: N/A | AF39: APELACIÓN
A40: 163873 | B40: CONTENCIOSO ADMINISTRATIVA | C40: 2005-01930 | D40: EJECUTIVO | E40: 38502 | F40: JUZGADO 60 - ADMINISTRATIVO SECCIÓN TERCERA | G40: JAMMER SAUL HERNANDEZ | H40: DADEP | I40: MARIO ENRIQUE VILLALBA GUTIERREZ | J40: DIRECTA | K40: DEMANDADO | L40: INCUMPLIMIENTO CONTRATO ARRENDAMIENTO 0036-1994 | M40: NA | N40: INCUMPLIMIENTO CONTRATO ARRENDAMIENTO 0036-1994 | O40: NA | P40: 22819121 | Q40: NA | R40: BIEN FISCAL | S40: 2-440 | T40: SANTAFE | U40: NA | V40: NA | W40: NA | X40: NA | Y40: NA | Z40: 39112 | AA40: NA | AB40: NA | AC40: SEGUIMIENTO SECRETARÍA JURÍDICA - PROCESO DE REPRESENTACIÓN INDIRECTA. RECONOCEN PERSONERIA AL APODERADO DEL DADEP | AD40: EN CURSO | AE40: N/A | AF40: ACREDITA TRAMITE EMBARGO DE CUENTAS - SEGUIMIENTO DE BIENES EN CABEZA DEL DEMANDADO PARA EMBARGO DE LOS MISMOS.
A41: 190121 | B41: CIVIL | C41: 2006-00181 | D41: REIVINDICATORIO | E41: 38810 | F41: JUZGADO 17 CIVIL DEL CIRCUITO | G41: JAMMER SAUL HERNANDEZ | H41: DADEP | I41: JUAN DE JESUS LARA | J41: DIRECTA | K41: DEMANDADO | L41: REINVINDICAR BIEN FISCAL 2-987 (JUAN DE JESUS) | M41: NA | N41: REINVINDICAR BIEN FISCAL 2-987 (JUAN DE JESUS) | O41: NA | P41: NA | Q41: NA | R41: BIEN FISCAL | S41: 2-987 | T41: BARRIOS UNIDOS | U41: 186.1 | V41: NA | W41: NA | X41: NA | Y41: NA | Z41: 40317 | AA41: NA | AB41: NA | AC41: SEGUIMIENTO PROCESAL - PENDIENTE REPROGRAMACION DILIGENCIA DE ENTREGA. ACTUALIZACIÓN DE LINDEROS DEL PREDIO. FIJA FECHA PARA AUDIENCIA DE ENTREGA PARA EL PRÓXIMO CINCO (5) DE MARZO DE 2024, A LAS 9:00 AM. EN FECHA 05 DE MARZO DE 2024, SE PROCEDE A REPROGRAMAR LA AUDIENCIA PARA EL PROXIMO 31-05-2024 A LAS 8:00 AM. | AD41: CON FALLO | AE41: N/A | AF41: SENTENCIA DE PRIMERA INSTANCIA-GESTIONES PARA ACTUALIZAR LINDEROS DEL PREDIO Y ENTREGA DEL MISMO.
A42: 478069 | B42: PENAL | C42: 2014-11942 | D42: PENAL | E42: 41892 | F42: JUZGADO 29 PENAL DEL CIRCUITO CON FUNCIÓN DE CONOCIMIENTO | G42: JOSE AGUSTÍN AVENDAÑO | H42: DADEP | I42: JORGE ENRIQUE CORTES ROJAS | J42: DIRECTA | K42: DENUNCIANTE | L42: JABOQUE | M42: FRAUDE PROCESAL - OBTENCION DOCUMENTO PUBLICO FALSO | N42: TRASLAPE BIEN PRIVADO SOBRE BIEN PUBLICO | O42: JABOQUE | P42: NA | Q42: NA | R42: BIEN DE USO PUBLICO | S42: 1-4138 | T42: ENGATIVA | U42: NA | V42: NA | W42: NA | X42: NA | Y42: NA | Z42: NA | AA42: NA | AB42: NA | AC42: SE ASISTE A AUDIENCIA PREPARATORIA Y SE SE PROGRAMA CONTINUACION DE LA MISMA PARA EL 24 DE MAYO DEL 2024 A PARTIR DE LAS 2PM a partir de las 2pm. | AD42: EN CURSO | AE42: N/A | AF42: AUDIENCIA PREPARATORIA
A43: 539716 | B43: PENAL | C43: 2015-20028 | D43: PENAL | E43: 42644 | F43: FISCALIA 79 SUB UNIDAD DE TIERRAS | G43: JOSE AGUSTÍN AVENDAÑO | H43: SECRETARIA DE GOBIERNO | I43: LUIS CARLOS MORALES Y OTROS | J43: DIRECTA | K43: INTERVINIENTE | L43: INVASIÓN DE PREDIOS QUIBA BAJA (EN ESTUDIO SI SE INVOLUCRARON BIENES DE USO PÚBLICO) | M43: INVASION A TIERRAS | N43: INVASIÓN DE PREDIOS QUIBA NAJA (EN ESTUDIO SI SE INVOLUCRARON BIENES DE USO PÚBLICO) | O43: QUIBA LA BAJA | P43: NA | Q43: NA | R43: BIEN DE USO PUBLICO | S43: 1-4572 | T43: CIUDAD BOLIVAR | U43: NA | V43: NA | W43: NA | X43: NA | Y43: NA | Z43: NA | AA43: NA | AB43: NA | AC43: SEGUIMIENTO PROCESAL - EXPEDIDAS ORDENES A POLICÍA JUDICIAL EN SEGUIMIENTO A SU EJECUCIÓN. | AD43: EN CURSO | AE43: N/A | AF43: INDAGACIÓN
A44: 632510 | B44: CIVIL | C44: 2019-00624 | D44: DESLINDE Y AMOJONAMIENTO | E44: 43804 | F44: JUZGADO 15 CIVIL DEL CIRCUITO | G44: MARIA FERNANDA CRUZ | H44: MARA BELEN GUATAQUI DE RUIZ | I44: DADEP CONJUNTO RESIDENCIAL EL MEREY LUIS ALFONSO PATIÑO | J44: DIRECTA | K44: DEMANDADO | L44: FIJACIÓN LINDEROS Y MOJONES Y ENTREGA POSESIÓN | M44: N/A | N44: FIJACIÓN LINDEROS Y MOJONES Y ENTREGA POSESIÓN | O44: N/A | P44: N/A | Q44: N/A | R44: ZONA DE CESIÓN | S44: 1465-5 | T44: SUBA | U44: N/A | V44: N/A | W44: N/A | X44: N/A | Y44: N/A | Z44: N/A | AA44: N/A | AB44: N/A | AC44: SE ESPERA FIJACIÓN DILIGENCIA DESLINDE Y AMOJONAMIENTO | AD44: EN CURSO | AE44: N/A | AF44: CONTESTACIÓN DEMANDA
A45: 563425 | B45: CONSTITUCIONAL | C45: 2017-00651 11001310304020170065100 | D45: ACCION POPULAR | E45: 43039 | F45: JUZGADO 40 CIVIL DEL CIRCUITO | G45: MARIA FERNANDA MADIEDO SANCHEZ | H45: DADEP | I45: URBANIZADORA SANTA FE DE BOGOTA -URBANSA S.A.; COMPAÑÍA SURAMERICANA DE CONSTRUCCIONES S.A.; NUEVO MUNDO COMPAÑÍA GENERAL S.A.; INVERSIONES REACOL S.A. | J45: DIRECTA | K45: DEMANDADO | L45: ENTREGA ZONAS DE CESIÓN | M45: NA | N45: ENTREGA, FORMAL Y MATERIALMENTE LAS ZONAS DE CESION NGRATUITAS A FAVOR DEL DISTRITO CAPITAL CAMINO VERDE | O45: CAMINO VERDE | P45: N/A | Q45: N/A | R45: ZONA DE CESIÓN | S45: 1468 | T45: SUBA | V45: N/A | W45: N/A | X45: N/A | Y45: N/A | Z45: N/A | AA45: N/A | AB45: N/A | AC45: Se tiene por notificada a la demandada Compañía Suramericana de Construcciones S.A., en los términos previstos por el Decreto 806 de 2020, quien dentro del término legal de traslado guardó silencio. Se convocó a mesa de trabajo con SRI para el 8 de marzo de 2022 según por solicitud de URBANSA S.A. quienes manifestaron interés de arreglo directo. Se fija fecha de audiencia de pacto para el 26 DE ENERO DE 2022 A LAS 11:00 A.M. al despacho desde el 10-8-2023, auto de fecha 7 diciembre de 2023 reconoce peronseria para actuar por secretaria se orden notificacion a los accionados faltantes del libelo inicial. 12-2-2024 ingresa al despacho . La sociedad accionada interpone recurso de apelación contra el auto que fija fecha el cual fue descorrido en oportunidad por lo cual que no se da apertura a la audiencia. El 29 de julio de 2022, por solicitud del DADEP se profiere auto que VINCULA al Instituto Distrital de Recreación y Deporte – IDRD, el Jardín Botánico de Bogotá José Celestino Mutis, la empresa Codensa S.A. y a la Empresa de Acueducto y Alcantarillado de Bogotá EAAB. El 16 de septiembre de 2022 se allega contestación de la demanda de SOLUCIONES ESTRATEGICAS S.A.S., no se remitió al correo institucional ni se ha fijado en lista para descorrer excepciones, el memorial se ubicó en SIPROJ al ser cargado por el IDRD. 2023-07-06 no acepto renuncia de poder del anterior abogado pese a que se envio poder, 10-8-2023 al despacho auto 7-12-2023 se ordena por secretaria notificar a los accionados; reconoce personeria.2024-02-12 Al despacho. 2024-03-22 Auto ordena notificar ordena que por secretaria se notifique a la Alcaldía local de suba; Jardín botanico; codensa; acueducto y alcantarillado de Bogotá. Se realizan notificaciones a los vinculados conforme lo ordenado mediante auto de fecha 7 y 29 julio de 2022, se remiten coforme articulo 8 ley 2213 de 2022 el dia 4 de Abril de 2024 , los 10 dias fenecen el 19 de abril de 2024, se remiten constancia al juez de conocimiento. el 4-8-2024 se radica en secretaria memorial solicitanco aclaracion auto vinculacion apoderado enel colombia. 2-5-2024 INGRESA CONTESACION DE LA DEMANDA ALCALDIA LOCAL Y ACUEDUCTO. proceso al despacho desde el 2 julio de 2024. Orfeo 20242010143861 de fecha 8-10-2024 se programo visita. SRI informa que se realizó visita de inspección el pasado 9 de octubre a las zonas de cesión con destino a vías de las ETAPAS 2,3, y 4 de la Urbanización camino verde, encontrandose de conformidad con el procedimiento de entrega simplificada del Decreto 072 del 2023. Por consiguiente, se encuentra en elaboracion el acta de recibo para dichas zonas. Quedaron pendientes los controles ambientales , los parques de las etapas 2, 3 y 4. No se encontró viable el recibo de las zonas de cesión de la ETAPA 5. Se solicito informacion a la arq nodierth sobre el estado de la firma del acta de recibo parcial .El 04/02/2025 auto resuelve aclaración providencia, fija fecha audiencia para el 8 de junio del 2025 a las 9:00am para llevar a cabo audiencia especial de pacto de cumplimiento. | AD45: EN CURSO | AE45: SRI | AF45: PACTO DE CUMPLIMIENTO
A46: 539715 | B46: PENAL | C46: 2016-17038 | D46: PENAL | E46: 42625 | F46: FISCALIA 365 SUBUNIDAD DE TIERRAS | G46: JOSE AGUSTÍN AVENDAÑO | H46: DADEP | I46: JULIAN ALIRIO MARTINEZ Y OTROS | J46: DIRECTA | K46: DENUNCIANTE | L46: RINCON DE LOS ANGELES | M46: FRAUDE PROCESAL - OBTENCION DOCUMENTO PUBLICO FALSO | N46: APROPIACION BIENES DE USO PUBLICO COLINDANTES CON BIEN PRIVADO ADJUDICADO EN REMATE | O46: RINCON DE LOS ANGELES - CASTILLA | P46: NA | Q46: NA | R46: BIEN DE USO PUBLICO | S46: 1-4875 - 1-4876 | T46: KENNEDY | U46: NA | V46: NA | W46: NA | X46: NA | Y46: NA | Z46: NA | AA46: NA | AB46: NA | AC46: SEGUIMIENTO PROCESAL - EXPEDIDAS ORDENES A POLICÍA JUDICIAL EN SEGUIMIENTO A SU EJECUCIÓN. | AD46: EN CURSO | AE46: N/A | AF46: INDAGACIÓN
A47: 541723 | B47: CONTENCIOSO ADMINISTRATIVA | C47: 2016-00329 11001333400220160032900 | D47: NULIDAD SIMPLE | E47: 43133 | F47: TRIBUNAL ADMINISTRATIVO DE CUNDINAMARCA SECCION PRIMERA MIXTA ORAL | G47: JOAN SEBASTIAN MARQUEZ ROJAS | H47: DADEP | I47: UNIDAD ADMINISTRATIVA ESPECIAL DE CATASTRO DISTRITAL | J47: DIRECTA | K47: COADYUVANTE | L47: NULIDAD ACTO ADMINISTRAIVO PROFERIDO POR UAECD RESOLUCIONES 2010-110519 | M47: N/A | N47: NULIDAD DEL ACTO ADMINISTRATIVO QUE AFECTÓ BIENES DE USO PÚBLICO -RINCON DE LOS ÁNGELES-, | O47: RINCON DE LOS ANGELES | P47: N/A | Q47: N/A | R47: ZONA DE CESIÓN | S47: 1-4875: 1-4876 | T47: KENNEDY | U47: N/N | V47: N/A | W47: N/A | X47: N/A | Y47: N/A | Z47: 26/02/2021 | AA47: N/A | AB47: N/A | AC47: SENTENCIA DE PRIMERA INSTANCIA LA CUAL FUE APELADA POR EL TERCERO INTERVINIENTE ESTA AL DESPACHO DEL TAC DESDE EL 21-06-2023 | AD47: EN CURSO | AE47: N/A | AF47: AL DESPACHO PARA ADMISIÓN DEL RECURSO DE APELACIÓN
A48: 419787 | B48: CONSTITUCIONAL | C48: 2013-00545 | D48: ACCION POPULAR | E48: 41527 | F48: JUZGADO 2 CIVIL DEL CIRCUITO DE BOGOTÁ | G48: MARIA FERNANDA MADIEDO SANCHEZ | H48: DADEP | I48: ORGANIZACIÓN LUIS CARLOS SARMIENTO ANGULO | J48: DIRECTA | K48: DEMANDADO | L48: ENTREGA ZONAS DE CESIÓN | M48: NA | N48: ZONAS DE CESION IGLESIA SAN CARLOS BORROMEO | O48: VILLA LUZ VI ETAPA | P48: NA | Q48: NA | R48: ZONA DE CESIÓN | S48: 1553 | T48: ENGATIVA | U48: 8981 | V48: NA | W48: NA | X48: NA | Y48: NA | Z48: NA | AA48: NA | AB48: NA | AC48: EL PROCESO SE ENCUENTRA AL DESPACHO PARA SENTENCIA CON FECHA DEL 01 DE SEPTIEMBRE DE 2021 DE ACUERDO A LO QUE SE EVIDENCIA EN LA RAMA JUDICIAL, POR LO CUAL SE REALIZARA SEGUIMIENTO PROCESAL, SIENDO LA UTIMA REVISION EL 16/11/2022 se revisa el 21-12-2022 y continua al despacho para sentencia. Se consulta el proceso el 15-6-2023 y sigue en el despacho para sentencia. sentencia niega pretensiones el 16-6-2023. se interpone recurso de apelacion el 11 de julio de 2023 se remite al Tribunal superior por recurso de apelacion- 27-11-2023 ingresa al despacho, se radica memorial impulso. auto de fecha 2024-05-07 Auto obedézcase y cúmplase LO RESUELTO POR EL SUPERIOR. | AD48: CON FALLO | AE48: SRI | AF48: CUMPLIMIENTO DE FALLO
A49: 523930 | B49: PENAL | C49: 2009-01098 | D49: PENAL | E49: 42389 | F49: JUZGADO 3 DE EJECUCIÓN DE PENAS | G49: JOSE AGUSTÍN AVENDAÑO | H49: DADEP COADYUVANTE ASESOR JURIDICO NOTARIA 68 BOGOTA | I49: SERGIO ALBERTO BERNAL BELLO | J49: DIRECTA | K49: INTERVINIENTE | L49: QUINTAS DE SOTAVENTO FRAUDE | M49: FALSEDAD EN DOCUMENTO PUBLICO - OBTENCIO DOCUMENTO PUBLICO FALSO - ESTAFA | N49: REGISTRO ORIP FALLO DE PERTENENCIA FALSO | O49: SOTAVENTO | P49: NA | Q49: NA | R49: ZONA DE CESIÓN | S49: 2589 | T49: CIUDAD BOLIVAR | U49: NA | V49: NA | W49: NA | X49: NA | Y49: NA | Z49: 42579 | AA49: 42690 | AB49: NA | AC49: Mediante orfeo 20204000014332 del 29/01/2020 Juzgado de EJECUCIÓN DE SENTENCIAS DE ACACIAS META INFORMA REDUCCIÓN DE PENA DE 2 MESES Se allega comunicación del Juzgado de Ejecución de Penas de Acacias Meta, manifestando que se concedió la libertad condicional a Sergio Bernal se envía memorial y copia el 10 de diciembre de 2020, | AD49: CON FALLO | AE49: N/A | AF49: EJECUCIÓN Y PENAS
A50: 479932 | B50: PENAL | C50: 2014-23132 | D50: PENAL | E50: 41885 | F50: FISCALIA 60 ESPECIALIZADO - UNIDAD DE FE PUBLICA Y ORDEN ECONÓMICO - TARDÍA ORDINARIO | G50: JOSE AGUSTÍN AVENDAÑO | H50: DADEP | I50: ISABEL SEGOVIA OSPINA | J50: DIRECTA | K50: DENUNCIANTE | L50: COMPARTIR BOCHICA | M50: OBTENCION DE DOCUMENTO PUBLICO FALSO | N50: ESCRITURA PUBLICA DE MEJORAS SOBRE PREDIO PUBLICO | O50: BOCHICA | P50: NA | Q50: NA | R50: ZONA DE CESIÓN | S50: 1539-3 | T50: ENGATIVA | U50: NA | V50: NA | W50: NA | X50: NA | Y50: NA | Z50: NA | AA50: NA | AB50: NA | AC50: SE ASISTE DE MANERA PRESENCIAL AL DESPACHO DE LA FISCAL DE CONOCIMIENTO E INDICA QUE PARA LA REVISIÓN DEL EXPEDIENTE DEBERÁ ASISTIRSE EL 14 DE MAYO DE 2024 A LAS 9:30AM, QUEDANDO PROGRAMADO EL TURNO PARA VERIFICACIÓN DEL ESTADO PROCESAL, INDICACIÓN DEL ESTADO ACTUAL DE LAS ORDENES EMITIDAS HASTA EL MOMENTO Y EL RESPECTIVO IMPULSO PROCESAL. | AD50: EN CURSO | AE50: N/A | AF50: INDAGACION
A51: 513957 | B51: CONSTITUCIONAL | C51: 2015-01062 | D51: ACCION POPULAR | E51: 42148 | F51: JUZGADO 31 CIVIL DEL CIRCUITO DE BOGOTÁ | G51: SHIRLEY AVELLANEDA PEÑA | H51: DADEP | I51: ASOCIACION DE VIVIENDA CAMINOS DE LA ESPERANZA - PROTECHO DE COLOMBIA - INVERSIONES CONCIVILES LTDA - SOCIEDAD FIDUCIARIA | J51: DIRECTA | K51: DEMANDADO | L51: ENTREGA Y ESCRITURACION CIUDADELA EL PORVENIR SUBA I ETAPA | M51: NA | N51: ENTREGA Y ESCRITURACION CIUDADELA EL PORVENIR SUBA I ETAPA | O51: CIUDADELA EL PORVENIR ETAPA I SUBA | P51: NA | Q51: NA | R51: ZONA DE CESIÓN | S51: 3346 | T51: SUBA | U51: 41680 | V51: NA | W51: NA | X51: NA | Y51: NA | Z51: NA | AA51: NA | AB51: NA | AC51: SENTENCIA PRIMERA INSTANCIA NIEGA PRETENSIONES " Así las cosas, se negarán las pretensiones de la demanda en contra de la ASOCIACIÓN PROTECHO DE COLOMBIA y la ASOCIACIÓN DE VIVIENDA CAMINOS DE ESPERANZA EN LIQUIDACIÓN, por cuánto no se probó que aquellas estén vulnerando el derecho colectivo al goce del espacio público, en tanto, ni siquiera existe certeza de cuál es ese espacio público (áreas, ubicación, mojones, etc.) que aquellas supuestamente están reteniendo, usurpando o se encuentran en mora de titularizar a favor del Distrito. MEMORANDO 20221100047843 DEL 19-07-2022 SRI SOLICITANDO ACTUALIZACIÒN INFORME TECNICO PARA ESTABLECER ESTRATEGIA JURIDICA. 2022-10-26 ARCHIVO DEFINITIVO. | AD51: CON FALLO | AE51: SRI | AF51: ARCHIVO DEFINITIVO
A52: 390260 | B52: CONTENCIOSO ADMINISTRATIVA | C52: 2012-00060 | D52: REPARACIÓN DIRECTA | E52: 41172 | F52: TRIBUNAL ADMINISTRATIVO DE CUNDINAMARCA SECCION TERCERA ORAL | G52: JOAN SEBASTIAN MARQUEZ ROJAS | H52: JOSE ALVARO BELTRAN URREGO | I52: DADEP - IDPAC - JUNTA DE ACCION COMUNAL CHUNIZA | J52: DIRECTA | K52: DEMANDADO | L52: ACCIDENTE EN SALON COMUNAL - CHUNIZA - HERIDO | M52: NA | N52: NA | O52: CHUNIZA | P52: NA | Q52: NA | R52: ZONA DE CESIÓN | S52: 1660-49 | T52: USME | U52: NA | V52: NA | W52: NA | X52: NA | Y52: 166998817 | Z52: 20/05/2020 | AA52: NA | AB52: NA | AC52: FALLO CONFIRMATORIO DE SEGUNDA INSTANCIA | AD52: CON FALLO | AE52: N/A | AF52: FALLO CONFIRMATORIO DE SEGUNDA INSTANCIA
A53: 255133 | B53: CONTENCIOSO ADMINISTRATIVA | C53: 2007-00102 | D53: EJECUTIVO | E53: 39204 | F53: JUZGADO 61 ADMINISTRATIVO | G53: JAMMER SAUL HERNANDEZ | H53: DADEP | I53: VICTOR HUGO PANESSO GOMEZ | J53: DIRECTA | K53: DEMANDADO | L53: INCUMPLIMIENTO CONTRATO ARRENDAMIENTO 0062-1993 | M53: NA | N53: INCUMPLIMIENTO CONTRATO ARRENDAMIENTO 0062-1993 | O53: NA | P53: 49479714 | Q53: NA | R53: BIEN FISCAL | S53: 2-440 | T53: SANTAFE | U53: NA | V53: NA | W53: NA | X53: NA | Y53: NA | Z53: 40193 | AA53: NA | AB53: NA | AC53: SEGUIMIENTO SECRETARÍA JURÍDICA - PROCESO DE REPRESENTACIÓN INDIRECTA | AD53: EN CURSO | AE53: N/A | AF53: CON SEGUIMIENTO CONSTANTE A LOS BIENES EN CABEZA DEL DEMANDADO PARA EL POSIBLE EMBARGO DE LOS MISMOS.
A54: 514409 | B54: CONTENCIOSO ADMINISTRATIVA | C54: 2015-01859 | D54: REPARACIÓN DIRECTA | E54: 42240 | F54: TRIBUNAL ADMINISTRATIVO DE CUNDINAMARCA - SECCION TERCERA | G54: JOAN SEBASTIAN MARQUEZ ROJAS | H54: LUIS EDUARDO RODRIGUEZ | I54: ALCALDIA MAYOR - ALCALDIA LOCAL DE CIUDAD BOLIVAR - DADEP | J54: DIRECTA | K54: DEMANDADO | L54: OCUPACION DE PROPIEDAD PRIVADA CON SALON COMUNAL | M54: NA | N54: OCUPACION DE PROPIEDAD PRIVADA CON SALON COMUNAL | O54: NA | P54: NA | Q54: NA | R54: ZONA DE CESIÓN | S54: 1683-53 | T54: CIUDAD BOLIVAR | U54: NA | V54: NA | W54: NA | X54: 159.8 | Y54: 344727500 | Z54: 42949 | AA54: 22/05/2024 | AB54: NA | AC54: CONDÉNASE en costas de esta instancia a la parte demandante, que serán liquidadas de manera concentrada por el Tribunal Administrativo de Cundinamarca de acuerdo con el artículo 366 del Código General del Proceso, teniéndose en cuenta la fijación de agencias en derecho a favor de la parte demandada por la suma de 0.1% del valor total de las pretensiones negadas. hacer seguimiento a la liquidación de las costas en el tribunal, con el auto iniciar cobro persuasivo | AD54: CON FALLO | AE54: N/A | AF54: SENTENCIA DE SEGUNDA INSTANCIA.
A55: 701116 | B55: CIVIL | C55: 2021-00299 | D55: PERTENENCIA | E55: 44477 | F55: JUZGADO 36 CIVIL DEL CIRCUITO DE BOGOTA | G55: MARIA FERNANDA CRUZ | H55: JESUS ANTONIO MARTINEZ RIAÑO | I55: JOSEFINA CORREDOR DE CORREDOR | J55: DIRECTA | K55: INTERVINIENTE | L55: PRESCRIPCIÓN ADQUISITIVA DE DOMINIO arrera 7 B No. 9 – 22 Barrio Egipto, CHIP AAA0144RNKC | M55: NA | N55: PRESCRIPCIÓN ADQUISITIVA DE DOMINIO arrera 7 B No. 9 – 22 Barrio Egipto, CHIP AAA0144RNKC | O55: N/A | P55: N/A | Q55: N/A | R55: ZONA DE CESIÓN | S55: 1693-11 | T55: CANDELARIA | U55: N/A | V55: N/A | W55: N/A | X55: N/A | Y55: N/A | Z55: N/A | AA55: N/A | AB55: N/A | AC55: VINCULACIÓN PROCESO | AD55: EN CURSO | AE55: N/A | AF55: NOTIFICACIONES, se espera notificaión remisión link proceso
A56: 607901 | B56: PENAL | C56: 2019-31233 | D56: PENAL | E56: 43670 | F56: FISCALÍA 103 SECIONAL UNIDAD FE PÚBLICA Y ORDEN ECONCÓMICO | G56: JOSE AGUSTÍN AVENDAÑO | H56: DADEP | I56: MARIA STELLA ALVAREZ MARIELA GÓMEZ | J56: DIRECTA | K56: DENUNCIANTE | L56: BARRIO SAN FRANCISCO RURAL | M56: FRAUDE PROCESAL FALSEDAD DOCUMENTO PÚBLICO OBTENCIÓN DOCUMENTO PÚBLICO FALSO | N56: Fiscal se encuentra revisando el expediente para tomar decisiones de ordenes a PJ o en su defecto evaluando una posible prescripción | O56: BARRIO SAN FRANCISCO RURAL | P56: N/A | Q56: N/A | R56: N/A | S56: 1693-37 | T56: CHAPINERO | U56: N/A | V56: N/A | W56: N/A | X56: N/A | Y56: N/A | Z56: N/A | AA56: N/A | AB56: N/A | AC56: SEGUIMIENTO A ORDENES A PJ, SE TRASLADA PROCESO A FISCALÍA 277 SECCIONAL , A QUIEN SE LE SOLICITARA LA SUSPENSIÓN DEL PODER DISPOSITIVO DEL BIEN DEL DISTRITO | AD56: EN CURSO | AE56: N/A | AF56: INDAGACIÓN
A57: 516361 | B57: CONTENCIOSO ADMINISTRATIVA | C57: 2015-00428 11001333603120150042800 | D57: RESTITUCION DE INMUEBLE ARRENDADO | E57: 42284 | F57: JUZGADO 31 - ADMINISTRATIVO DE ORALIDAD | G57: GENARO SALAZAR GONZALEZ | H57: DADEP | I57: MARIA ARACELY FORERO | J57: DIRECTA | K57: DEMANDADO | L57: TERMINACION CTO ARRENDAMIENTO SOBRE PREDIO UBICADO CALLE 23 1 70 | M57: NA | N57: TERMINACION CTO ARRENDAMIENTO SOBRE PREDIO UBICADO CALLE 23 1 70 | O57: PAZ CCENTRO | P57: NA | Q57: NA | R57: ZONA DE CESIÓN | S57: 1699-35 | T57: SANTAFE | U57: 410.16 | V57: NA | W57: NA | X57: NA | Y57: NA | Z57: NA | AA57: NA | AB57: NA | AC57: FUERON NOTIFICADOS LOS DEMANDADOS | AD57: EN CURSO | AE57: N/A | AF57: SENTENCIA A FAVOR DEL DADEP 6-11-2024
A58: 981906 | B58: CIVIL | C58: 2017-00742 | D58: DESLINDE Y AMOJONAMIENTO | E58: 44899 | F58: JUZGADO 6 CIVIL CIRCUITO DE BOGOTA | G58: MARIA FERNANDA CRUZ | H58: JULIAN JARAMILLO CORTES | I58: DISTRITO CAPITAL - DADEP | J58: DIRECTA | K58: DEMANDADO | L58: FIJACIÓN MOJONES SEÑALAMIENTO DE LINDEROS | M58: NA | N58: FIJACIÓN MOJONES SEÑALAMIENTO DE LINDEROS- COLINDA CON PREDIO PÚBLICO | O58: DDESARROLLO LEGALIZADO EL CARMEN | P58: N/A | Q58: N/A | R58: ZONA DE CESIÓN | S58: 1743-4 | T58: FONTIBON | U58: N/A | V58: N/A | W58: N/A | X58: N/A | Y58: N/A | Z58: N/A | AA58: N/A | AB58: N/A | AC58: SE CONTESTO LA DEMANDA EL 13 DE ABRIL DEL 2022 , SE ESPERA PRONUNCIAMIENTO DEL JUZGADO FRENTE A EXCEPCIONES PRESENTADOS POR UAECD | AD58: EN CURSO | AE58: N/A | AF58: NOTIFICACIONES
A59: 253519 | B59: CIVIL | C59: 2007-00242 | D59: REIVINDICATORIO | E59: 39476 | F59: JUZGADO 51 CIVIL DEL CIRCUITO DE BOGOTA | G59: JAMMER SAUL HERNANDEZ | H59: JULIO ENRIQUE RAMOS HERNANDEZ Y OTROS | I59: DADEP Y OTROS | J59: DIRECTA | K59: DEMANDADO | L59: REIVINDICAR PREDIO DONDE FUNCIONA COLEGIO DISTRITAL ESTRELLA DEL SUR | M59: NA | N59: REIVINDICAR PREDIO DONDE FUNCIONA COLEGIO DISTRITAL ESTRELLA DEL SUR | O59: NA | P59: NA | Q59: NA | R59: ZONA DE CESIÓN | S59: 1683-51 | T59: CIUDAD BOLIVAR | U59: 1235242 | V59: NA | W59: NA | X59: 1077 | Y59: NA | Z59: 45109 | AA59: NA | AB59: NA | AC59: AUTO DEL 06-05-2024 DECLARA DESIERTO EL RECURSO DE APELACIÓN | AD59: EN CURSO | AE59: N/A | AF59: CON SENTENCIA DE PRIMERA INSTANCIA FAVORABLE DEL 07-02-2023 EJECUTORIADO PENDIENTE REGISTRO DE LA SENTENCIA.
A60: 617718 | B60: CONTENCIOSO ADMINISTRATIVA | C60: 2019-00107 11001333400120190010700 | D60: NULIDAD SIMPLE | E60: 43687 | F60: JUZGADO 1 ADMINISTRATIVO DEL CIRCUITO DE BOGOTÁ | G60: JOAN SEBASTIAN MARQUEZ ROJAS | H60: ROBIERTTH ANDRÉS REYES GÓMEZ | I60: ALCALDÍA LOCAL DE USAQUÉN - DADEP | J60: DIRECTA | K60: VINCULADO | L60: NULIDAD DE LA RESOLUCIÓN NO 3684 DE FECHA 27 12 2010 PROFERIDA POR LA ALCALDÍA LOCAL DE USAQUEN | M60: N/A | N60: SE DECLARE LA NULIDAD DE LA RESOLUCIÓN NO 3684 DE FECHA 27-12-2010 MEDIANTE EL CUAL LA ALCALDÍA LOCAL DE USAQUEN REGISTRÓ LA PERSONERÍA JURÍDICA DE LA UNIDAD INMOBILIARIA CERRADA MARANTÁ SECTOR 6 ENTIDAD SIN ANIMO DE LUCRO UBICADA EN LA CALLE 189 NO 20-18 | O60: UNIDAD INMOBILIARIA CERRADA MARANTÁ SECTOR 6 | P60: N/A | Q60: N/A | R60: N/A | S60: 176-59 176-20 176-47 176-8 176-4 176-3 | T60: N/A | U60: N/A | V60: N/A | W60: N/A | X60: N/A | Y60: N/A | Z60: N/A | AA60: N/A | AB60: N/A | AC60: FIJACIÓN DE AUDIENCIA INICIAL | AD60: EN CURSO | AE60: N/A | AF60: AUDIENCIA INICIAL
A61: 454983 | B61: CONSTITUCIONAL | C61: 2014-00280 | D61: ACCION POPULAR | E61: 41775 | F61: JUZGADO 36 CIVIL DEL CIRCUITO DE BOGOTÁ | G61: SHIRLEY AVELLANEDA PEÑA | H61: DADEP | I61: COOPERATIVA MULTIACTIVA DEL CENTRO INTERNACIONAL DE LA UNION COOPCILDUN | J61: DIRECTA | K61: DEMANDADO | L61: ENTREGA Y ESCRITURACION ZONAS DE CESION URBANIZACION YERREYON | M61: NA | N61: ENTREGA Y ESCRITURACION ZONAS DE CESION URBANIZACION YERREYON | O61: YERREYON | P61: NA | Q61: NA | R61: ZONA DE CESIÓN | S61: 1771-1 1771-2 | T61: SUBA | U61: 1.486,00 | V61: NA | W61: NA | X61: NA | Y61: NA | Z61: PACTO DE CUMPLIMIENTO 28-5-15 | AA61: NA | AB61: DEMANDADO ENTREGAR Y ESCRITURAR | AC61: A PARTIR DE PACTO DE CUMPLIMIENTO INCUMPLIDO SE SOLICITÓ DESARCHIVO DEL PROCESO E INCIDENTE DE DESACATO - PREVIO ABRIR INCIDENTE, JUEZ REQUIRIÓ AL URBANIZADOR. En tramite de cumplimiento del pacto de cumplimiento por parte de los urbanizadores condenados. 2023-07-06 en rama judicial sigue sin movientos | AD61: EN CURSO | AE61: SRI | AF61: INCIDENTE DESACATO FRENTE A PACTO DE CUMPLIMIENTO
A62: 269314 | B62: CIVIL | C62: 2007-00354 | D62: PERTENENCIA | E62: 39304 | F62: JUZGADO 7 CIVIL DEL CIRCUITO DE ORALIDAD DE BOGOTÁ | G62: JAMMER SAUL HERNANDEZ | H62: José Hernando Jiménez - Inversiones J&N Pineda - Bertha Ligia López Rivera - Claudia Esperanza Calderón Villamil | I62: Fundación Empresa Privada Compartir - Personas Indeterminadas | J62: DIRECTA | K62: INTERVINIENTE | L62: Declaración de PERTENENCIA a favor de unos particulares por prescripción adquisitiva de dominio del inmueble ubicado entre las Calles 89A a la Calle 90 A y entre las carreras 103C y AK 95 y 96 - ESPACIO PUBLICO - ALO BACHUE | M62: NA | N62: Declaración de PERTENENCIA a favor de unos particulares por prescripción adquisitiva de dominio del inmueble ubicado entre las Calles 89A a la Calle 90 A y entre las carreras 103C y AK 95 y 96 - ESPACIO PUBLICO - ALO BACHUE | O62: BACHUE | P62: NA | Q62: NA | R62: ZONA DE CESIÓN | S62: 1539 | T62: ENGATIVA | U62: NA | V62: NA | W62: NA | X62: 3600 | Y62: NA | Z62: 42889 | AA62: 20/10/2017 | AB62: NA | AC62: NOTIFICACION DE MANDAMIENTO DE PAGO COSTAS PROCESALES. SE RADICARON OFICIOS DE EMBARGO UNA VEZ DECTRETADAS MEDIDAS CAUTELARES. SE RADICAN OFICIOS CON EMBARGO DE CUENTAS. | AD62: CON FALLO | AE62: N/A | AF62: LIBRA MANDAMIENTO DE PAGO POR 750.000 DE COSTAS -NOTIFICACIÓN DE EMBARGOS.
A63: 744472 | B63: CIVIL | C63: 2022-01199 11001400302920220119900 | D63: PERTENENCIA | E63: 44907 | F63: JUZGADO 29 CIVIL MUNICIPAL | G63: GENARO SALAZAR GONZALEZ | H63: CHENQUE MEYER AREVALO HERRERA | I63: ARMANDO ACUÑA HERNANDEZ - PERSONAS INDETERMINADAS | J63: DIRECTA | K63: INTERVINIENTE | L63: Consultado el mapa digital de la Defensoría del Espacio Público – SIGDEP y el Sistema de Información de la Defensoría del Espacio Público-SIDEP, por la nomenclatura CL 63A SUR 75J 00 y el CHIP AAA0148ASLF, el predio se traslapa con áreas que se encuentran incluidas como bienes destinados al uso público en el Inventario General de Espacio Público y Bienes Fiscales del Sector Central del Distrito Capital, a cargo del Departamento Administrativo de la Defensoría del Espacio Público y se identifican con los RUPI 184-2, 184-6, 3036-16 y 3036-65, de los cuales se adjuntan las certificaciones correspondientes | M63: N/A | N63: Consultado el mapa digital de la Defensoría del Espacio Público – SIGDEP y el Sistema de Información de la Defensoría del Espacio Público-SIDEP, por la nomenclatura CL 63A SUR 75J 00 y el CHIP AAA0148ASLF, el predio se traslapa con áreas que se encuentran incluidas como bienes destinados al uso público en el Inventario General de Espacio Público y Bienes Fiscales del Sector Central del Distrito Capital, a cargo del Departamento Administrativo de la Defensoría del Espacio Público y se identifican con los RUPI 184-2, 184-6, 3036-16 y 3036-65, de los cuales se adjuntan las certificaciones correspondientes | O63: LOS TRES REYES | P63: N/A | Q63: N/A | R63: ZONA DE CESIÓN | S63: 184-2; 184-6; 3036-16; 3036-65 | T63: CIUDAD BOLIVAR | U63: 723.9 | V63: N/A | W63: N/A | X63: N/A | Y63: N/A | Z63: N/A | AA63: N/A | AB63: N/A | AC63: ADMISION DE LA INTERVENCION COMO TERCEROS INTERESADOS ARTÍCULO 63 CGP | AD63: EN CURSO | AE63: N/A | AF63: VINCULACION DE LOS SUJETOS PROCESALES
A64: 701108 | B64: CIVIL | C64: 2020-00911 | D64: NULIDAD DE ESCRITURA PÚBLICA | E64: 44497 | F64: JUZGADO 47 CIVIL MUNICIPAL DE BOGOTA | G64: MARIA FERNANDA CRUZ | H64: DISTRITO CAPITAL - DADEP | I64: PROYECTOS Y CONSTRUCCIONES PROURBYCON Y OTROS | J64: DIRECTA | K64: DEMANDADO | L64: NULIDAD ESCRITURA PÚBLICA No. 4494 DEL 13 DE DICIEMBRE DEL 1993, 816 DEL 4 DE MARZO DEL 1994, 4234 DEL 3 DE NOVIMEBRE DE 199, 5961 DEL 23 DE DICIEMBRE D 1996, 4615 DEL 10 DE NOVIEMBRE DE 1998 DE LA NOTARIA 13 DEL CIRCULO DE BOGOTÁ | M64: NA | N64: OBTENER LA NULIDAD POR OBJETO ILICITO DE LAS ESCRITURAS PÚBLICAS | O64: NOGALES DE SUBA | P64: N/A | Q64: N/A | R64: ZONA DE CESIÓN | S64: 1928 | T64: SUBA | U64: 60MTS2 | V64: N/A | W64: N/A | X64: N/A | Y64: N/A | Z64: N/A | AA64: N/A | AB64: N/A | AC64: ADMISIÓN DEMANDA, NOTIFICACIONES | AD64: EN CURSO | AE64: N/A | AF64: NOTIFICACIONES
A65: 462173 | B65: PENAL | C65: 2014-00869 | D65: PENAL | E65: 41648 | F65: FISCALIA 365 SUB UNIDAD DE TIERRAS | G65: JOSE AGUSTÍN AVENDAÑO | H65: DADEP | I65: MANUEL PARRA PATIÑO | J65: DIRECTA | K65: DENUNCIANTE | L65: NOGALES DE SUBA | M65: FRAUDE PROCESAL - OBTENCION DOCUMENTO PUBLICO FALSO | N65: VENTA DE ZONA VERDE POR PARTE DE PROURBYCON | O65: NOGALES DE SUBA | P65: NA | Q65: NA | R65: ZONA DE CESIÓN | S65: 1928-14 | T65: SUBA | U65: NA | V65: NA | W65: NA | X65: NA | Y65: NA | Z65: NA | AA65: NA | AB65: NA | AC65: SEGUIMIENTO PROCESAL - EXPEDIDAS ORDENES A POLICÍA JUDICIAL EN SEGUIMIENTO A SU EJECUCIÓN. | AD65: EN CURSO | AE65: N/A | AF65: INDAGACIÓN
A66: 597928 | B66: CIVIL | C66: 2018-00471 | D66: NULIDAD DE ESCRITURA PÚBLICA | E66: 43333 | F66: JUZGADO 3 CIVIL DEL CIRCUITO DE ORALIDAD DE BOGOTÁ | G66: MARIA FERNANDA CRUZ | H66: AGRUPACION PRADERA DE SUBA II ETAPA PH | I66: DISTRITO CAPITAL | J66: DIRECTA | K66: DEMANDADO | L66: NULIDAD DE EP POR OBJETO ILÍCITO | M66: N/A | N66: LA AGRUPACION DE VIVIENDA PRADERA DE SUBA ETAPA I P.H. PRESENTA DEMANDA PARA OBTENER LA NULIDAD DE LAS ESCRITURAS PUBLICAS 3541 DEL 7 DE NOVIEMBRE DE 1990 NOT. 30 DE BOGOTA, 0511 DE 09 DE ABRIL DE 2004 , ESC 1618 DEL 16 DE JUNIO DE 2004 AMBAS DE NOT 59 DE BOGOTA, ESC 5525 DEL 29 DE OCTUBRE DE 1992 NOT 7 DE BOGOTA Y LA CANCELACION DE LOS FMI 50N 20067981, 50N-936549, EN VIRTUD QUE EL CONSTRUCTOR VENDIÓ UNA ZONA COMUN DE PROPIEDAD DE LA AGRUPACION | O66: PRADERA DE SUBA II ETAPA P.H | P66: N/A | Q66: N/A | R66: ZONA DE CESIÓN | S66: 1953-1 AL 5 | T66: SUBA | U66: N/A | V66: N/A | W66: N/A | X66: N/A | Y66: N/A | Z66: N/A | AA66: N/A | AB66: N | AC66: SE ESPERA SE FIJE FECHA PRIMERA AUDIENCIA DE TRÁMITE | AD66: EN CURSO | AE66: N/A | AF66: EN CURSO
A67: 271844 | B67: CIVIL | C67: 2007-00359 | D67: REIVINDICATORIO | E67: 39433 | F67: JUZGADO 29 CIVIL DEL CIRCUITO DE BOGOTÁ | G67: JAMMER SAUL HERNANDEZ | H67: HECTOR JOSE BUITRAGO Y OTRO | I67: DADEP - SEC EDUCACION | J67: DIRECTA | K67: DEMANDADO | L67: COBRO DE COSTAS - PROCESO INICIAL PRETENDIA REIVINDICAR PREDIO DONDE FUNCIONA COLEGIO RODRIGO TRIANA | M67: NA | N67: COBRO DE COSTAS - PROCESO INICIAL PRETENDIA REIVINDICAR PREDIO DONDE FUNCIONA COLEGIO RODRIGO TRIANA | O67: NA | P67: 10000000 | Q67: NA | R67: ZONA DE CESIÓN | S67: 3012-9 | T67: KENNEDY | U67: NA | V67: NA | W67: NA | X67: NA | Y67: NA | Z67: 40954 | AA67: 41166 | AB67: NA | AC67: SEGUIMIENTO AL COBRO DE COSTAS, REALIZAR CONSULTA DE BIENES PARA INFORMAR AL DESPACHO JUDICIAL DE HALLARSE. | AD67: EN CURSO | AE67: N/A | AF67: COSTAS POR 10 MILLONES DE PESOS-SE TRAMITAN OFICIOS DE EMBARGO.
A68: 768030 | B68: CONTENCIOSO ADMINISTRATIVA | C68: 2023-00622 | D68: CONTROVERSIA CONTRACTUAL | E68: 45187 | F68: TRIBUNAL ADMINISTRATIVO DE CUNDINAMARCA | G68: JOAN SEBASTIAN MARQUEZ ROJAS | H68: DADEP | I68: MINISTERIO DE VIVIENDA Y FONDO ROTATORIO REGISTRADURIA | J68: DIRECTA | K68: DEMANDADO | L68: AFECTACION DE DERECHOS COLECTIVOS-BIEN DE USO PUBLICO-FISCAL | M68: N/A | N68: CON LA ESCRITURA PÚBLICA 959 DEL 31 DE MARZO DE 1995 DE LA NOTARIA 22 SE REALIZÓ UNA VENTA DE UN INMUEBLE ENTRE EL INSTITUTO NACIONAL DE VIVIENDA DE INTERÉS Y REFORMA URBANA “INURBE” Y EL FONDO ROTATORIO DE LA REGISTRADURÍA NACIONAL DEL ESTADO CIVIL UBICADO EN LA CIUDAD DE BOGOTÁ, CALLE 40 SUR NÚMERO 77-53/51 Y CARRERA 77B NÚMERO 40-06/08 CON UN ÁREA TOTAL DE 1.026.60 MTS2 DE LA URBANIZACIÓN CIUDAD KENNEDY, LA SUBDIRECCIÓN DE REGISTRO INMOBILIARIO DE ESTE DEPARTAMENTO ADMINISTRATIVO DE LA DEFENSORÍA DEL ESPACIO MEDIANTE EL MEMORANDO 20232030025933 PROCEDIÓ A REALIZAR UN ESTUDIO TÉCNICO-JURÍDICO DEL PREDIO IDENTIFICADO CON EL CHIP AAA0043XLKC Y EL FOLIO DE MATRÍCULA INMOBILIARIA 50S-40233691. EN DICHO ESTUDIO SE ENCONTRÓ QUE ESTE PREDIO FUE ADQUIRIDO POR EL FONDO ROTATORIO DE LA REGISTRADURÍA NACIONAL MEDIANTE LA ESCRITURA PÚBLICA NO. 959 DE MARZO 31 DE 1995, OTORGADA EN LA NOTARÍA VEINTIDÓS (22) DE BOGOTÁ. COMO SE CONCLUYE EN EL ESTUDIO TÉCNICO JURÍDICO QUE SE ADJUNTA, SE PRESENTA DOBLE TITULARIDAD RESPECTO A LOS PREDIOS RELACIONADOS EN EL MISMO, SIENDO TRANSFERIDOS EN EL AÑO 1967 A FAVOR DEL DISTRITO Y EN EL AÑO 1995 SE TRANSFIRIERON NUEVAMENTE AL FONDO ROTATORIO DE LA REGISTRADURÍA NACIONAL. EN EL ESTUDIO TÉCNICO QUE SE ADELANTÓ SE EVIDENCIÓ QUE EXISTE UN TRASLAPE ENTRE LAS ÁREAS ADQUIRIDAS POR MEDIO DE LA ESCRITURA NO. 5206 DE 15 DE NOVIEMBRE DE 1967 (RUPIS 2- 72, 2-923, 2-924, 2-925, 2-926, 2-927 Y 2-928), Y EL ÁREA DE COMPRA EN EL ARIO DE 1995 POR PARTE DEL FONDO ROTATORIO DE LA REGISTRADURÍA NACIONAL. | O68: CIUDAD KENNEDY CENTRAL | P68: N/A | Q68: N/A | R68: BIEN FISCAL | S68: 2-.72 | T68: KENNEDY | U68: 43 MTS2 | V68: N/A | W68: N/A | X68: N/A | Y68: N/A | Z68: EN TRAMITE | AA68: EN TRAMITE | AB68: EN TRAMITE | AC68: EL 27 DE SEPTIEMBRE DE 2024, SE DESCORRE TRASLADO DE EXCEPCIONES POR PARTE DEL DADEP | AD68: EN CURSO | AE68: SRI | AF68: PRONUNCIAMIENTO SOBRE LAS EXCEPCIONES Y FIJACIÓN DE AUDIENCIA INICIAL.
A69: 417849 | B69: CONSTITUCIONAL | C69: 2013-00517 11001310303820130051700 | D69: ACCION POPULAR | E69: 41477 | F69: JUZGADO 38 CIVIL DEL CIRCUITO DE BOGOTÁ | G69: MARIA FERNANDA MADIEDO SANCHEZ | H69: DADEP | I69: LUS DIANA REYES ALONSO | J69: DIRECTA | K69: DEMANDADO | L69: ENTREGA ZONAS DE CESIÓN | M69: NA | N69: ZONAS DE CESION SAN FELIPE EL DORADO | O69: SAN FELIPE EL DORADO | P69: NA | Q69: NA | R69: ZONA DE CESIÓN | S69: 2086-18 2086-19 | T69: FONTIBON | U69: =2001.59+1802.87 -> 3804.46 | V69: NA | W69: NA | X69: NA | Y69: NA | Z69: NA | AA69: NA | AB69: NA | AC69: SEGUIMIENTO PROCESAL - ALEGATOS DE CONCLUSIÓN PRESENTADOS - A LA ESPERA DE FALLO DE PRIMERA INSTANCIA. SUSPENDIDO POR PREJUDICIALIDAD POR EL PROCESO 2013-01962 2023-07-06 al despacho desde el 2020 Se consulto el proceso en el Consejo de Estado donde surte recurso de apelacion, el cual ingreso al despacho el 29 de mayo de 2023, este estado se verifico en rama el 15-11-2023. se revisa estado 23-1-2024 sin novedad. al despacho 26-2-2024 se consulta el 11 -3-2024. 26-2-2024 al despacho para sentencia en el - CONSEJO DE ESTADO - SECCIÓN PRIMERA - BOGOTÁ SIN NOEVEDAD PROCESAL 29-5-2024- se revisa proceso 3-2-2025 proceso sin novedad procesal, | AD69: EN CURSO | AE69: SRI | AF69: SUSPENDIDO POR PREJUDICIALIDAD
A70: 55135 | B70: CIVIL | C70: 2002-01056 11001310303420020105601 | D70: PERTENENCIA | E70: 37575 | F70: JUZGADO 41 - CIVIL DEL CIRCUITO DE ORALIDAD | G70: GENARO SALAZAR GONZALEZ | H70: Juan de Jesús Gaitán Mora - María Leonilde Torres Gaitán - Luz Diana Reyes Alonso (Cesionaria) | I70: Urbanizadora San Felipe Ltda - Personas Indeterminadas | J70: DIRECTA | K70: INTERVINIENTE | L70: PERTENENCIA BIENES SAN FELIPE EL DORADO | M70: NA | N70: PERTENENCIA BIENES SAN FELIPE EL DORADO | O70: SAN FELIPE EL DORADO | P70: NA | Q70: NA | R70: ZONA DE CESIÓN | S70: 2086-19 | T70: FONTIBON | U70: NA | V70: NA | W70: NA | X70: 2001 | Y70: NA | Z70: NA | AA70: NA | AB70: NA | AC70: SE PRESENTO DEMANDA AD EXCLUYENTE POR PARTE DEL DADEP EL 15 DE NOVIEMBRE DEL 2022 | AD70: EN CURSO | AE70: N/A | AF70: AUTO ORDENA EMPLAZA 09-09-2024 A CARGO DEL DEMANDANTE
A71: 429265 | B71: CONTENCIOSO ADMINISTRATIVA | C71: No. 25000234100020130196200 | D71: NULIDAD Y RESTABLECIMIENTO DEL DERECHO | E71: 41540 | F71: CONSEJO DE ESTADO - SECCION PRIMERA | G71: JOAN SEBASTIAN MARQUEZ ROJAS | H71: LUZ DIANA REYES | I71: SEC PLANEACION - CONTRALORIA DE BOGOTA - DADEP | J71: DIRECTA | K71: INTERVINIENTE | L71: NULIDAD RESOLUCIONES SEC PLANEACION POR PRESUNTA VIOLACION DEBIDO PROCESO - SAN FELIPE EL DORADO | M71: NA | N71: NULIDAD RESOLUCIONES SEC PLANEACION POR PRESUNTA VIOLACION DEBIDO PROCESO - SAN FELIPE EL DORADO | O71: SAN FELIPE EL DORADO | P71: NA | Q71: NA | R71: ZONA DE CESIÓN | S71: 2086-19 | T71: FONTIBON | U71: NA | V71: NA | W71: NA | X71: 1836.93 | Y71: 287885975 | Z71: 43103 | AA71: NA | AB71: NA | AC71: SENTENCIA DE SEGUNDA INSTANCIA | AD71: EN CURSO | AE71: N/A | AF71: AL DESPACHO PARA FALLO
A72: 289508 | B72: CIVIL | C72: 2007-00381 | D72: REIVINDICATORIO | E72: 39279 | F72: JUZGADO 46 CIVIL DEL CIRCUITO | G72: JAMMER SAUL HERNANDEZ | H72: DADEP | I72: JOSE RAFAEL GARZON GUTIERREZ Y OTRO | J72: DIRECTA | K72: DEMANDADO | L72: RESTITUCION DE BIEN FISCAL2-76 OCUPADO BARRIO CALVO SUR | M72: NA | N72: RESTITUCION DE BIEN FISCAL2-76 OCUPADO BARRIO CALVO SUR | O72: NA | P72: NA | Q72: NA | R72: BIEN FISCAL | S72: 2-76 | T72: SAN CRISTOBAL | U72: 234.2 | V72: NA | W72: NA | X72: NA | Y72: NA | Z72: 43888 | AA72: NA | AB72: NA | AC72: SENTENCIA DE PRIMERA Y SEGUNDA INSTANCIA FAVORABLE A ESPERA DE COMISORIO PARA ENTREGA DE PREDIO | AD72: EN CURSO | AE72: N/A | AF72: SE RADICA SOLICITUD DE DESPACHO COMISORIO AL JUZGADO 87 CIVIL MUNICIPAL AUDIENCIA PARA EL 11-12-2024.
A73: 557345 | B73: CIVIL | C73: 2016-00430 11001400304620160043000 | D73: RESTITUCIÓN DE TENENCIA | E73: 42850 | F73: JUZGADO 46 CIVIL MUNICIPAL | G73: GENARO SALAZAR GONZALEZ | H73: DADEP | I73: CARMEN ROSA BARON Y ROGELIO MORALES | J73: DIRECTA | K73: DEMANDADO | L73: RESTITRUCION INMUEBLE SANTA FE CARRERA 3 CON CALLE 26 | M73: NA | N73: RESTITUCIÓN INMUEBLE SANTA FE CARRERA 3 CON CALLE 26 | O73: N/A | P73: N/A | Q73: N/A | R73: BIEN FISCAL | S73: 2-1013 | T73: SANTAFE | U73: 321.16 | V73: N/A | W73: N/A | X73: N/A | Y73: N/A | Z73: N/A | AA73: N/A | AB73: N/A | AC73: EL PROCESO FUE ENVIADO AL JUZGADO 46 CIVIL MUNICIPAL | AD73: EN CURSO | AE73: N/A | AF73: SENTENCIA A FAVOR DE LA ENTIDAD 30-09-2024
A74: 742520 | B74: CIVIL | C74: 2018-00406 11001310303620180040600. | D74: NULIDAD DE ESCRITURA PÚBLICA | E74: 43315 | F74: JUZGADO 36 CIVIL DEL CIRCUITO | G74: GENARO SALAZAR GONZALEZ | H74: ALFREDO MATTOS HURTADO | I74: ANIBAL TORRES RIOS, MARIA FERNANDA RODRIGUEZ CUERVO | J74: DIRECTA | K74: INTERVINIENTE | L74: BIENES DE USO PUBLICO | M74: N/A | N74: INTERVENCION EXCLUYENTE DE DECLARATIVO DE NULIDAD ABSOLUTA DE ESCRITURAS PUBLICAS CONFORME A LOS TÉRMINOS SEÑALADOS EN EL ARTÍCULO 1740 Y S.S. DEL CÓDIGO CIVIL, EN CONTRA DE LOS SEÑORES ALFREDO MATTOS HURTADO Y OTROS, POR LAS IRREGULARIDADES PRESENTADAS EN LA SUSCRIPCIÓN DE LAS ESCRITURAS PÚBLICAS 313 DEL 21 DE MAYO DEL 2014 OTORGADA EN LA NOTARIA ÚNICA DE TABIO CUNDINAMARCA; 310 DEL 4 DE AGOSTO DEL 2014 OTORGADA EN LA NOTARIA ÚNICA DE TENJO CUNDINAMARCA; 362 DEL 9 DE SEPTIEMBRE DEL 2014 OTORGADA EN LA NOTARIA ÚNICA DE TENJO CUNDINAMARCA Y 443 DEL 12 DE JULIO DEL 2016 OTORGADA EN LA NOTARIA ÚNICA DE SUBACHOQUE, CON LO CUAL SE AFECTÓ UN PREDIO FISCAL DEL DISTRITO CAPITAL IDENTIFICADO CON AL RUPI 2-1049 DENOMINADO EL REFUGIO QUE CUENTA CON UNA EXTENSIÓN DE 111.926,68 M2 E IDENTIFICADO CON EL FOLIO DE MATRÍCULA INMOBILIARIA 050C-1810573. | O74: EL REFUGIO | P74: N/A | Q74: N/A | R74: BIEN DE USO PUBLICO | S74: 2-1049 | T74: ENGATIVA | U74: 111.926,68 M2 E | V74: N/A | W74: N/A | X74: N/A | Y74: N/A | Z74: EN TRAMITE | AA74: EN TRAMITE | AB74: N/A | AC74: SE PRESENTO DEMANDA AD EXCLUDENDUM ART 63 CGP, PROCESO RELACIONADO CON EL DE NULIDAD DE E.P. 2023-00016 | AD74: EN CURSO | AE74: N/A | AF74: DESPACHO 16-07-2024 PARA REPROGRAMAR AUDIENCIA
A75: 731366 | B75: CIVIL | C75: 2023-00016 11001310305120230001600 | D75: NULIDAD DE ESCRITURA PÚBLICA | E75: 45231 | F75: JUZGADO 51 CIVIL DEL CIRCUITO | G75: GENARO SALAZAR GONZALEZ | H75: DEPARTAMENTO ADMINISTRATIVO DE LA DEFENSORIA DEL ESPACIO PUBLICO | I75: SECRETARIA DE AMBIENTE/ ALFREDO MATTOS Y OTROS | J75: DIRECTA | K75: DEMANDADO | L75: NULIDAD DE ESCRITURA PUBLICA | M75: N/A | N75: MEDIANTE LA ESCRITURA PÚBLICA 1687 DEL 24 DE JUNIO DEL 2004 DE LA NOTARIA 36 DEL CÍRCULO DE BOGOTÁ EL ENTONCES DEPARTAMENTO ADMINISTRATIVO DEL MEDIO AMBIENTE (DAMA) HOY SECRETARÍA DISTRITAL DE AMBIENTE DECIDIÓ SEGREGAR MATERIALMENTE EL PREDIO DENOMINADO LA PONDEROSA REGISTRADO EN EL FOLIO DE MATRÍCULA INMOBILIARIA 50C-1322137 DANDO ORIGEN A TRES PREDIOS. A FAVOR DE MATTOS HURTADO ALFREDO ADQUIRIDO MEDIANTE LE ESCRITURA PÚBLICA NRO. 1687 DEL 24 DE JUNIO DEL 2004 OTORGADA EN LA NOTARIA 36 DEL CÍRCULO DE BOGOTÁ CON UN ÁREA DE 11.926.68 MTS2 Y REGISTRADO EN EL FOLIO DE MATRÍCULA INMOBILIARIA 050C-1810573 PREDIO DENOMINADO EL REFUGIO, CON UN ÁREA DE CIENTO ONCE MIL NOVECIENTOS VEINTISÉIS CON SESENTA Y OCHO DECÍMETROS CUADRADOS (111.926.68 MTS2). QUEDANDO UN REMANENTE DE DOSCIENTOS NOVENTA Y SEIS MIL DOSCIENTOS VEINTISIETE METROS CUADRADOS CON CUARENTA Y NUEVE DECÍMETROS (296.227.49MTS2). | O75: REFUJIO LA PONDEROSA | P75: N/A | Q75: N/A | R75: BIEN FISCAL | S75: 2-1049 | T75: ENGATIVA | U75: 111.926.68 MTS2 | V75: N/A | W75: N/A | X75: N/A | Y75: N/A | Z75: EN CURSO | AA75: N/A | AB75: N/A | AC75: NOTIFICACION DE LOS DEMANDADOS | AD75: EN CURSO | AE75: N/A | AF75: DESIGNA CURADOR 13-08-2024
A76: 288991 | B76: CONSTITUCIONAL | C76: 2009-00567 | D76: ACCION POPULAR | E76: 40031 | F76: JUZGADO 16 CIVIL DEL CIRCUITO | G76: SHIRLEY AVELLANEDA PEÑA | H76: DADEP | I76: INVERSIONES UISSAN | J76: DIRECTA | K76: DEMANDADO | L76: ENTREGA DE ZONAS DE CESIÓN URBANIZACION MUISCA | M76: NA | N76: ENTREGA Y ESCRITURACION DE LAS ZONAS DE CESION | O76: MUISCA I | P76: NA | Q76: NA | R76: ZONA DE CESIÓN | S76: 3687 | T76: ENGATIVA | U76: 6804.067 | V76: NA | W76: NA | X76: NA | Y76: NA | Z76: 44008 | AA76: NA | AB76: NA | AC76: SENTENCIA FAVORABLE PRIMERA INSTANCIA SE DEBE REALIZAR LA ENTREGA DE LAS ZONAS DE CESIÓN DE LA URBANIZACIÓN MUISCAS. MEMORIAL AL JUZGADO RADICADO 20201100122391 DEL 17-11-2020 SOLICITANDO MODULACION DE FALLO. MEDIANTE MEMORIAL 20221100020741 DEL 28-08-2022 SE REITERO SOLITITUD AL DESPACHO SOLICITANDO MODULACION DE FALLO DE ACUERDO CON LA RESPUESTA DADA POR LA SRI REFERENTE AL PLANO QUE CORRESPONDE A LA ZONA DE CESIÓN. EL JUZGADO MEDIANTE AUTO DE FECHA 27-05-2022 MODULO EL FALLO JUDICIAL. MEDIANTE MEMORANDO 20221100031623 DEL 01-06-2022 SE REMITIO A LA SRI AUTO DE MODULACION DE FALLO Y SOLICITUD DE TRAMITE DE ACTA DE TOMA DE POSESION. MEDIANTE RADICADO ORFEO 20231300179511 SE SOLICITO AL DESPACHO LIQUIDACION DE COSTAS.14-12-2024 FIJACION ESTADO APRUEBA COSTAS, EN TRAMITE DE COBRO. | AD76: CON FALLO | AE76: SRI | AF76: SENTENCIA DE PRIMERA INSTANCIA
A77: 539060 | B77: CIVIL | C77: 2015-00782 | D77: DIVISORIO | E77: 42472 | F77: JUZGADO 11 CIVIL DEL CIRCUITO DE BOGOTA | G77: MARIA FERNANDA CRUZ | H77: CENTRAL DE INVERSIONES SA | I77: DADEP ETB | J77: DIRECTA | K77: DEMANDADO | L77: PARTICION Y VENTA INMUEBLE RUPI 2-1203 | M77: NA | N77: PARTICION Y VENTA INMUEBLE RUPI 2-1203 | O77: NA | P77: NA | Q77: =+V77*W77 -> 8.9402683e+08 | R77: BIEN FISCAL | S77: 2-1203 | T77: SUBA | U77: NA | V77: 1.7907649e+09 | W77: 0.499243 | X77: NA | Y77: NA | Z77: NA | AA77: NA | AB77: NA | AC77: SEGUIMIENTO PROCESAL - SEGUIMIENTO QUE SE EXPIDA AUTO QUE ORDENA DIVISIÓN MATERIAL DEL INMUEBLE AVALUO Y REMATE | AD77: EN CURSO | AE77: N/A | AF77: SEGUIMIENTO PROCESAL - SEGUIMIENTO QUE SE EXPIDA AUTO QUE ORDENA DIVISIÓN MATERIAL DEL INMUEBLE AVALUO Y REMATE. POR PARTE DEL DESPCHO SE SOLCIITÓ CONCILIACIÓN, A LA ESPERA DE DECISIÓN EN FIRME
A78: 363971 | B78: CIVIL | C78: 2011-00083 | D78: DIVISORIO | E78: 40647 | F78: JUZGADO 1 CIVIL DEL CIRCUITO DE SOACHA | G78: MARIA FERNANDA CRUZ | H78: ICBF | I78: DISTRITO CAPITAL Y OTROS | J78: DIRECTA | K78: DEMANDADO | L78: PARTICION Y VENTA INMUEBLE 2-1230 | M78: NA | N78: PARTICION Y VENTA INMUEBLE 2-1230 | O78: NA | P78: NA | Q78: 146899639 | R78: BIEN FISCAL | S78: 2-1230 | T78: SOACHA | U78: NA | V78: =100%*Q78/W78 -> 4.121e+08 | W78: 0.356466 | X78: NA | Y78: NA | Z78: 41389 | AA78: NA | AB78: NA | AC78: SEGUIMIENTO PROCESAL - PRIMERA DILIGENCIA DE REMATE FRACAZADA - SEGUIMIENTO FIJACIÓN NUEVA FECHA DILIGENCIA REMATE | AD78: EN CURSO | AE78: N/A | AF78: SEGUIMIENTO PROCESAL - PRIMERA DILIGENCIA DE REMATE FRACAZADA - SEGUIMIENTO FIJACIÓN NUEVA FECHA DILIGENCIA REMATE , pendiente presentar avaluo auto fecha 24 de mayo de 2024
A79: 347764 | B79: CIVIL | C79: 2009-00254 | D79: REIVINDICATORIO | E79: 40120 | F79: JUZGADO 10 CIVIL DEL CIRCUITO DE BOGOTÁ | G79: JAMMER SAUL HERNANDEZ | H79: JOSE DEL CARMEN AYALA | I79: DADEP | J79: DIRECTA | K79: DEMANDADO | L79: REIVINDICACION PREDIO DONDE FUNCIONA JAC SAN CIPRIANO NORTE | M79: NA | N79: REIVINDICACION PREDIO DONDE FUNCIONA JAC SAN CIPRIANO NORTE | O79: SAN CIPRIANO | P79: NA | Q79: NA | R79: ZONA DE CESIÓN | S79: 2277-1 | T79: SUBA | U79: NA | V79: NA | W79: NA | X79: 213.57 | Y79: NA | Z79: 43230 | AA79: 43426 | AB79: NA | AC79: SEGUIMIENTO PROCESAL - CON SENTENCIA DE SEGUNDA INSTANCIA . PENDIENTE LIQUIDACION DE COSTAS. En el Marco del proceso reivindicatorio 2009-00254 el juzgado 16 Civil del Circuito de Bogotá D.C., procedió en fecha 10 de mayo de 2018 a dictar fallo de primera instancia el cual fuera favorable al DADEP, pues desestimó la petición del particular de reclamar el predio público. Cabe señalar que frente a la anterior decisión el demandante promovió recurso de apelación ante el Tribunal Superior de Bogotá, recurso que fuera resuelto en fecha 22 de noviembre confirmando en su integridad el fallo de primera instancia el cual es preciso recordar fuera favorable al Distrito. Con lo anterior se protegieron 123.57 Mts2 de espacio correspondiente al predio identificado con el RUPI 2277-3, salvaguardando el salón comunal del Barrio San Cipriano Norte. | AD79: CON FALLO | AE79: N/A | AF79: COBRO COSTAS MEDIANTE PROCESO DE EJECUCIÓN-SE APRUEBA LIQUIDACIÓN DEL CRÉDITO- SE SOLICITAN MEDIDAS CAUTELARES
A80: 792124 | B80: CIVIL | C80: (2024-00118) 11001310301920240011800 | D80: NULIDAD DE ESCRITURA PÚBLICA | E80: 45348 | F80: JUZGADO 19 CIVIL DEL CIRCUITO | G80: GENARO SALAZAR GONZALEZ | H80: DADEP | I80: ALIANZA FIDUCIARIA | J80: DIRECTA | K80: DEMANDADO | L80: OCUPACION DE ESPACIO PUBLICO | M80: N/A | N80: GOCE DEL ESPACIO PUBLICO | O80: LA MERCED | P80: N/A | Q80: N/A | R80: ZONA DE CESIÓN | S80: 2-1274 | T80: SANTAFE | U80: 231.91 MTS2 | V80: N/A | W80: N/A | X80: N/A | Y80: N/A | Z80: N/A | AA80: N/A | AB80: N/A | AC80: SEGUIMIENTO POR CALIFICACION A LA DEMANDA | AD80: EN CURSO | AE80: N/A | AF80: DEMANDA ADMITIDA, ESTA AL DESPACHO DESDE EL 07-08-2024 PARA RESOLVER RECURSO DE REPOSICION.
A81: 538181 | B81: PENAL | C81: 2007-31060 | D81: PENAL | E81: 42628 | F81: FISCAL 66 SECCIONAL UNIDAD DELITOS LEY 600 DE 2000 | G81: JOSE AGUSTÍN AVENDAÑO | H81: HERNANDO RAMIREZ | I81: MARICELA MILKE OSSA | J81: DIRECTA | K81: INTERVINIENTE | L81: CEMENTERIO CENTRAL | M81: ESTAFA AGRAVADA | N81: ADQUISICION DADEP-UAESP PREDIOS CEMENTERIO CENTRAL TITULO FALSO | O81: CEMENTERIO CENTRAL | P81: NA | Q81: NA | R81: BIEN FISCAL | S81: 2-1300 | T81: SANTAFE | U81: NA | V81: NA | W81: NA | X81: NA | Y81: NA | Z81: NA | AA81: NA | AB81: NA | AC81: La Fiscalía 103 decide mantener en firme la resolución dada en primera instancia en la cual resuelve precluir la acción penal por los delitos de estafa agravada respecto de los procesados MARCELLA MILKE OSSA, ALEXANDER GOMEZ SOLER y CLAUDIA GUERRERO MATEUS, estamos a la espera de actuar dentro del trámite de incidental en el cual la Fiscalía tomara decisiones de fondo. | AD81: EN CURSO | AE81: N/A | AF81: PRECLUSION DE LA INVESTIGACION
A82: 744464 | B82: CIVIL | C82: 2022-01104 | D82: PERTENENCIA | E82: 44572 | F82: JUZGADO 36 CIVIL MUNICIPAL | G82: GENARO SALAZAR GONZALEZ | H82: FRANCISCO JAVIER BALLESTEROS MILLAN - NANCY BALLESTEROS MILLAN | I82: ALBERTO HERRERA - JAIME NIETO CANO | J82: DIRECTA | K82: INTERVINIENTE | L82: Consultado el mapa digital de la Defensoría del Espacio Público – SIGDEP y el Sistema de Información de la Defensoría del Espacio Público-SIDEP, se estableció que el inmueble con nomenclatura KR 20 164B 14 MJ, se encuentra construido sobre un predio que a la fecha se encuentra incluido como bien fiscal en el Inventario General de Espacio Público y Bienes Fiscales del Sector Central del Distrito Capital, a cargo del Departamento Administrativo de la Defensoría del Espacio Público y se identifica con el RUPI 2-1307, del cual se adjunta la certificación correspondiente. | M82: N/A | N82: Consultado el mapa digital de la Defensoría del Espacio Público – SIGDEP y el Sistema de Información de la Defensoría del Espacio Público-SIDEP, se estableció que el inmueble con nomenclatura KR 20 164B 14 MJ, se encuentra construido sobre un predio que a la fecha se encuentra incluido como bien fiscal en el Inventario General de Espacio Público y Bienes Fiscales del Sector Central del Distrito Capital, a cargo del Departamento Administrativo de la Defensoría del Espacio Público y se identifica con el RUPI 2-1307, del cual se adjunta la certificación correspondiente. | O82: EL TOBERIN | P82: N/A | Q82: N/A | R82: ZONA DE CESIÓN | S82: 2-1307 | T82: USAQUEN | U82: 417.54 | V82: N/A | W82: N/A | X82: N/A | Y82: N/A | Z82: N/A | AA82: N/A | AB82: N/A | AC82: ADMISION DE LA INTERVENCION COMO TERCEROS INTERESADOS ARTÍCULO 63 CGP | AD82: EN CURSO | AE82: N/A | AF82: EN AUDIENCIA DE INSPECCIÓN JUDICIAL EL JUZGADO 36 CM ADJUDICO ILEGALMENTE UN BIEN FISCAL, SE CORRE EL TRASLADO DE LA NULIDAD INVOCADA POR EL DADEP 21-11-2024
A83: 750162 | B83: CIVIL | C83: 2010-00474 | D83: PERTENENCIA | E83: 40413 | F83: JUZGADO 19 CIVIL DEL CIRCUITO DE EJECUCIÓN DE BOGOTÁ | G83: JAMMER SAUL HERNANDEZ | H83: LUIS HERNANDO MORALES | I83: PERSONAS INDETERMINADAS | J83: DIRECTA | K83: INTERVINIENTE | L83: PROCESO DE PERTENENCIA SOBRE PREDIO PÚBLICO | M83: N/A | N83: SE PRETENDE LA NULIDAD DE LA SENTENCIA DE FECHA 09 DE MARZO DE 2012 POR MEDIO DEL CUAL SE PRESCRIBIÓ UNA ZONA PÚBLICA | O83: URBANIZACIÓN FRANCO | P83: N/A | Q83: N/A | R83: ZONA DE CESIÓN | S83: 994-2 | T83: FONTIBON | U83: 1395,93 MTS2 | V83: N/A | W83: N/A | X83: N/A | Y83: N/A | Z83: 41155 | AA83: N/A | AB83: N/A | AC83: SEGUIMIENTO A SOLICITUD DE RECONSTRUCCIÓN DEL EXPEDIENTE | AD83: EN CURSO | AE83: N/A | AF83: CON OFICIOS A LOS DEMANDANTES Y ENTIDADES PARA LA RECONSTRUCCIÓN DEL EXPEDIENTE.
A84: 635511 | B84: CIVIL | C84: 2019-00104 73449310300120190010400 | D84: DIVISORIO | E84: 43795 | F84: JUZGADO 1 CIVIL DEL CIRCUITO DE MELGAR - TOLIMA- | G84: MARIA FERNANDA CRUZ | H84: INVERSIONES SAJUC & CIA S EN C | I84: DISTRITO CAPITAL BOOTA; COLPENSIONES; DIAN; MUNICIPIO DE MELGAR; BANCO UNIÓN PACÍFICO; ANTONIO VANEGAS SANTORO; GUILLERMO LEÓN CORRAL; JAIME PINILLA MONROY; MARIA LUISA CARRIZOSA; MARIA CRIATINA TAMAYO | J84: DIRECTA | K84: DEMANDADO | L84: DIVISION Y ENTREGA DE PORCENTAJE ADJUDICADO EN SUCESION CON FIN ESPECIFICO DE PREMIO | M84: N/A | N84: DIVISION Y ENTREGA DE PORCENTAJE ADJUDICADO EN SUCESION CON FIN ESPECIFICO DE PREMIO | O84: N/A | P84: N/A | Q84: N/A | R84: BIEN FISCAL | S84: 2-1391 | T84: MELGAR | U84: N/A | V84: POR DETERMINAR | W84: 0.0007 | X84: N/A | Y84: N/A | Z84: N/A | AA84: N/A | AB84: N/A | AC84: SE ESPERA SE REALICE LA DIVISION Y ORDENE REMANTE | AD84: EN CURSO | AE84: N/A | AF84: NOTIFICACIONES
A85: 611632 | B85: CONSTITUCIONAL | C85: (2016-00274) 11001310303320160027400 | D85: ACCION POPULAR | E85: 42649 | F85: JUZGADO 34 CIVIL DEL CIRCUITO | G85: MARIA FERNANDA MADIEDO SANCHEZ | H85: Libardo Melo Vega | I85: C.C. Sorpresas | J85: DIRECTA | K85: VINCULADO | L85: VULNERACION DERECHO A LA INFORMACION DE LOS CONSUMIDORES | M85: N/A | N85: El accionante manifiesta la vulneración a los derechos e intereses colectivos de recibir información suficiente, clara, oportuna, verificable, comprensible, precisa e idónea respecto del uso de los parqueaderos. | O85: Centro Comercial Sorpresas | P85: N/A | Q85: N/A | R85: ZONA DE CESIÓN | S85: 214-20 | T85: USAQUEN | U85: N/A | V85: N/A | W85: N/A | X85: N/A | Y85: N/A | Z85: N/A | AA85: N/A | AB85: N/A | AC85: A la espera de fijación de audiencia de pacto de cumplimiento en atención a la vinculación del HUB DE MOVILIDAD CALLE 136 notificados el 6 de junio de 2022. Con ocasión de recurso interpuesto el 13 de junio de 2022 por el HUB DE MOVILIDAD CALLE 136 nos encontramos a la espera de que sea resuelto y posteriormente fijada la fecha de audiencia de pacto de cumplimiento. 2023-07-06 fija fecha para audiencia de testimonio el 17 de julio el 28 -7-2023 se reporgrama diligencia para el 25 DE AGOSTO DE 2023 HORA 10:00 A.M. No se llevo a cabo diligencia el 25 de agosto de 2023 teniendo en cuenta que no compareció el testigo. FIJA FECHA AUDIENCIA (20 DE NOVIEMBRE DE 2023 HORA 10:00 A.M, el dia de la diligencia no comparecio el testigo. proceso ingresa al despacho 01-02-2024 para resolver traslado alegatos de conclusión. alegatos de conclusion 20241300098181 de fecha 17-7-2024.28-8-2024 ingresa al despacho con escritos de alegatos de conclusion. se revisa el 31-01-2025 proceso sin novedad procesal. | AD85: EN CURSO | AE85: SGIEP | AF85: ALEGATOS DE CONCLUSION
A86: 534654 | B86: CIVIL | C86: 2015-01192 | D86: DIVISORIO | E86: 42573 | F86: JUZGADO 34 CIVIL CIRCUITO DE BOGOTA | G86: MARIA FERNANDA CRUZ | H86: CISA | I86: DISTRITO CAPITAL Y OTROS | J86: DIRECTA | K86: DEMANDADO | L86: PARTICION Y VENTA INMUEBLE 2-1503 | M86: NA | N86: PARTICION Y VENTA INMUEBLE 2-1503 | O86: NA | P86: NA | Q86: 75911047 | R86: BIEN FISCAL | S86: 2-1503 | T86: BARRIOS UNIDOS | U86: NA | V86: 365378970 | W86: 0.1093 | X86: NA | Y86: NA | Z86: NA | AA86: NA | AB86: NA | AC86: SEGUIMIENTO PROCESAL: PREUBAS | AD86: EN CURSO | AE86: N/A | AF86: FECHA INTERROGATORIO PARA EL 6 DE FEBRERO DE 2019 A LAS 9:30 AL REPRESENTANTE LEGAL DE LA ENTIDAD DEMANDANTE (ICBF).
A87: 334762 | B87: CONSTITUCIONAL | C87: 2010-00001 | D87: ACCION POPULAR | E87: 40165 | F87: JUZGADO 8 CIVIL DEL CIRCUITO DE BOGOTÁ | G87: MARIA FERNANDA MADIEDO SANCHEZ | H87: DADEP | I87: TRANSPORTES PANAMERICANOS | J87: DIRECTA | K87: DEMANDADO | L87: ENTREGA ZONAS DE CESIÓN | M87: NA | N87: ENTREGAY ESCRITURACIÓN DE ZONAS DE CESIÓN ESTACIÓN DE SERVICIO SAN ANTONIO | O87: ESTACION DE SERVICIO PANAMERICANO | P87: NA | Q87: NA | R87: ZONA DE CESIÓN | S87: 3711 | T87: USAQUEN | U87: 1711.49 | V87: NA | W87: NA | X87: NA | Y87: NA | Z87: 42849 | AA87: NA | AB87: ORDEN A DEMANDADO DE ENTREGAR Y ESCRITURAR | AC87: SEGUIMIENTO CUMPLIMIENTO DEL FALLO. En la rama judicial la ultima actuaciòn respuesta auto requere de fecha 6-6-2022 lo anterior en respuesta al auto de fecha 2 -6-2022 en donde el juzgado requirió al urbanzador informe del cumplimiento del fallo. se radica memorial por parte de CIGESA S.A.S informando sobre las gestiones adelantadas y en el cual se informa que se esta a la espera de la expedicion de la constania de cumplimiento de obras del proyecto San antonio norte conforme solicitud radicado ante el IDU el dia 27 de Mayo de 2022, mediante auto de fecha 22 de junio el despacho tiene en cuenta la informacion radicada y dispone hacer seguimiento por secretaria cada 30 dias, el dia 7 de julio de 2022 se radica solicitud por parte se CIGESA S.A.S dirigida al despacho a fin de requerir se de respuesta por parte del IDU, mediante estado de fecha 3 de agosto de 2022 mediante auto se incopora la documentacion y se retiera el seguimiento por secretaria conforme auto de fecha 22 junio de 2022. Auto de fecha 7-10-2022 requiriendo dentro del termino de 8 dias a CIGESA informe sobre gestiones adelantadas para entrega de zonas de cesion. el 01 de noviembre de 2022 mediante radicado orfeo 20221100172111 se remite informe sobre el cumplimiento del fallo, el dia 8-11-2022 se emite auto corriendo traslado a cigesa sobre lo informado por el dadep, se fija en estado el 9-11-2022. consultada la web de la rama el14-12-2022 cigesa allega poliza de cumplimiento. Radicado orfeo 20234060008082 de fecha 16/01/2022 se allega documentacion para entrega de zonas de Cesion se encuentra en estudio por parte de SRI. Mediante orfeo 20234000013472 se allega por parte del accionado la documentacion requerida para continuar con el tramite de entrega de zonas de cesion. El día diez (10) de febrero de 2023, se realizo la visita por parte del DADEP al sitio de las obras para verificar que el cerramiento perimetral de la zona verde se había retirado en su totalidad. Se adelanto el acta de recibo con los documentos y la información anexada por el urbanizador , no obstante, estamos pendiente que se allegue por parte de estos , una certificación de la EAAB en donde se determine que sobre CARRERA 16, no se realizaron obras de acueducto y alcantarillado. Se remite memorando 20231300024243 a SRI solictando informe sobre estado actual del proceso de entrega de zonas de cesion a fin de informar al despacho. SRI da respuesta 20232010026213 informando que se dará proyeccion al acta de recibo zonas de cesion. Mediante memorando a SRI 20231300036163 de fecha 27-9-2023 se solicito informacion sobre estado de entrega y proyeccion acta de recibo. proceso ingresa al despacho el 26-9-2023. ACTA DE RECIBO 045 DEL 12/09/2023 pendiente que SRI ejecute las actividades pertinentes para la incorporacion cartografica y alfanumerica de los sistemas de informacion del DADEP y al inventario general de espacio publico y bienes fiscales. de lo anterior se informa al despacho mediante memorial de fecha 12/10/2023. 25-10-23 Agréguese a los autos, la documental allegada por la parte actora – Departamento Administrativo de la Defensoría del Espacio Público, descorriendo el traslado ordenado en auto adiado 2 de octubre del corriente. Pendiente auto archivo juzgado por cumplimiento de ordenes.Auto de fecha 9 de Mayo Auto ordena correr traslado accionado allega escrituración a favor del Departamento Administrativo de la Defensoría del Espacio Público – DADEP, de las zonas de cesión a la urbanización Montijo, vista en la anotación No. 18 del folio de matrícula inmobiliaria No. 50N455390- Fls. 1055 a 1063, de la cual se corre traslado a la parte actora por el término de ejecutoria de este proveído. AUTO DE FECHA 5-6-2024 Secretaría, procédase archivar las presentes diligencias. Una vez se tenga esta certificación continuaremos con el tramite de recibo. | AD87: CON FALLO | AE87: SRI | AF87: ARCHIVO
A88: 582144 | B88: CIVIL | C88: 2017-00795 | D88: DIVISORIO | E88: 43347 | F88: JUZGADO 27 CIVIL DEL CIRCUITO | G88: MARIA FERNANDA CRUZ | H88: INSTITUTO COLOMBIANO DE BIENESTAR FAMILIAR -ICBF- | I88: DADEP | J88: DIRECTA | K88: DEMANDADO | L88: DIVISORIO - PARTICION Y ENTREGA RUPI | M88: NA | N88: DIVISORIO - PARTICION Y ENTREGA RUPI | O88: CARRERA 33 No. 39-20 SUR | P88: N/A | Q88: N/A | R88: BIEN FISCAL | S88: 2-1561 | T88: RAFAEL URIBE | U88: 235,20 | V88: DETERMINAR | W88: 0.0533 | X88: NA | Y88: NA | Z88: NA | AA88: NA | AB88: NA | AC88: SEGUIMIENTO PROCESAL - SEGUIMIENTO NOTIFICACION POR AVISO | AD88: EN CURSO | AE88: N/A | AF88: SEGUIMIENTO PROCESAL - SE CONTESTO DEMANDA
A89: 747601 | B89: PENAL | C89: 2023-67085 | D89: PENAL | E89: 44994 | F89: FISCALIA 80 - ESPECIALIZADA | G89: JOSE AGUSTÍN AVENDAÑO | H89: DADEP | I89: INDETERMINADO | J89: DIRECTA | K89: DENUNCIANTE | L89: DENUNCIA PENAL - FRAUDE PROCESAL | M89: FRAUDE PROCESAL | N89: FALSIFICACION DOCUMENTO PUBLICO | O89: N/A | P89: N/A | Q89: N/A | R89: N/A | S89: 2-1564 | T89: N/A | U89: N/A | V89: N/A | W89: N/A | X89: N/A | Y89: N/A | Z89: N/A | AA89: N/A | AB89: N/A | AC89: SSE RECIBE CORREO ELECTRÓNICO POR PARTE DE LA FISCALÍA 80 ESPECIALIZADA EL DÍA 26 DE JUNIO, EN EL CUAL EL SR. FISCAL MENCIONA LA GRAN CARGA LABORAL QUE TIENE EL DESPACHO, MOTIVO POR EL CUAL, EN ORDEN DE LLEGADA DE CADA DENUNCIA, SE ANALIZARA CADA CASO. | AD89: EN CURSO | AE89: N/A | AF89: INVESTIGACION
A90: 793476 | B90: CIVIL | C90: (2024-00120) 11001310301820240012000 | D90: NULIDAD DE ESCRITURA PÚBLICA | E90: 45355 | F90: JUZGADO 18 CIVIL DEL CIRCUITO | G90: GENARO SALAZAR GONZALEZ | H90: DADEP | I90: MARTHA RUTH ARDILA HERRERA | J90: DIRECTA | K90: DEMANDADO | L90: OCUPACION DE ESPACIO PUBLICO | M90: N/A | N90: GOCE DEL ESPACIO PUBLICO | O90: RENANIA URAPANES | P90: N/A | Q90: N/A | R90: ZONA DE CESIÓN | S90: 2-1564 | T90: KENNEDY | U90: 1.678.86 MTS2 | V90: N/A | W90: N/A | X90: N/A | Y90: N/A | Z90: N/A | AA90: N/A | AB90: N/A | AC90: SEGUIMIENTO POR CALIFICACION A LA DEMANDA | AD90: EN CURSO | AE90: N/A | AF90: ADMITE DEMANDA 08-05-2024, SE NOTIFICO DEMANDADOS PENDIENTE INGRESO AL DESPACHO
A91: 561413 | B91: CIVIL | C91: 2016-00168- 2023-000030 | D91: EXPROPIACIÓN | E91: 42613 | F91: JUZGADO 3 CIVIL CIRCUITO DE ZIPAQUIRA | G91: MARIA FERNANDA CRUZ | H91: AGENCIA NACIONAL DE INFRAESTRUCTURA | I91: FONDO NACIONAL DE GARANTÍAS - DISTRITO CAPITAL (HACIENDA) | J91: DIRECTA | K91: DEMANDADO | L91: EXPROPIACIÓN CAJICA ANI | M91: NA | N91: EXPROPIACIÓN JUDICIAL ANI | O91: NA | P91: NA | Q91: NA | R91: BIEN FISCAL | S91: 2-1580 | T91: CAJICA | U91: NA | V91: 2.556.432.000 | W91: 0.0038 | X91: NA | Y91: NA | Z91: NA | AA91: NA | AB91: NA | AC91: SEGUIMIENTO AL PROCESO: VERIFICAR AUTO QUE FIJA FECHA PARA AUDIENCIA DE OPOSICION DE AVALUO | AD91: EN CURSO | AE91: N/A | AF91: SEGUIMIENTO AL PROCESO. VERIFICAR AUTO QUE FIJA FECHA PARA AUDIENCIA DE OPOSICION DE AVALUO
A92: 534677 | B92: CIVIL | C92: 2015-00746 | D92: DIVISORIO | E92: 42519 | F92: JUZGADO 4 CIVIL CIRCUITO DE BOGOTA | G92: MARIA FERNANDA CRUZ | H92: ICBF | I92: DISTRITO CAPITAL Y OTROS | J92: DIRECTA | K92: DEMANDADO | L92: PARTICION Y VENTA INMUEBLE 2-1581 | M92: NA | N92: PARTICION Y VENTA INMUEBLE 2-1581 | O92: NA | P92: NA | Q92: 29088360 | R92: BIEN FISCAL | S92: 2-1581 | T92: SUBA | U92: NA | V92: =100%*Q92/W92 -> 1499400000 | W92: 0.0194 | X92: NA | Y92: NA | Z92: NA | AA92: NA | AB92: NA | AC92: SEGUIMIENTO PROCESAL - SEGUIMIENTO QUE SE EXPIDA AUTO QUE ORDENA DIVISIÓN MATERIAL DEL INMUEBLE AVALUO Y REMATE | AD92: EN CURSO | AE92: N/A | AF92: SEGUIMIENTO PROCESAL - SEGUIMIENTO QUE SE EXPIDA AUTO QUE ORDENA DIVISIÓN MATERIAL DEL INMUEBLE AVALUO Y REMATE
A93: 664524 | B93: CIVIL | C93: 2020-00410 (11001310301620200041000) | D93: NULIDAD DE ESCRITURA PÚBLICA | E93: 44167 | F93: JUZGADO 16 CIVIL DEL CIRCUITO | G93: GENARO SALAZAR GONZALEZ | H93: DADEP | I93: NADIME AMPARO YAVER LICHT | J93: DIRECTA | K93: DEMANDADO | L93: NULIDAD DE ESCRITUA PUBLICA | M93: FALSEDAD EN DOCUMENTO PUBLICO | N93: MEDIANTE ESCRITURA PÚBLICA 1385 DEL 10 DE JULIO DEL 2019 DE LA NOTARIA CINCUENTA Y OCHO (58) DEL CÍRCULO DE BOGOTÁ, BOGOTÁ D.C., DEPARTAMENTO ADMINISTRATIVO DE LA DEFENSORIA DEL ESPACIO PUBLICO, ENTIDAD PÚBLICA EN SU CALIDAD DE VENDEDORA POR INTERMEDIO DE SU DIRECTORA Y ARQUITECTA NADIME AMPARO YAVER LICH TRANSFIERE A TÍTULO DE VENTA AL SEÑOR FRANCISCO DANIEL GOMEZ ZULUAGA, MAYOR DE EDAD, DOMICILIADO Y RESIDENCIADO EN LA CIUDAD DE BOGOTÁ, IDENTIFICADO CON LA CÉDULA DE CIUDADANÍA NRO.80.229.739, EL PREDIO CON NOMENCLATURA URBANA ACTUAL NUMERO SETENTA -SETENTA Y UNO (70-71) DE LA CARRERA VEINTINUEVE C (29C) Y RUPI 2-1817. | O93: LOS ALCAZARES | P93: N/A | Q93: N/A | R93: BIEN FISCAL | S93: 2-1817 | T93: BARRIOS UNIDOS | U93: 320.40M2 | V93: NO | W93: N/A | X93: N/A | Y93: N/A | Z93: N/A | AA93: N/A | AB93: N/A | AC93: LOS DEMANDADOS CONTESTARON LA REFORMA DE LA DEMANDA CON EXCEPCIONES PREVIAS Y DE FONDO, SE DESCORRIO EL TRASLADO DE CADA UNA DE LAS RESPUESTAS EL 15 DE JUNIO DEL 2022 | AD93: EN CURSO | AE93: N/A | AF93: EL JUZGADO ENVIO EL PROCESO AL 68 ADMINISTRATIVO POR JURISDICCIÓN, PENDIENTE CALIFICACION DEL JDO.
A94: 336196 | B94: PENAL | C94: 2010-01004 | D94: PENAL | E94: 40235 | F94: FISCALIA 365 SUB UNIDAD DE TIERRAS | G94: JOSE AGUSTÍN AVENDAÑO | H94: DADEP | I94: BERTHA LIGIA LOPEZ RIVERA | J94: DIRECTA | K94: DENUNCIANTE | L94: CIUDAD BACHUE - DEFRAUDACION DE LA PROPIEDAD | M94: FALSEDAD EN DOCUMENTO PUBLICO - ESTAFA - ALO | N94: EN EL MARCO DE QUERELLA POLICIVA SE HACE VALER FMI FALSO - ALO | O94: BOCHICA COMPARTIR | P94: NA | Q94: NA | R94: ZONA DE CESIÓN | S94: 1539 | T94: ENGATIVA | U94: NA | V94: NA | W94: NA | X94: NA | Y94: NA | Z94: NA | AA94: NA | AB94: NA | AC94: SEGUIMIENTO A ORDENES A PJ | AD94: EN CURSO | AE94: N/A | AF94: INDAGACIÓN
A95: 541653 | B95: CIVIL | C95: 2016-00556 | D95: DIVISORIO | E95: 42690 | F95: JUZGADO 41 CIVIL DEL CIRCUITO | G95: MARIA FERNANDA CRUZ | H95: EDUARDO PATARROYO CORDOBA | I95: DADEP - DISTRITO CAPITAL Y OTROS | J95: DIRECTA | K95: DEMANDADO | L95: DIVISORIO - PARTICION Y ENTREGA RUPI 2-1858 | M95: NA | N95: DIVISORIO - PARTICION Y ENTREGA RUPI 2-1858 | O95: NA | P95: NA | Q95: DETERMINAR | R95: BIEN FISCAL | S95: 2-1858 | T95: CHAPINERO | U95: NA | V95: DETERMINAR | W95: 0.0529 | X95: NA | Y95: NA | Z95: NA | AA95: NA | AB95: NA | AC95: SEGUIMIENTO PROCESAL - SEGUIMIENTO QUE SE EXPIDA AUTO QUE ORDENA DIVISIÓN MATERIAL DEL INMUEBLE AVALUO Y REMATE | AD95: EN CURSO | AE95: N/A | AF95: SEGUIMIENTO PROCESAL - SEGUIMIENTO QUE SE EXPIDA AUTO QUE ORDENA DIVISIÓN MATERIAL DEL INMUEBLE AVALUO Y REMATE
A96: 534671 | B96: CIVIL | C96: 2015-00570 | D96: DIVISORIO | E96: 42220 | F96: JUZGADO 1 CIVIL DEL CIRCUITO DE FUNZA | G96: MARIA FERNANDA CRUZ | H96: CISA | I96: DISTRITO CAPITAL Y OTROS | J96: DIRECTA | K96: DEMANDADO | L96: PARTICION Y VENTA INMUEBLE 2-1958 TENJO | M96: NA | N96: PARTICION Y VENTA INMUEBLE 2-1958 TENJO | O96: NA | P96: NA | Q96: 119757120 | R96: BIEN FISCAL | S96: 2-1958 | T96: TENJO | U96: NA | V96: =100%*Q96/W96 -> 1405600000 | W96: 0.0852 | X96: NA | Y96: NA | Z96: NA | AA96: NA | AB96: NA | AC96: SE ESPERA AUTO QUE ORDENE LA DIVISIÓN CUANDO SE TERMINE DE NOTIFICAR POR PARTE DE LOS DEMANDANTES | AD96: EN CURSO | AE96: N/A | AF96: A LA ESPERA DE AUTO QUE ORDENE PARTICIÓN INMUBLE, DIVISIÓN, NOMBRAMIENTO AUXILIAR PAR AVALUO Y POSTERIOR REMATE
A97: 673114 | B97: CIVIL | C97: 2018-00399 | D97: DIVISORIO | E97: 43343 | F97: JUZGADO 20 CIVIL CIRCUITO DE BOGOTA | G97: MARIA FERNANDA CRUZ | H97: ICBF | I97: JORGE ABELLO | J97: DIRECTA | K97: VINCULADO | L97: DIVISION Y SUBASTA | M97: N/A | N97: POR PARTE DEL DEMANDANTE SE PRETENDE QUE SE SUBASTE EL INMUEBLE Y SEA REPARTIDO EL DINERO DE ACUERDO A LOS PORCENTAJES DE PROPIEDAD CRA 92 No. 150 - 56 INT 2 | O97: N/A | P97: N/A | Q97: N/A | R97: BIEN FISCAL | S97: 2-1960 | T97: SUBA | U97: 476 | V97: 1038741000 | W97: 0.014749 | X97: N/A | Y97: N/A | Z97: N/A | AA97: N/A | AB97: N/A | AC97: SEGUIMIENTO PROCESAL - NOTIFICCIONES Y VINCULACIÓN | AD97: EN CURSO | AE97: N/A | AF97: NOTIFICACIONES
A98: 692782 | B98: CIVIL | C98: 2022-00013 11001310302820220001300, | D98: REIVINDICATORIO | E98: 44866 | F98: JUZGADO 28 CIVIL DEL CIRCUITO DE BOGOTÁ | G98: GENARO SALAZAR GONZALEZ | H98: DADEP | I98: JOSELYN LOPEZ | J98: DIRECTA | K98: DEMANDADO | L98: RECUPERAR BIEN FISCAL 2-1975 | M98: N/A | N98: Se interpone demanda DECLARATIVA REIVINDICATORIA, en contra del señor JOSELYN LOPEZ, mayor de edad, domiciliado y residenciado en la ciudad de Bogotá, identificado con la cédula de ciudadanía Nro. 79.837.355 de Bogotá y de su núcleo familiar, por la indebida ocupación del predio Fiscal ubicado en la calle 34 Nro. 17-44, con folio de matrícula inmobiliaria 050C-464111 CHIP AAA0083HOCX y Registro Único de Patrimonio Inmobiliario (RUPI) 2-1975. | O98: TEUSAQ | P98: TEUSAQUILLO | Q98: N/A | R98: BIEN FISCAL | S98: 2-1975. | T98: TEUSAQUILLO | U98: 32.06 | V98: N/A | W98: N/A | X98: N/A | Y98: N/A | Z98: N | AA98: N | AB98: N/A | AC98: AUTO ADMISORIO DE LA DEMANDA, ESTA EN NOTIFICACION DE LA MISMA AL DEMANDADO | AD98: EN CURSO | AE98: N/A | AF98: RELEVA CURADOR 14-06-2024
A99: 679310 | B99: CIVIL | C99: 2021-00030 | D99: DIVISORIO | E99: 44447 | F99: JUZGADO 16 CIVIL DEL CIRCUITO DE BOGOTA | G99: MARIA FERNANDA CRUZ | H99: CENTRAL DE INVERSIONES S.A. - CISA | I99: SECRETARIA DE HACIENDA DE BOGOTA | J99: DIRECTA | K99: DEMANDADO | L99: EL DEMANDANTE SOLICITA LA VENTA DEL INMUEBLE IDENTIFICADO CON EL NÚMERO DE MATRÍCULA INMOBILIARIA NO. 50N-20227124 DE LA OFICINA DE REGISTRO DE INSTRUMENTOS PÚBLICOS DE BOGOTÁ, UBICADO EN LA DIRECCIÓN AK 45 106B 28 AP 503 EDIFICIO LANCASTER HOUSE, BOGOTÁ, TENIENDO EN CUENTA QUE EL 23 DE SEPTIEMBRE DE 2013 CISA ADQUIRIÓ EL 61.8% DEL INMUEBLE MEDIANTE TRANSFERENCIA DE DOMINIO DE BIENES FISCALES A TÍTULO GRATUITO CONFORME RESOLUCIÓN NO. 8027 DEL 23 DE SEPTIEMBRE DE 2013 DE LA DIRECCIÓN DE IMPUESTOS Y ADUANAS NACIONALES – DIAN Y EL 22 DE FEBRERO DE 2012 MEDIANTE SENTENCIA PROFERIDA POR EL JUZGADO PRIMERO CIVIL DEL CIRCUITO DE BOGOTÁ LA SECRETARÍA DE HACIENDA DE BOGOTÁ ADQUIRIÓ, MEDIANTE DACIÓN EN PAGO, EL 38.2% DEL INMUEBLE | M99: N/A | N99: DIVISION VENTA EN SUBASTA PÚBLICA INMUEBLE AK 45 No. 106B – 28 apto 503 Barrio San Patricio identificado con el folio de Matricula Inmobiliaria No. 50N-20227124 | O99: N/A | P99: N/A | Q99: N/A | R99: BIEN FISCAL | S99: 2-2042 | T99: USAQUEN | U99: N/A | V99: SE ENCUENTRA PENDIENTE AVALUO | W99: SE ENCUENTRA PENDIENTE AVALUO | X99: N/A | Y99: N/A | Z99: N/A | AA99: N/A | AB99: N/A | AC99: Por parte de la Secretaría de Hacienda Distrital en la contestación de la demanda solicitud la vinculación de la entidad, se espera pronunciamiento por parte del juzgado y se requirio avaluo para cuando se deba dar contestación de la demanda | AD99: EN CURSO | AE99: N/A | AF99: Notificaciones
A100: 447619 | B100: PENAL | C100: 849309 | D100: PENAL | E100: 41705 | F100: FISCALIA 106 SECCIONAL UNIDAD PRIMERA DE FE PUBLICA | G100: JOSE AGUSTÍN AVENDAÑO | H100: DADEP | I100: GUSTAVO VIVAS MONCADA - GUSTAVO LEON ZAMBRANO - AYDE RODIRGUEZ MORALES | J100: DIRECTA | K100: DENUNCIANTE | L100: VENTA ZONAS CESION ZULIA | M100: FRAUDE PROCESAL - FALSEDAD DOCUMENTO PUBLICO - OBTENCION FRAUDULENTA DOCUMENTO PUBLICO | N100: URBANIZADOR LOTEA Y ENAJENA ZONAS DE CESION URBANIZACION ZULIA | O100: ZULIA | P100: NA | Q100: NA | R100: ZONA DE CESIÓN | S100: 2207 | T100: SUBA | U100: NA | V100: NA | W100: NA | X100: NA | Y100: NA | Z100: NA | AA100: NA | AB100: NA | AC100: SE ASISTE DE MANERA PRESENCIAL AL DESPACHO 02/04/24, EN LA QUE SE INFORMA QUE SE ESTAN ADELANTANDO LAS ACTUACIONES PERTINENTES PARA LA VINCULACIÓN DE LOS INDICIADOS MEDIANTE PERSONA AUSENTE POR QUÉ YA SE HIZO BÚSQUEDA SE ENVIARON TELEGRAMAS A RENDIR DECLARATORIA, POR ELLO SE VOLVERA AL DESPACHO AL CABO DE UN MES PARA REVISAR EL ESTADO | AD100: EN CURSO | AE100: N/A | AF100: INDAGACION
...

Sheet REPRESENTACIÓN JUDICIAL SJD
A1: DEPARTAMENTO ADMINISTRATIVO DE DEFENSORÍA DEL ESPACIO PÚBLICO
A2: OFICINA ASESORA JURIDICA - EQUIPO REPRESENTACION JUDICIAL
A3: BASE DE DATOS PROCESOS JUDICIALES
A4: PROCESOS JUDICIALES REPRESENTADOS DIRECTAMENTE POR LA SJD
A5: ID SIPROJ | B5: JURISDICCIÓN | C5: PROCESO | D5: TIPO DE PROCESO | E5: FECHA DE PRESENTACIÓN DE LA DEMANDA - DENUNCIA - (EN SU DEFECTO, FECHA DE ADMISIÓN) | F5: DESPACHO QUE ACTUALMENTE CONOCE EL PROCESO | G5: ABOGADO A CARGO | H5: DEMANDANTE / DENUNCIANTE | I5: DEMANDADO / DENUNCIADO (APELLIDOS - NOMBRES) | J5: TIPO DE REPRESENTACION DIRECTA - INDIRECTA | K5: DADEP DTE - DDO - INTERVINIENTE - COMITÉ - DENUNCIANTE | L5: TEMA PROCESO | M5: DELITO (PROCESOS PENALES) | N5: DESCRIPCION | O5: NOMBRE DE LA URBANIZACION | P5: PRETENSIONES DE LA DEMANDA EN DINERO (DADEP DEMANDANTE) | Q5: VALOR EFECTIVO RECAUDO (EJECUTIVO) (DADEP DEMANDANTE) | R5: TIPO DE ZONA (CESIÓN, FISCALES, DOTACIONAL, PREDIO PÚBLICO DE NO CESIÓN, INSTITUCIONAL) | S5: RUPI | T5: LOCALIDAD | U5: METROS CUADRADOS | V5: AVALUO CATASTRAL - COMERCIAL PREDIO | W5: % DE LA CUOTA PARTE DEL DADEP (DIVISORIOS) | X5: CONDENAS O INDEMNIZACIONES QUE EN SENTENCIA EVITARÍA LA ENTIDAD EN METROS CUADRADOS | Y5: CONDENAS O INDEMNIZACIONES QUE EN SENTENCIA EVITARÍA LA ENTIDAD EN DINERO | Z5: FECHA DE SENTENCIA EN PRIMERA INSTANCIA | AA5: FECHA DE SENTENCIA EN SEGUNDA INSTANCIA | AB5: ORDENES AL DADEP EN SENTENCIA DEFINITIVA | AC5: ACCIONES A SEGUIR | AD5: EN CURSO - CON FALLO | AE5: AREA RESPONSABLE DEL CUMPLIMIENTO | AF5: ETAPA PROCESAL
A6: 31038 | B6: CONSTITUCIONAL | C6: 2001-00029 | D6: ACCION DE GRUPO | E6: 37222 | F6: TRIBUNAL ADMINISTRATIVO DE CUNDINAMARCA - SECCION CUARTA - SUBSECCION B | G6: MARIA FERNANDA MADIEDO SANCHEZ | H6: GLORIA PATRICIA SEGURA | I6: ALCALDIA LOCAL DE SAN CRISTOBAL - ALCALDIA MAYOR - SOCIEDAD SAN ROSA | J6: INDIRECTA | K6: VINCULADO POR EL DESPACHO | L6: RECUPERACION ESPACIO PUBLICO | M6: NA | N6: INDEMNIZACION POR LA SUMA DE 16.000.000.000 A CAJA DE VIVIENDA POPULAR POR FALLAS CONSTRUCTIVAS - PARA QUE COMPAREZCA A HACER ESCRITURAS A DISTRITO CAPITAL | O6: SANTA ROSA - ALPES DEL ZIPA | P6: NA | Q6: NA | R6: BIEN DE USO PUBLICO DE NO CESION | S6: 1292 | T6: SAN CRISTOBAL | U6: 10445 | V6: NA | W6: NA | X6: NA | Y6: NA | Z6: 38058 | AA6: 39383 | AB6: SIN ORDENES - DADEP VINCULADO RES SEGEN CUMPLIMIENTO FALLO | AC6: se asistió a mesa de trabajo el dia 15 julio de 2022, se elaboró memorando 20221100055893 de fecha 10-8-2022 a SAI mediante orfeo 20223010058933 se da respuesta aducienco carencia de competencia para conocer, hacer seguimiento o impulsar actuaciones administrativas surtidas en las alcaldías locales por infracción al régimen de obras y urbanismo que versen sobre inmuebles de propiedad privada. Por último, indican que como resultado de la mesa de trabajo efectuada en el mes de julio de 2022, no se suscribieron compromisos a cargo de la Subdirección de Administración Inmobiliaria y del Espacio Público. se consulta la web de la rama el proceso se radico memorial al despacho desde el 14-12-2022. se asisite a mesa de trabajo interinstitucional el dia 30 de Mayo de 2023. 16-6-2023 al despacho memorial. se asiste a reunion interinstitucional 19 diciembre de 2023 a la cual se asiste. mediante orfeo de fecha 20233000198691 de fecha 28-12-2024 se remite el inventario de predios incorporados en el inventario de bienes del Distrito del sector del Barrio Santa Rosa._x000D_ | AD6: CON FALLO | AE6: SRI-SGIEP | AF6: CUMPLIMIENTO DE FALLO
A7: 167094 | B7: CONSTITUCIONAL | C7: 2001-00544 | D7: ACCION POPULAR | E7: 37193 | F7: TRIBUNAL ADMINISTRATIVO DE CUNDINAMARCA - SECCION SEGUNDA | G7: MARIA FERNANDA MADIEDO SANCHEZ | H7: ESTANISLAO ESCALANTE BARRETO | I7: ALCALDIA MAYOR - SEC SALUD - IDU - SEC OBRAS - ALCALDIA LOCAL DE KENNEDY | J7: INDIRECTA | K7: COMITÉ | L7: RECUPERACION ESPACIO PUBLICO | M7: NA | N7: RECUPERACION DE RIO TUNJUELITO POR CONTAMINACION FRIGORIFICO GUADALUPE | O7: FRIGORIFICO GUADALUPE | P7: NA | Q7: NA | R7: VIAS PEATONALES - VIAS VEHICULARES - ZONA VERDE - ZONA COMUNAL | S7: 3296 | T7: KENNEDY | U7: 2739 | V7: NA | W7: NA | X7: NA | Y7: NA | Z7: 37379 | AA7: 37463 | AB7: ACOMPAÑAMIENTO RECUPERACION ESPACIO PUBLICO | AC7: SE ALLEGA INFORME DE CUMPLIMIENTO POR PARTE DE LA DRA LUZ ELENA RODIRGUEZ ALLEGANDO INFORME DEL IDU A LA SENTENCIA. MEDIANTE DECRETO 818 DE 26/12/2020 SE ARTICULA EL CUMPLIMEINTO DEL FALLO JUDICIAL, el dia 3 de junio de 2022 se instala la Comisión para el goce de un ambiente sano, la salubridad pública en la ronda hídrica del río Tunjuelo., se radica por parte de la Alcaldia Local de kennedy informe de cumplimiento al juzgado de conocimiento el 24-06-2022. 13-4-2023 reunion del comite intersectorial. El 17 mayo de 2024 se remtio informe a la SJD sobre las actuaciones años 2022 a 2024. Mesa de trabajo 24-5-2024 se informa por parte de gobierno como lideres de la comision para el dia 14 junio de 2023 presencial. el enlace de gobierno es:alfonso.moreno@gobiernobogota.gov.co | AD7: CON FALLO | AE7: SGIEP | AF7: CUMPLIIMIENTO FALLO
A8: 10886 | B8: CONSTITUCIONAL | C8: 2002-00152 | D8: ACCION POPULAR | E8: 37245 | F8: CONSEJO DE ESTADO - SECCION PRIMERA | G8: SHIRLEY AVELLANEDA PEÑA | H8: JOSE YAMID SANMIGUEL | I8: ALCALDIA MAYOR - CVP - IDIGER - EAAB | J8: INDIRECTA | K8: COMITÉ | L8: GAVILANES | M8: NA | N8: RECUPERACION RONDA Y ZAMPA | O8: SANTA CECILIA - SANTA RITA - SAN PEDRO - BERLIN - BILBAO - TIBABUYES OCCIDENTAL - TIBABUYES II | P8: NA | Q8: NA | R8: RONDA - ZAMPA | S8: 2875 - 468 - 2427 - 2969 - 1373 - 2835 - 3439 - 1605 - 2875 | T8: SUBA | U8: NA | V8: NA | W8: NA | X8: NA | Y8: NA | Z8: 37971 | AA8: 38883 | AB8: ACOMPAÑAMIENTO RECUPERACION ESPACIO PUBLICO | AC8: MEDIANTE LA RESOLUCION 306 DEL 06-10-2006, INVOLUCRA PARA EL CUMPLIMIENTO DEL FALLO EMPRESA DE ACUEDUCTO Y ALCANTARILLADO DE BOGOTÁ EAAB E.S.P., CAJA DE VIVIENDA POPULAR, IDIGER, SECRETARIA DE GOBIERNO - ALCALDIA LOCAL DE SUBA, DADEP, SECRETARIA DISTRITAL DE AMBIENTE. MEDIANTE RADICADO 20222030023983 LA SRI INFORME LAS ACTUACIONES ADELANTADAS PRA DAR CUMPLIMIENTO AL FALLO. MEDIANTE RADICADO 2022030043441 DEL 05-04-2022 SE SOLICITO A LA SDP DEFINIR COPMO SE ENCUENTRA DEFINIDO EN EL DECRERO DISTRITAL 555 DE 2021, EL SUELO DE PROTECCIÒN Y ESPACIO PÚBLIOCO DE LOS DESARROLLOS LEGALIZADOS. MEDIANTE EL RADICADO 20222030004331 DEL 05-04-2022 SE SOLICITO A LA CAJA DE VIVIENDA POPULAR INFORMAR EL ESTADO DE LA TRASNFERENCIA DE LOS 46 PREDIOS VIABILIZADOS DE ACUERDO CON LA RESPUESTA DADA AL DADEP MEDIANTE EL RADICADO 20182030157311 DEL 03-12-2018, DONDE SE SOLICITO QUE SE ENVIARAN LOS INSUMOS TÈCNICOS JURIDIDOS, CARTOGRAFICOS, RESOLUCIONES Y DEMAS SOPORTES DE LOS PREDIOS QUE HAN ADQUIRIDO PARA REALIZAR EL ANALISIS Y DETERMINAR LA TRASNFERENCIA A FAVOR DEL DISTRITO CAPITAL PARA AVANZAR CON EL CUMPLIMIENTO DEL FALLO JUDICIAL. Mediante orfeo 20221100141531 de 12 de septiembre de 2022 se reporta a la SJD que a la fecha no se está a la espera de la remisión de insumos técnicos, jurídicos, cartográficos por parte de la SECRETARIA DISTRITAL DE PLANEACIÓN Y LA CAJA DE VIVIENDA POPULAR para realizar la transferencia a favor del Distrito Capital. 15-02-2024 SOLICITUD DE INFORME SJD ESTADO DE AVANCE CUMPLIMIENTO DE FALLO SE SOLICITO A LA SRI | AD8: CON FALLO | AE8: SRI | AF8: CUMPLIMIENTO FALLO
A9: 12622 | B9: CONSTITUCIONAL | C9: 2003-00035 | D9: ACCION POPULAR | E9: 37672 | F9: TRIBUNAL ADMINISTRATIVO DE CUNDINAMARCA - SECCION CUARTA - SUBSECCION A | G9: MARIA FERNANDA MADIEDO SANCHEZ | H9: LIGIA ELENA PINTO DE MURCIA Y OTROS | I9: ALCALDIA MAYOR - PLANEACION - SEC GOBIERNO - ALCALDIA LOCAL DE CIUDAD BOLIVAR - IDIGER | J9: INDIRECTA | K9: COMITÉ | L9: TRIGAL DEL SUR INCORPORACION SUELO DE PROTECCION | M9: NA | N9: REMOCION EN MASA INCORPORACION COMO SUELO DE PROTECCION | O9: TRIGAL DEL SUR | P9: NA | Q9: NA | R9: REMOCION EN MASA | S9: 2925 | T9: CIUDAD BOLIVAR | U9: 10465 | V9: NA | W9: NA | X9: NA | Y9: NA | Z9: 38408 | AA9: 40143 | AB9: ACOMPAÑAMIENTO RECUPERACION ESPACIO PUBLICO - INCORPORACION PREDIOS | AC9: SEGUIMIENTO AL CUMPLIMIENTO DEL FALLO - SE SEGUIRÁ ASISTIENDO A MESAS DE TRABAJO QUE SE CONVOQUEN PARA EL EFECTO. Oficio de fecha 7-6-2022 SDP por medio del cual se recomienda a la SJD orientar la estrategia para que los pagos por reasentamientos ya realizados dieran la posibilidad de la transferencia del derecho de dominio al Distrito de aquellos predios de propiedad de las familias reasentadas. Esa gestión permitiría dar aplicación a lo establecido en el artículo 34 del Decreto Distrital 555 de 2022. El 5 de marzo de 2024 se elabora oficio con destino a la CVP solicitando los insumos juridicos para proceder con la incorporacion del suelo de proteccion y de espacio publico en los predios, por otro lado se fija or parte de la Secretaria juridica distrital fecha de mesa de trabajo el 2 de Mayo de 2024. Por otro lado se solicita por parte de la SJD para el dia 17 de abril de 2024 los informes de las acciones realizadas para el cumplimiento del fallo. | AD9: CON FALLO | AE9: SRI | AF9: CUMPLIIMIENTO FALLO
A10: 54949 | B10: CONSTITUCIONAL | C10: 2003-02010 | D10: ACCION POPULAR | E10: 37930 | F10: TRIBUNAL ADMINISTRATIVO DE CUNDINAMARCA - SECCION SEGUNDA - SUBSECCION A | G10: SHIRLEY AVELLANEDA PEÑA | H10: JAC URBANIZACION GILMAR | I10: DADEP - SEC GOBIERNO - ALCALDIA LOCAL DE SUBA | J10: INDIRECTA | K10: DEMANDADO | L10: URBANIZACIÒN GILMAR | M10: NA | N10: ENTREGA DE ZONAS DE CESION | O10: CALLE 164 CON CARRERA 56 B | P10: NA | Q10: NA | R10: CESION | S10: 3363 | T10: SUBA | U10: 544.56 | V10: NA | W10: NA | X10: NA | Y10: NA | Z10: 38183 | AA10: NA | AB10: RECIBIR | AC10: SEGUIMIENTO MESA DE TRABAJO ALCALDÍA LOCAL SUBA PARA EVENTUAL COMPENSACIÓN ZONA VERDE E INTERVENCIÓN VIA PÚBLICA IDU. PARA ARCHIVO | AD10: CON FALLO | AE10: SRI | AF10: CUMPLIIMIENTO FALLO
A11: 10886 | B11: CONSTITUCIONAL | C11: 2003-02530 | D11: ACCION POPULAR | E11: 2 | F11: TRIBUNAL ADMINISTRATIVO DE CUNDINAMARCA - SECCION CUARTA | G11: SHIRLEY AVELLANEDA PEÑA | H11: ROBERTO RAMIREZ ROJAS | I11: ALCALDIA LOCAL DE SANTAFE | J11: INDIRECTA | K11: COMITÉ | L11: VENDEDORES ESPACIO PUBLICO CARRERA 7 DESDE PALACIO NARIÑO HASTA CALLE 24 - EJES VIALES | M11: NA | N11: VENDEDORES ESPACIO PUBLICO CARRERA 7 DESDE PALACIO NARIÑO HASTA CALLE 24 - EJES VIALES | O11: NA | P11: NA | Q11: NA | R11: BIEN DE USO PUBLICO DE NO CESION | S11: NA | T11: SANTAFE | U11: NA | V11: NA | W11: NA | X11: NA | Y11: NA | Z11: 39759 | AA11: 40941 | AB11: INTEGRA COMITÉ DE VERIFICACION CUMPLIMIENTO FALLO | AC11: A) AMPÁRASE EL DERECHO COLECTIVO AL GOCE Y DISFRUTE DEL ESPACIO PÚBLICO, AFECTADO POR LAS VENTAS INFORMALES DE VENDEDORES ESTACIONARIOS, SEMI-ESTACIONARIOS Y AMBULANTES, UBICADOS EN LAS CALLES Y ANDENES DE I) LA CALLE 19, ENTRE CARRERAS 3A Y 15; II) LA CALLE 14, ENTRE CARRERAS 5A Y 10 A • III) LA CARRERA LOA ENTRE CALLES LOA Y 20; IV) DECRETO 098 DE 2004 PARA DAR CUMPLIMIENTO AL FALLO. DADEP REALIZA SEGUIMENTO AL CUMPLIMIENTO DEL FALLLO - DADEP NO TIENE ORDEN ESPECIFICA - APOYA OPERATIVOS - AUTO FIJA FECHA 2003-002530 FIJA AUDIENCIA 13 DE OCTUBRE DE 2022 A LAS 9:00 A.M. AUTO 11 DE OCTUBRE DE 2022 REPROGRAMA AUDIENCIA DE VERIFICACION FALLO PARA EL 31 DE OCTUBRE DE 2022. AUDIENCIA DE INSPECCION JUDICIAL PROGRAMADA PARA EL 22-02-2024 SUSPENDIDA POR ORDEN PUBLICO. 21-02-2024 AUTO FIJA FECHA AUDIENCIA 07-05-2024. auto del 06-05-2024 reprograma audiencia para el 17-05-2024. | AD11: CON FALLO | AE11: SGI | AF11: CUMPLIMIENTO DE FALLO
A12: 52051 | B12: CONSTITUCIONAL | C12: 2004-00702 | D12: ACCION POPULAR | E12: 38090 | F12: TRIBUNAL ADMINISTRATIVO DE CUNDINAMARCA | G12: MARIA FERNANDA MADIEDO SANCHEZ | H12: MARY LUZ MARTINEZ CRUZ | I12: ALCALDIA MAYOR - SEC GOBIERNO - DADEP - ALCALDIA LOCAL DE KENNEDY | J12: INDIRECTA | K12: DEMANDADO | L12: INVASION ESPACIO PUBLICO | M12: NA | N12: CERRAMIENTO REJA METALICA Y CASETA VIGILANCIA | O12: AMERICAS SECTOR AVENIDA GALAN | P12: NA | Q12: NA | R12: CESION | S12: 2232 | T12: KENNEDY | U12: 1516.82 | V12: NA | W12: NA | X12: NA | Y12: NA | Z12: 38743 | AA12: 40276 | AB12: COMITÉ | AC12: OPERATIVO DE 03 DE OCTUBRE DE 2017 RETIRA CERRAMIENTOS Y SE SUPERAN HECHOS DEMANDA - SE PROCEDERÁ A INFORMAR JUZGADO SOLICITANDO ARCHIVO. EL 24 DE OCTUBRE DE 2018 SE REMITE INFORME DE CUMLIMIENTO DEL FALLO. SE REGISTRA Revisión procesos rama judicial: desde 18 de dic 18 DEVUELTA DEL DESPACHO PARA ARCHIVAR | AD12: CON FALLO | AE12: SGIEP | AF12: CUMPLIIMIENTO FALLO - PARA SOLICITAR ARCHIVO
A13: 51123 | B13: CONSTITUCIONAL | C13: 2005-00662 | D13: ACCION POPULAR | E13: 38464 | F13: TRIBUNAL ADMINISTRATIVO DE CUNDINAMARCA - SECCION SEGUNDA - SUBSECCION B | G13: MARIA FERNANDA MADIEDO SANCHEZ | H13: SONIA ANDREA RAMIREZ LAMY | I13: SDP - DAMA - SEC GOBIERNO - ALCALDIA LOCAL DE KENNEDY | J13: INDIRECTA | K13: DEMANDADO | L13: CERROS ORIENTALES | M13: NA | N13: PROTECCION DE CERROS ORIENTALES | O13: NA | P13: NA | Q13: NA | R13: CERRO ORIENTAL | S13: NA | T13: CHAPINERO | U13: NA | V13: NA | W13: NA | X13: NA | Y13: NA | Z13: 38989 | AA13: 41583 | AB13: SIN ORDEN | AC13: SEGUIMIENTO- Audiencia de verificacion de fallo 20-10-2022, requerimiento incidente de desacato de fecha 3-5-2023, se verifican las ordenes las cuales van dirigidas a la CAR para que en el término de un mes contando a partir de la notificación de esta decisión, para que allegue informe ante el Despacho, en aras de verificar la ejecución de la medida preventiva, que con acierto y en cumplimiento de sus funciones, impuso en contra de la SOCIEDAD LUNA BRILLANTELU Y CIA S.C.A y el señor JUAN DIEGO LÓPEZ ARANGO, asi como al EEABB. AUTO DE FECHA 22 DE ABRIL DE 2024 determinaciones a otras entidades y no al DADEP. La Subdirección de Gestión Inmobiliaria y de Espacio Público de esta Defensoría, efectuara el acompañamiento a las Inspecciones de Policía y Alcaldías Locales en las tareas de restitución para los predios localizados en AOPP, e incorporados en el inventario de esta Defensoría que presentan ocupaciones ilegales. AUTO DE FECHA 5 junio de 2024 conmina. Auto de 29-10-2024 Audiencia de verificacion AP 2005-00662 8 AM | AD13: CON FALLO | AE13: SRI-SGIEP | AF13: SEGUIMIENTO
A14: 188832 | B14: CONSTITUCIONAL | C14: 2006-00096 | D14: ACCION POPULAR | E14: 39020 | F14: JUZGADO 25 ADMINISTRATIVO | G14: SHIRLEY AVELLANEDA PEÑA | H14: JORGE ARTURO SALAMANCA FERNANDEZ | I14: ALCALDIA MAYOR DE BOGOTA - DADEP - IDRD - SEC GOBIERNO - ALCALDIA LOCAL BARRIOS UNIDOS | J14: INDIRECTA | K14: DEMANDADO | L14: CONJUNTO RESIDENCIAL ALTAVISTA | M14: NA | N14: ENTREGA DE ZONAS DE CESION | O14: CONJUNTO RESIDENCIAL ALTAVISTA | P14: NA | Q14: NA | R14: VERDE | S14: 2721 | T14: BARRIOS UNIDOS | U14: 2380.39 | V14: NA | W14: NA | X14: NA | Y14: NA | Z14: 40116 | AA14: 40808 | AB14: PLAN DE ACCION ALCALDIA MAYOR | AC14: TENIENDO EN CUENTA EL ACTA DE TOMA DE POSESIÓN NO. 056 DE FECHA 17 DE SEPTIEMBRE DE 2015, EL PLANO URBANÍSTICO DEFINITIVO CU2-BU 15/4-02 Y LA RESOLUCIÓN DE APROBACIÓN URBANÍSTICA NO. RES 03-2-0014 DEL 23 DE ENERO DE 2003, PARA DAR CUMPLIMIENTO AL FALLO SE HAN REALIZADO ACTUACIONES POR PARTE DE LA SIR MEDIANTE LOS RADICADOS 20202030058921 DEL 10-06-2020 DIRIGIDO A LA FIDUCARIA DAVIVIENDA SOLICITANDO SI PRETENDEN CONTINUAR CON EL TRÁMITE DE TRANSFERENCIA Y TITULACIÓN DE LAS ZONAS DE CESIÓN OBLIGATORIAS, DEBERÁ SOLICITAR Y TRAMITAR LA MODIFICACIÓN DE LA RESOLUCIÓN MEDIANTE LA CUAL SE APRUEBA EL PROYECTO URBANÍSTICO. SOLICITUD A SRI ESTADO DE ZONAS DE CESION | AD14: CON FALLO | AE14: SRI | AF14: CUMPLIIMIENTO FALLO
A15: 167054 | B15: CONSTITUCIONAL | C15: 2006-00356 | D15: ACCION POPULAR | E15: 38718 | F15: JUZGADO 37 ADMINISTRATIVO DE BOGOTA | G15: MARIA FERNANDA MADIEDO SANCHEZ | H15: EFRAIN FORERO MOLINA | I15: ALCALDIA LOCAL DE KENNEDY - PERSONERIA - IPES - SEC SALUD | J15: INDIRECTA | K15: VINCULADO POR EL DESPACHO | L15: RECUPERACION ESPACIO PUBLICO | M15: NA | N15: VENDEDORES ORDENA INCOPORAR ZONAS DE CESION | O15: TERMINAL PESQUERO | P15: NA | Q15: NA | R15: CESION | S15: 15371008 | T15: KENNEDY | U15: 6033 | V15: NA | W15: NA | X15: NA | Y15: NA | Z15: 40373 | AA15: 40724 | AB15: INCORPORAR LOS PREDIOS DE CESION QUE SE SEÑALAN EN LEVANTAMIENTO TOPOGRAFICO | AC15: SEGUIMIENTO SRI ELABORACIÓN ESCRITURA PÚBLICA PARA LA TITULACIÓN DE LAS ZONAS DE CESIÓN, auto 14 julio de 2022 auto niega incidente , la SRI informa que a la fecha 18-11-2022 se realizó la resitucion de las zonas verdes, de control ambiental y vial contenidas en el plano F-242/1mediante 2 escrituras públicas y ya estan incorporadas las zonas al inventario general de espacio público. se consulta en el VUR y se verifica la titularidad. ORFEO . 20242030021371 DE FECHA 21 -2-2024 SE INFORMA que la urbanizadora transfirió mediante Escritura Pública N° 1864 del 09/07/2013 de la Notaría 61 de Bogotá debidamente registrada, el derecho real de dominio y posesión a favor de Bogotá Distrito Capital de 7 predios. | AD15: CON FALLO | AE15: SRI | AF15: CUMPLIMIENTO FALLO-ARCHIVO
A16: 249292 | B16: CONSTITUCIONAL | C16: 2008-00006 11001333100620080000600 | D16: ACCION POPULAR | E16: 39468 | F16: JUZGADO 6 ADMINISTRATIVO | G16: MARIA FERNANDA MADIEDO SANCHEZ | H16: HENRY JARAMILLO GONZALEZ | I16: DADEP - IDRD - JARDIN BOTANICO - SEC AMBIENTE | J16: INDIRECTA | K16: DEMANDADO | L16: RECUPERACION ESPACIO PUBLICO | M16: NA | N16: PARQUE METROPOLITANO SAN CARLOS INVASION VIVERO | O16: CENTRO URBANO BOSQUE SAN CARLOS - HOSPITAL FUNDACION SAN CARLOS | P16: NA | Q16: NA | R16: CESION | S16: 477-667 | T16: RAFAEL URIBE | U16: 48728.75 | V16: NA | W16: NA | X16: NA | Y16: NA | Z16: 40942 | AA16: 41494 | AB16: RECUPERAR E INCORPORAR ZONAS DE CESION | AC16: MESAS DE TRABAJO CON EL URBANIZADOR PARA LOGRAR CUMPLIMIENTO DEL FALLO. 29 DE NOVIEMBRE SE REMITIÓ INFORME DE VERIFICACIÓN DE FALLO. MEDIANTE AUTO DEL 15 DE FEBRERO DE 2019, EL JUZGADO 6 ADVO SOLICITA A LA FUNDACIÓN INFORME RESPECTO DEL CUMPLIMEINTO DEL FALLO DEL JUZGADO 6 CIVIL DEL CTO SE ALLEGA NFORME A LA SJD EN MARZO DE 2022 POR PARTE DE LA DRA SANDRA CAROLINA LOPEZ VIVEROS- Subdirección de registro Inmobiliario. se consulta la web de la rama el 15-7-2022 recibe memoriales- 14-6-2023 CUADERNO DESACATO *Ingresa el proceso al despacho del señor JUEZ DR. MAYFREN PADILLA TELLEZ, hoy 14 de junio de 2023 - informando que la parte accionante allego solicitud de tramite de desacato con solicitud cautelar. proceso al despacho 5-9-2023. el 29-2-2023 se remite informe al apoderado de SJD, Ingresa al despacho el 20-3-2024. Auto de fecha 7 Mayo de 2024; abstenerse de abrir incidente de desacato, conforme a lo expuesto en la parte motiva del proveido SEGUNDO: Por Secretaria, OFICIESE a la Superintendencia de Notariado y Registro y a la Oficina de Registro de Instrumentos Publicos de Bogota Zona Sur para que informen el estado de la correspondiente actuacion de registro de la Escritura Publica No. 2186 del 27 de diciembre de 2021 otorgada por la Notaria 75 de Bogota, correspondiente a Declaratoria de propiedad Publica de las zonas de cesion Urbanizacion Bosque de San Carlos, la cual fue radicada con el numero 2022-45358. En igual sentido, oficia al juez de la AP 2010-00522 oficiar para que informe el estado de cumplimiento de la AP 2010-00522 por parte de la Fundacion H san Carlos. se radica informe SJD 5 julio de 2024 al despacho sobre espacio de participacion se haran trimestrales. Auto de fecha 8 de agosto de 2024 requiere al dadep para que en el termino de 30 dias rinda informe en el refleje que ha iniciado todos los trámites administrativos y judiciales para la efectiva transferencia y titulación de las zonas de cesión a favor del Distrito Capital, en los términos del punto (i) del ordinal cuarto de la sentencia, so pena de abrir incidente de desacato en su contra. | AD16: CON FALLO | AE16: SRI | AF16: CUMPLIIMIENTO FALLO
A17: 266228 | B17: CONSTITUCIONAL | C17: 2008-00322 | D17: ACCION POPULAR | E17: 39792 | F17: TRIBUNAL ADMINISTRATIVO DE CUNDINAMARCA - SECCIÓN PRIMERA | G17: MAGDA BOLENA ROJAS BALLESTEROS | H17: JARLINS MONTENEGRO SAENZ | I17: ALCALDIA LOCAL DE KENNEDY | J17: INDIRECTA | K17: VINCULADO POR EL DESPACHO | L17: COLEGIO CARVAJAL | M17: NA | N17: ASOCIACION PROVIVIENDA DE TRABAJADORES TIENE COLEGIO CARVAJAL | O17: COLEGIO CARVAJAL | P17: NA | Q17: NA | R17: CESION - LOTE INSTITUCIONAL | S17: 4132 | T17: KENNEDY | U17: 4903 | V17: NA | W17: NA | X17: NA | Y17: NA | Z17: 18/06/2013 | AA17: 42251 | AB17: DECLARATORIA DE PROPIEDAD PUBLICA | AC17: EN CUMPLIMIENTO DEL FALLO - SEGUIMIENTO ACCIONES DE ESCRITURACION . El 20 de mayo de 2022 se solicitó la vinculación y apertura de incidente de desacato en contra de la SNR por no dar cumplimiento a lo dispuesto por el despacho judicial en sentencia ejecutoriada de segunda instancia . 08/02/2023. Sjca solicitó medida cautelar consistente en la SUSPENSIÓN DE LAS ORDENES DADAS EN EL PROCESO DE NULIDAD Y RESTABLECIMIENTO DEL DERECHO 2004-00366, como quiera que son contrarias a las dadas en el medio de control de protección de derechos colectivos 2008-00322 hasta que se resuelvan las acciones adelantadas y por adelantar dentro de estos dos procesos 05/07/2024. Se corrió traslado de la solicitud de medida cautelar. 17/07/2024. Al Despacho sin pronunciamiento | AD17: CON FALLO | AE17: SRI | AF17: CUMPLIMIENTO DE FALLO
A18: 267029 | B18: CONSTITUCIONAL | C18: 2009-00052 | D18: ACCION POPULAR | E18: 39814 | F18: JUZGADO 19 ADMINISTRATIVO | G18: MARIA FERNANDA MADIEDO SANCHEZ | H18: LUIS EDUARDO MARTINEZ GUTIERREZ | I18: ALCALDIA MAYOR - ALCALDIA LOCAL DE KENNEDY - DADEP - IDU - EAAB | J18: INDIRECTA | K18: DEMANDADO | L18: RECUPERACION ESPACIO PUBLICO | M18: NA | N18: RESTITUCION BIENES DE USO PUBLICO RIO FUCHA OCUPADAS POR PARTICULARES - RIO FUCHA - NICOLAS ESGUERRA | O18: ALSACIA | P18: NA | Q18: NA | R18: CESION | S18: 833 | T18: KENNEDY | U18: 22321.75 | V18: NA | W18: NA | X18: NA | Y18: NA | Z18: 41758 | AA18: 41908 | AB18: RECUPERACION INMEDIATA ESPACIO PUBLICO | AC18: SEGUIMIENTO DEL CUMPLIMIENTO DEL FALLO (SE REALIZO MESA DE TRABAJO CITADA POR PARTE DE LA ABOGADA DE LA SECRETARIA JURIDICA DISTRITAL EL 23 DE FEBRERO ED 2022, CON EL FIN DE REVISAR Y ACTUALIZAR LAS ACTIVIDADES QUE SE HAN ADELANTADO PARA EL CUMPLIMIENTO DE LA SENTENCIA, EN LA CUAL SE DEJO COMO COMPROMISOS CITAR MESAS DE TRABAJO CON CAJA DE VIVIENDA POPULAR Y HABITAT PARA INICIOS DEL MES DE MARZO DE 2022). LLEGADA LA FECHA SE LLEVA A CABO MESA DE TRABAJA SE ESTABLECE COMO COMPROMISOS LOS SIGUIENTES: Presentación de un informe en el cual se indique si las familias objeto de reubicación son aptas para los programas que oferta cada Entidad. Hábitat, IDIGER y Caja de Vivienda Popular y Conseguir acta de la mesa Paymes – alcaldía Alcaldía Local de Kennedy. Mesa de trabajo de fecha 14/06/2022. POR STADO DE 23 DE ENERO DE 2023, SE NOTIFCA AUTO DEL 20 DEL MISMO MES Y AÑO, QUE EN SU PARTE RESOLUTIVA SEÑALA: "CONCEDER el término de 10 días contados a partir de la ejecutoria del presente proveído, para que las partes y los particulares, rindan informe escrito final y unificado, que dé cuenta del cumplimiento de la sentencia proferida por el 29 de abril de 2014 y confirmada por el Tribunal Administrativo de Cundinamarca Sección Primera Subsección “C” de Descongestión el 26 de septiembre de 2014. Se asisite a mesa de trabajo el dia 26-5-2023 sin embargo no se establecen compromisos para el DADEP. mesa de trabajo 16-8-2023 sec juridica, memorando de SGIEP 20233000033323 informe actuaciones cumplimiento del fallo. se solicita informe gestiones 20241300016193 de fecha 12-3-2024 a SGIEP. | AD18: CON FALLO | AE18: SGIEP | AF18: CUMPLIMIENTO DE FALLO
A19: 271268 | B19: CONSTITUCIONAL | C19: 2009-00080 | D19: ACCION POPULAR | E19: 39902 | F19: JUZGADO 36 ADMINISTRATIVO DE BOGOTÁ PRIMERA INSTANCIA TRIBUNAL ADMINISTRATIVO DE CUNDINAMARCA SECCION PRIMERA SUBSECCIÓN B | G19: SHIRLEY AVELLANEDA PEÑA | H19: LUIS ORLANDO DELGADILLO AYALA | I19: ALCALDIA MAYOR - DADEP - OTROS | J19: INDIRECTA | K19: DEMANDADO | L19: HACIENDA SAN SIMON | M19: NA | N19: REGISTRO Y ENTREGA DE ZONAS DE CESION | O19: SAN SIMON | P19: NA | Q19: NA | R19: CESION | S19: 1851 | T19: SUBA | U19: 647000 | V19: NA | W19: NA | X19: NA | Y19: NA | Z19: NA | AA19: NA | AB19: NA | AC19: SENTENCIA FAVORABLE 1ª INSTANCIA 2019-09-16. AUTO QUE ADMITE RECURSO DE APELACION 2019-12-13. AUTO QUE DECRETA PRUEBAS 2020-09-03. 2020-11-25 TRASLADO ALEGATOS DE CONCLUSIÓN 2ª INSTANCIA. 2020-11-27. 17-11-2023 PRESENTACIÓN DE ALEGATOS DE CONCLUSIÓN 2ª INSTANCIA. TRASLADO RECURSO DE REPOSICIÓN, INTERPUESTO EN CONTRA DEL AUTO DE FECHA 10 DE NOVIEMBRE DE 2020, SE FIJA FECHA EL 10 DE DICIEMBRE, INICIA TRASLADO 11 DE DICIEMBRE, FINALIZA 15 DE DICIEMBRE DE 2020. EL PROCESO SE ENCUENTRA AL DESPACHO DESDE EL 18 DE ENERO DE 2021, PENDIENTE DE QUE SE RESUELVA EL RECURSO DE REPOSICIÓN INTERPUESTO POR EL APODERADO DE MALUBU S.A. CONTRA EL AUTO NOTIFICADO POR ESTADO DE FECHA 23 DE NOVIEMBRE DE 2020 (AUTO QUE CORRIÓ TRASLADO PARA ALEGAR). 08 Oct 2021 AUTO QUE RESUELVE REPOSICIÓN REPONE AUTO QUE CORRE TRASLADO DE DOCUMENTOS Y CORRE TRASLADO PARA ALEGAR DE CONCLUSIÓN, DECRETA PRUEBA DE OFICIO Y UNA VEZ SE ALLEGUE LA INFORMACIÓN REQUERIDA SE ORDENA CORRER TRASLADO A LAS PARTES DE LA PRUEBA DOCUMENTAL. SOLO SE VISUALIZARÁ CUANDO TODAS LAS FIRMAS ESTEN REALIZADAS. 2021-10-15 ACLARACIÓN DE AUTO. SOLICITANDO SE ACLARE LA FECHA DEL AUTO REQUERIDO EN EL NUMERAL 1 DE LA PARTE RESOLUTIVA DEL AUTO DEL 8 DE OCTUBRE DE 2021, POR PARTE DE LA CONTRALORÍA.25/10/2021. 2022-08-16 AL DESPACHO EL 17-02-2022. AUTO DEL 24-08-2022 CORRE TRASLADO DE PRUEBAS INCORPORADAS. 27-09-2022 DESCORRE TRASLADO DE RESPUESTA DADEP MANIFESTANDO QUE NO SE HA CUMPLIDO LO SOLICITADO POR EL DESPACHO Y SOLICITANDO AL DADEP Y UAECD QUE SUGIERA LA ALTERNATIVA PARA EL CUMPLIMIENTO DEL FALLO, SE DEBE PRONUNCIARSE EN LOS ALEGATOS DE CONCLUSIÓN.26-01-2024 CONTINUA AL DESPACHO PENDIENTE SENTENCIA. | AD19: EN CURSO | AE19: SRI | AF19: SEGUNDA INSTANCIA
A20: 285457 | B20: CONSTITUCIONAL | C20: 2009-00257 | D20: ACCION POPULAR | E20: 39814 | F20: JUZGADO 13 ADMMINISTRATIVO | G20: MARIA FERNANDA MADIEDO SANCHEZ | H20: ENRIQUE LEON CARDENAS | I20: ALCALDIA MAYOR - ALCALDIA LOCAL DE KENNEDY - DADEP - SEC SALUD - SEC AMBIENTE - SEC MOVILIDAD | J20: INDIRECTA | K20: DEMANDADO | L20: RECUPERACION ESPACIO PUBLICO | M20: NA | N20: RECUPERACION ESPACIO PUBLICO BARRIO MARIA PAZ | O20: MARIA PAZ | P20: NA | Q20: NA | R20: VIAS - ANDENES | S20: 2755 | T20: KENNEDY | U20: 77857.53 | V20: NA | W20: NA | X20: NA | Y20: NA | Z20: 40822 | AA20: NA | AB20: RECUPERAR ESPACIO PUBLICO | AC20: Se realiza audiencia de verificación de cumplimiento de fallo el día 28 de febrero de 2022, posteriormente se realiza otra audiencia de verificación de cumplimiento de fallo el 28 de junio de 2022, a las 9:00 am, septiembre 27 de 2022 notifica por estado auto que auto decide solicitudes y fija fecha para audiencia de inspección judicial para diciembre 2 de 2022 a las 8:00 a.m. se interpone recurso de reposición contra auto el 26 de septiembre de 2022, noviembre 08 de 2022 fija en lista traslado de 3 días del recurso de reposición propuesto por Bogotá D.C. EL DIA 2 DE DICIEMBRE DE 2022, SE REALIZÓ INSPECCION JUDICIAL EN LE BARRIO MARIA PAZ, DE ACUERDO CON LO ORDENADO EN AUTO DE 26 DE SEPTEMBRE DE 2022. el 23-02-2023 se allega al despacho informe de gestion unificadas por parte de la Apoderada de la SJD. El 30-3-2023 ingresa el proceso al despacho por solicitud de incidente de de desacato. el proceso ingreso al despacho el 30-3-2023 , se revisa la web de la rama y se registra como ultima actuacion la recepcion de memoriales el 11 de abril de 2023 por parte de EMRS ALLEGÓ SOLICITUD EL 17-3-2023. Mediante auto de fecha 14 DE ABRIL DE 2023 el despacho requiere informe informe para el 31 de Mayo de 2023, a su vez de acuerdo a la conformacion de las mesas de trabajo de fija como fecha 30-6-2023 y 1-9-2023 para la asistencia del DADEP. DADEP participa en MEGATOMA el 14-12-2023. se radica informe de las 3 comisiones al juzgado por parte del apoderado de SJD el dia 2 de febrero de 2024. Reunion 12-3-2024 se programaran reuniones todos los ultimos jueves de cada mes se hara mesas de trabajo, se debe programar recorrido segun oficio concejo 01 de marzo de 2024. auto de fecha 8 Mayo de 2024 ADICIONAR el auto admisorio del incidente de desacato, de 4 de septiembre de 2023 la vinculacion de la directora Lucia bastidas, se da traslado por termino de 3 dias para pronunciarse sobre hechos nuevos, y adicionalmente se ordena inspeccion judicial 14 de junio, 16 de agosto y 4 septiembre a los lideres de cada comision. AL DESPACHO 21-5-2024 COM RECURSO REPOSICION PARCIAL AUTO 8 MAYO DE 2024. se apoyo en la megatoma el dia 13 de agosto de 2024 con 25 defensores de espacio publico. inspeccion judicial 18 octubre de 2024 Auto de fecha 6 de Noviembre de 2024 auto PRIMERO.- REQUERIR a la Personería de Bogotá, para que como lo hizo en diciembre de 2022, conforme consta en memorial a folios 7603 y ss. del expediente; de ser posible, aporte registros fotográficos y videos con tecnología DRON, que permitan verificar hora y fecha de su producción; en los que se evidencie las condiciones actuales del sector del Barrio María Paz; de cinco (5) fechas y horas tomadas de manera aleatoria. Recurso de reposicion apoderado DC contra auto de fecha 6 noviembre e 2024. proxima megatoma 28 Noviembre de 2024. auto 12 de diciembre de 2024 resuelve SEGUNDO.- ACCEDER para que Bogotá, D.C. - Sector Central, y las demás entidades de todos los órdenes y niveles, e intervinientes en esta acción popular, dentro del mes siguiente a la notificación de esta providencia, aporten registros fotográficos, y de video que evidencien las condiciones actuales del Barrio María Paz, de cinco (5) fechas y horas aleatorias, donde se pueda evidenciar la dirección, fecha y hora de su producción, y las remitan al expediente en el citado término. 14-01-2025 SJD radica fotografias del DC. , 20 Enero de 2025 Personeria allega material fotografico. | AD20: CON FALLO | AE20: SGIEP | AF20: CUMPLIMIENTO DE FALLO
A21: 324636 | B21: CONSTITUCIONAL | C21: 2010-00116 | D21: ACCION POPULAR | E21: 40395 | F21: JUZGADO 43 ADMINISTRATIVO SECCION CUARTA | G21: SHIRLEY AVELLANEDA PEÑA | H21: NELSON ENRIQUE SAENZ | I21: ALCALDIA MAYOR - ALCALDIA LOCAL DE BOSA - DADEP - TECNI INTEGRAL - SUDEIN LTDA | J21: INDIRECTA | K21: DEMANDADO | L21: INVASION ESPACIO PUBLICO ANDEN TECNI INTEGRAL SUDEIN | M21: NA | N21: INVASION ESPACIO PUBLICO ANDEN TECNI INTEGRAL SUDEIN | O21: TECNI INTEGRAL Y SUDEIN | P21: NA | Q21: NA | R21: BIEN DE USO PUBLICO DE NO CESION | S21: 2607 | T21: BOSA | U21: 131 | V21: NA | W21: NA | X21: NA | Y21: NA | Z21: 40966 | AA21: NA | AB21: SIN ORDENES AL DADEP - EXHORTA ALCALDIA LOCAL DE BOSA | AC21: SEGUIMIENTO AL CUMPLIMIENTO DEL FALLO. 2019-03-19 SIN RECURSO TERMINACIÓN DE PROCESO. | AD21: CON FALLO | AE21: SGI | AF21: EN CUMPLIMIENTO DE FALLO
A22: 332456 | B22: CONSTITUCIONAL | C22: 2010-00164 | D22: ACCION POPULAR | E22: 40458 | F22: JUZGADO 39 ADMINISTRATIVO DE BOGOTÁ | G22: MARIA FERNANDA MADIEDO SANCHEZ | H22: JORGE HUMBERTO VARGAS ROJAS | I22: DISTRITO CAPITAL Y SECRETARIA DISTRITAL DE PLANEACION | J22: INDIRECTA | K22: VINCULADO POR EL DESPACHO | L22: INVASION QUIRINAL | M22: NA | N22: CAMBIO DE USO DE VIA VEHICULAR A PARQUE | O22: PABLO SEXTO | P22: NA | Q22: NA | R22: VIA VEHICULAR | S22: 175-75 | T22: TEUSAQUILLO | U22: 2605.63 | V22: NA | W22: NA | X22: NA | Y22: NA | Z22: 40752 | AA22: 41431 | AB22: COORDINAR CON LA SDP LA MODIFICACION DE PLANOS URBANIZTICOS POR CAMBIO DE USO DEL SUELO | AC22: SEGUIMIENTO AL CUMPLIMIENTO DEL FALLO se llevo mesa de trabajo de fecha 14/7/2022 a cargo de la SJD. mesa de trabajo 19-5-2023, MESA DE TRABAJO 22 de noviembre de 2023, con el fin de revisar y actualizar las actividades que se han adelantado para el cumplimiento de la sentencia proferida por el Juzgado Treinta y Nueve (39) Administrativo de Descongestión del Circuito de Bogotá de fecha 28 de julio de 2011, modificada parcialmente por el Tribunal Administrativo de Cundinamarca Sección Primera Subsección “A” el 6 de junio de 2013. 23-10-2024 POR PARTE DE SJD SE SOLICITO INFORME A LA ALCALDIA. | AD22: CON FALLO | AE22: N/A | AF22: CUMPLIMIENTO DE FALLO
A23: 334871 | B23: CONSTITUCIONAL | C23: 2010-00252 | D23: ACCION POPULAR | E23: 40499 | F23: TRIBUNAL ADMINISTRATIVO - DESCONGESTION - SECCION TERCERA | G23: SHIRLEY AVELLANEDA PEÑA | H23: BENJAMIN POLANIA | I23: ALCALDIA LOCAL DE FONTIBON - SEC PLANEACION - SEC GOBIERNO - CURADOR URBANO 2 - CONSTRUCTORA BOLIVAR - URBANIZACION SABANA GRANDE II | J23: INDIRECTA | K23: VINCULADO POR EL DESPACHO | L23: ZONA COMUNAL EN AREAS DE CESION SABANA GRANDE II | M23: NA | N23: ZONA COMUNAL EN AREAS DE CESION SABANA GRANDE II | O23: SABANA GRANDE 1, 2, 3 Y 4 | P23: NA | Q23: NA | R23: DOTACIONAL | S23: 3158 | T23: FONTIBON | U23: NA | V23: NA | W23: NA | X23: NA | Y23: NA | Z23: 41809 | AA23: 41977 | AB23: COMITÉ VERIFICACION CUMPLIMIENTO FALLO | AC23: SEGUIMIENTO CUMPLIMIENTO DE FALLO 100% SOLICITUD DE APODERADA SJD SEGUIMIENTO PRONUNCIAMIENTO DESPACHO FIJAR AUDIENCIA DE VERIFICACIÓN DE FALLO O ARCHIVO. MEDIANTE OFICIO 20224000160312 del 15 de Julio la DEFENSORÍA DEL PUEBLO. 02-08-2022 Cita a Comité de Verificación se realizará el día 5 de agosto de 2022, a las 8.30 a.m. en las instalaciones de la Defensoría del Pueblo- Regional Bogotá, ubicada en la carrera 9 No. 16-21 segundo piso y estará presidido por la Doctora Ana Julia Ortiz Sierra, Defensora Pública adscrita a la Unidad de Defensoría Pública del Programa de Derecho Administrativo de la Regional Bogotá. 2024-04-10 AUTO QUE RESUELVE MEDIANTE AUTO DEL 09 DE ABRIL DE 2024 SE TIENE POR CUMPLIDAS UNAS ÓRDENES, PARCIALMENTE LA SENTENCIA Y REQUIERE PREVIA APERTURA DE INCIDENTE DE DESACATO. | AD23: CON FALLO | AE23: SRI | AF23: CUMPLIMIENTO DE FALLO
A24: 316655 | B24: CONSTITUCIONAL | C24: 2010-00271 | D24: ACCION POPULAR | E24: 40380 | F24: JUZGADO 13 - ADMINISTRATIVO SECCIÓN SEGUNDA | G24: SHIRLEY AVELLANEDA PEÑA | H24: FELIPE ANDRES BERNAL TOVAR | I24: ALCALDIA MAYOR - ALCALDIA LOCAL DE MARTIRES - DADEP - MOVILIDAD | J24: INDIRECTA | K24: DEMANDADO | L24: INVASION VEHICULOS Y MOTOS CALLE 15 ENTRE CARRERA 14 Y 17 | M24: NA | N24: INVASION VEHICULOS Y MOTOS CALLE 15 ENTRE CARRERA 14 Y 17 | O24: LA FAVORITA | P24: NA | Q24: NA | R24: CESION | S24: 2520 | T24: MARTIRES | U24: 400 | V24: NA | W24: NA | X24: NA | Y24: NA | Z24: 42853 | AA24: NA | AB24: NA | AC24: CUMPLIMIENTO DE SENTENCIA 28 DE ABRIL DE 2017, SE HA REALIZADO SEGUIMIENTO DE LAS ORDENES IMPUESTAS PARA PRESERVAR EL ESPACIO PÚBLICO. SE INTERPUSO RECURSO DE APELACIÓIN 2017-06-21. 2017-08-18 AUTO QUE ADMITE RECURSO DE APELACIÓN. 2019-07-23 RESUELVE: PRIMERO. NO SELECCIONAR para revisión la sentencia proferida por el Tribunal Administrativo de Cundinamarca, Sección Primera, Subsección A, el 8 de noviembre de 2018. SEGUNDO. NOTIFICAR la presente providencia, por estado, a las partes y al Ministerio Público. TERCERO. Ejecutoriada esta providencia, DEVOLVER el expediente al tribunal de origen para lo de su cargo. 2019-08-09 AUTO QUE NO SELECCIONA PARA REVISION. 2021-10-08 INFORME DADEP. MESAS DE TRABAJO TRIMESTRALES. 2021-11-05 AUTO QUE ORDENA REQUERIR.2021-12-14 AUTO FIJA FECHA DE AUDIENCIA. AUTO DE 11 DE OCTUBRE DE 2022 que ordena: 1. Solicitar a la Procuraduría General de la Nación, Defensoría del Pueblo y Personería de Bogotá rendir los informes requeridos, indicando los avances que se evidencien en el sector del barrio de la Favorita respecto a las actividades adelantadas en el cumplimiento de las órdenes impartidas en el fallo, por parte de las entidades accionadas; y realizar las funciones de verificación y seguimiento en el sector en las oportunidades y tiempos que se consideren necesarios. 2. Fijar el día 22 de noviembre de 2022 a las 9:00 de la mañana, como fecha para realizar audiencia presencial de verificación de cumplimiento de la sentencia proferida dentro de la presente acción popular. 2023-06-24 AUTO QUE ORDENA REQUERIR. 2023-12-19 AUTO INTERLOCUTORIO. Requiere al INSTITUTO PARA LA ECONOMÍA SOCIAL -IPES, a la SECRETARIA DE GOBIERNO - ALCALDÍA LOCAL DE LOS MÁRTIRES y al DEPARTAMENTO ADMINISTRATIVO DE DEFENSORIA DELESPACIO PÚBLICO –DADEP- para que, a más tardar el próximo jueves 18 de enero de 2024, remitan los informes requeridos por el despacho judicial. MARZO 07 DE 2024 NOTIFICA POR ESTADO AUTO QUE FIJA FECHA PARA AUDIENCIA DE VERIFICACIÓN DE CUMPLIMIENTO DE FALLO PARA MARZO 19 DE 2024 A LAS 8:30 A.M. 19-03-2024 ACTA DE AUDIENCIA. 2024-03-22 Se allega evidencia de reunión virtual interinstitucional para coordinación de cumplimiento a orden del despacho proferida en Audiencia del 19/03/2024, relacionada con la elaboración de censo de locales comerciales en sector de La Favorita. MAYO 21 DE 2024 NOTIFICA POR ESTADO AUTO QUE ORDENA REQUERIR A ENTIDADES. 06-06-24 Mesa de trabajo interinstitucional para cumplimiento de sentencia. 12-06-24.Presentación informe al Director Distrital de Gestión judicial. 20-06-24 Mesa de trabajo con el Ministerio público para organizar la entrega del requerimiento judicial a los propietarios de los establecimientos de comercio del barrio la Favorita. JUNIO 28 DE 2024 NOTIFICA POR ESTADO AUTO QUE FIJA FECHA PARA AUDIENCIA DE COMITÉ DE VERIFICACIÓN PARA JULIO 29 DE 2024 A LAS 10:30 A.M. LA CUAL SE LLEVARÁ A CABO DE MANERA PRESENCIAL Y ORDENA LA COMPARECENCIA OBLIGATORIA DE LOS FUNCIONARIOS TITULARES DE LAS ENTIDADES DESCRITAS EN EL PRESENTE AUTO .29-08-2024 AUDIENCIA DE SEGUIMIENTO DE CUMPLIMIENTO FALLO.12-11-2024 Audiencia verificación cumplimiento de fallo profiere auto requiere a SAE, comunicación pronunciamiento predio. 12-12-2024 fija audiencia cumplimiento de fallo, modificada para el 11 de febrero de 2025. Reunión SAE 12 DE DICIEMBRE DE 2024 | AD24: CON FALLO | AE24: SGI | AF24: CUMPLIMIENTO FALLO
A25: 33157 | B25: CONSTITUCIONAL | C25: 2010-00404 11001333101020100040400 | D25: ACCION POPULAR | E25: 40491 | F25: JUZGADO 10 - ADMINISTRATIVO SECCIÓN SEGUNDA | G25: MARIA FERNANDA MADIEDO SANCHEZ | H25: VEEDURIA PAIS TRANSPARENTE | I25: DISTRITO CAPITAL - ALCALDIA LOCAL DE KENNEDY - DADEP | J25: INDIRECTA | K25: DEMANDADO | L25: RECUPERACION ESPACIO PUBLICO | M25: NA | N25: INVASION ESPACIO PUBLICO AV BOYACA CALLE PRIMERA Y SEGUNDA SUR HASTA CARRERA 71D | O25: NA | P25: NA | Q25: NA | R25: ZONA DE CESION | S25: 2232-18 | T25: KENNEDY | U25: NA | V25: NA | W25: NA | X25: NA | Y25: NA | Z25: NA | AA25: NA | AB25: NA | AC25: Audiencia de pacto de cumplimiento llevada a cabo el día 06 de abril de 2022, Ante la falta de ánimo conciliatorio y la inasistencia de la totalidad de las partes interesadas, se declara fallida, Se emite respuesta con Radicado DADEP No. 20221100182571 de 17/11/22 al auto de pruebas de 03/11/22, donde se solicita prueba de oficio. Mediante auto de fecha 2 de marzo de 2023 se pone en conocimiento ( POR 3 DIAS ) de las demas partes del proceso el informe rendido por SRI del DADEP. AUTO de fecha 15 Junio de 2023 se resuelve: INCORPORAR los documentos allegados por el Jefe de la Oficina Jurídica de la Defensoría del Espacio Público – DADEP y CORRER TRASLADO a las partes y al agente del Ministerio Público por el término de cinco (5) días para que presenten por escrito sus alegatos y concepto respectivo. El 15-6-2023 INCORPORA DOCUMENTOS, CIERRA PERIODO PROBATORIO Y CORRE TRASLADO POR EL TPERMINO DE 5 DÍAS PARA ALEGATOS. al despacho para sentencia 7-5-2023 se revisa proceso el 23-5-2024 ENVIO A OTROS DESPACHOS. admite recurso de apelacion presentado por la parte demandada 13-8-2024. al despacho 18-9-2024 para resolver recurso. | AD25: FALLO | AE25: SGIEP | AF25: RECURSO APELACION
A26: 352556 | B26: CONSTITUCIONAL | C26: 2010-00537 11001333101420100053703 | D26: ACCION POPULAR | E26: 40791 | F26: JUZGADO 14 - ADMINISTRATIVO SECCIÓN SEGUNDA | G26: MARIA FERNANDA MADIEDO SANCHEZ | H26: GLEISON PINEDA | I26: DADEP - SEC GOBIERNO - ALCALDIA LOCAL DE SUBA | J26: INDIRECTA | K26: DEMANDADO | L26: RECUPERACION ESPACIO PUBLICO | M26: NA | N26: INVASION POR CERRAMIENTO ZONA DE CESION RESERVA BOSQUES DE LA COLINA | O26: BOSQUES DE LA COLINA | P26: NA | Q26: NA | R26: CESION | S26: 2022-7 | T26: SUBA | U26: 3.182,00 | V26: NA | W26: NA | X26: NA | Y26: NA | Z26: 14/11/17 | AA26: NA | AB26: RESTITUCIÓN DEL ESPACIO PÚBLICO INFRINGIDO POR LOS PROPIETARIOS DEL PREDIO CON MATRICULA 50N-20358538 | AC26: SEGUIMIENTO PROCESAL - IMPUGNACIÓN: MEDIANTE AUTO DE 9 DE FEBRERO DE 2018 EL TRIBUNAL ADMINISTRATIVO DE CUNDINAMARCA (MP: FREDY IBARRA) ADMITIÍO RECURSO DE APELACIÓN CONTRA EL FALLO IMPUGNADO . EN FIRME PROVIDENCIA DE FECHA 9 DE FEBRERO DE 2018 MEDIANTE LA CUAL SE DISPUSO ADMITIR EL RECURSO DE APELACIÓN PRESENTADO POR EL APODERADO JUDICIAL DEL DISTRITO CAPITAL EN CONTRA DE LA SENTENCIA DE FECHA 14 DE NOVIEMBRE DE 2017 PROFERIDA PRO EL JUZGADO 14 ADMINISTRATIVO ORAL DEL CIRCUITO JUDICIAL DE BOGOTÁ. AL DESPACHO DESDE EL 19/|10/2020 PARA SENTENCIA DE SEGUNDA INSTANCIA . el 8-9-2022 Revoca numeral 3 sentencia primera instancia . Documento firmado electrónicamente por:CESAR GIOVANNI CHAPARRO RINCON, Moises Rodrigo Mazabel Pinzon, Oscar Armando Dimate Cardenas. el 12-3-2024 mediante orfeo 20241300016033 memorando a SGIEP solicitando informacion sobre las actuaciones para el cumplimiento del fallo. Mediante orfeo 20243000018493 de fecha 3-4-2024 SGIEP remite acta de retiro de cierre metalico pendiente que la alcaldia local gestione el permiso de la secretaría de Ambiente concepto y autorización para el retiro de los setos. se recibe alcance informe SGIEP 20243010020053 de abril de 2024. Mediante memorando de fecha 24-5-2024 20243010024513 se remite informacion - auto de fecha 19 junio de 2024 Obedece y cumple, da por terminado proceso y ordena archivo. | AD26: CON FALLO | AE26: SGIEP | AF26: AUTO DE ARCHIVO
A27: 351749 | B27: CONSTITUCIONAL | C27: 2011-0002 | D27: ACCION POPULAR | E27: 40560 | F27: TRIBUNAL CONTENCIOSO ADMINISTRATIVO DE CUNDINAMARCA - SECCIÓN PRIMERA SUBSECCION B | G27: MARIA FERNANDA MADIEDO SANCHEZ | H27: LUIS ALFREDO LOZANO ALGAR | I27: SUPERINTEDENCIA DE NOTARIADO Y REGISTRO - DADEP - UAECD - ALCALDIA LOCAL DE KENNEDY | J27: INDIRECTA | K27: DEMANDADO | L27: RINCON DE LOS ANGELES- LA GLORIA | M27: NA | N27: RESTITUCION ESPACION PUBLICO ADJUDICADO EN REMATE | O27: RINCON DE LOS ANGELES | P27: NA | Q27: NA | R27: BIEN DE USO PUBLICO DE NO CESION | S27: 4875 - 4876 | T27: KENNEDY | U27: 1311 | V27: NA | W27: NA | X27: NA | Y27: NA | Z27: NA | AA27: NA | AB27: NA | AC27: SOLICITUD DE LA DIAN. DESDE EL 24 DE OCTUBRE ENTRA AK DESPACHO CON DICHA SOLICITUD el proceso se encuentra al despacho por memorial presentando por el Sr. Camilo Araque allegando PODER concedido por la Jefe de la Oficina Asesora Jurídica de la Superintendencia de Notariado y Registro desde el 2 de Mayo de 2022. al despacho fecha de ultma consulta 8/8/2022, se profiere fallo de primera instancia de fecha 28 Julio de 2022- en apelacion- Notariado y registro, PLAY PARK Y UAECD apelan. se realizo mesa de trabajo con la SJD y CATASTRO el dia 8 septiembre, se esta a la espera de la decision de una accion de lesividad que cursa en el mismo despacho. EL 23-9-2022 SE RADICA RECURSO DE APELACION -MIN VIVIENDA A LA SENTENCIA 28-7-2022 FAVORABLE AL DADEP. 25-11-2022 constancia secretarial auto de fecha 9-6-2023 Al despacho para pronunciarse sobre apelacion sentencia desde el 29 Junio de 2023. hoy 24-10-2024 el proceso se encuentra al despacho sin novedad. | AD27: CON FALLO | AE27: SRI | AF27: APELACION SENTENCIA
A28: 359511 | B28: CONSTITUCIONAL | C28: 2011-00278 (11001333102820110027800) | D28: ACCION POPULAR | E28: 22/08/11 | F28: JUZGADO 28 - ADMINISTRATIVO SECCIÓN SEGUNDA | G28: MARIA FERNANDA MADIEDO SANCHEZ | H28: PEDRO ELIAS NIÑO | I28: IDU - ALCALDIA LOCAL DE USAQUEN - SEC PLANEACION - DADEP | J28: INDIRECTA | K28: DEMANDADO | L28: NO PROLONGACION CARRERA 15 HOY 7D BARRIO BARRANCAS | M28: NA | N28: NO PROLONGACION CARRERA 15 HOY 7D BARRIO BARRANCAS | O28: NA | P28: NA | Q28: NA | R28: BIEN DE USO PUBLICO DE NO CESION | S28: NA | T28: USAQUEN | U28: NA | V28: NA | W28: NA | X28: NA | Y28: NA | Z28: NA | AA28: NA | AB28: NA | AC28: El 17 de junio de 2022 se corre traslado para presentar alegatos de conclusión los cuales son presentados en oportunidad por conducto de la SJD,fallo de segunda instancia de fecha 4 de otubre de 2023 ordenando modificar los numerales 5° y 7° de la sentencia de primera instancia y adicionando el numeral catorce.9-11-2023 auto obedezcase y cumplase. 12-12- 2023 auto ordene requerir cumplimiento de sentencia. Se realizó reunión interinstitucional de seguimiento en la cual la Secretaría Distrital de Planeación y la Secretaría Distrital del Hábitat se comprometieron a reunirse el 11 de enero para evaluar el cumplimiento del artículo 5º del fallo respecto a iniciar el proceso administrativo de Formalización.De acuerdo con lo anterior, se tiene agendada reunión para el día 6 de febrero de 2024, como quiera que, de acuerdo con lo señalado por la Secretaría Distrital del Hábitat del estudio que se realice por parte del Comité Técnico de Legalización y Formalización Urbanística en reunión de finales de enero se establecerán claridades frente al instrumento urbanístico reseñado por el Juzgado para cumplir con las finalidades de la acción popular. En ese orden de ideas, se tiene agendada reunión para el 6 de febrero fecha en el cual se acordará cronograma. Se asiste a reunion sin embargo se establecen compromisos para la Secretaría Distrital del Hábitat: Estudio de viabilidad, Secretaria Distrital de Planeación y alcaldia local teniendo en cuenta que la ultima orden es para el dadep de recibir las zonas. se asiste a mesa de trabajo en la alcaldia local usaquen el 11-3-2024. EL 11 DE MARZO DE 2024 se radico ante el juzgado viable la aplicación del el concepto no viabilidad de plicacion del instrumento de Regularización/Formalización concepto emitido por SDP. el 12 -3-2024 ingresa al DESPACHO. 24 JUNIO DE 2024 SE REALIZA VISITA A LA ZONA POR PARTE DE LA SRI . Acta de reunion JAC Desarrollo legalizado Barrancas 20244000062322 del 26/03/2024. se remite a SJD y el 27-6-2024 se radica por parte de SJD informe al despacho. el 16-1-2025 auto ordena cumplimiento entidades da 10 dias. se remite informe a SJD orfeo 20251300009381 de fecha 29-1-2025. | AD28: CON FALLO | AE28: SRI | AF28: CUMPLIMIENTO FALLO
